Workbook

Sheet APR
A1: APRIL MONTH RAKE LOADING DATA
A2: SL NO | B2: LOADING DATE | C2: RAKE NO | D2: PRIORTY NUMBER | E2: R.R NUMBER | F2: NO OF WAGON | G2: NET WEIGHT | H2: UNDER LOAD WT | I2: OVER LOAD WT | J2: O/L WAGON | K2: O/L CHARGE | L2: DETENTION HOURS | M2: DETENTION CHARGES | N2: SHUNTING HOURS | O2: SHUNTING CHARGES | P2: PILOT HOURS | Q2: PILOT CHARGES | R2: PCLA | S2: GST 5% | T2: TOTAL AMOUNT RS
A3: 1 | B3: 01.04.20 | C3: 240 | D3: 1 | E3: 141000012 | F3: 59 | G3: 3580.84 | H3: 255.98 | I3: 0 | J3: 1 | K3: 5000 | L3: 1 | M3: 17700 | N3: 0 | Q3: 0 | R3: =K3+M3+Q3 -> 22700 | S3: =R3*5% -> 1135 | T3: =R3+S3 -> 23835
A4: 2 | B4: 01.04.20 | C4: 241 | D4: 2 | E4: 151000006 | F4: 59 | G4: 3577.11 | H4: 257.39 | I4: 0 | J4: 0 | K4: 0 | L4: 0 | M4: 0 | N4: 0 | Q4: 0 | R4: =K4+M4+Q4 -> 0 | S4: =R4*5% -> 0 | T4: =R4+S4 -> 0
A5: 3 | B5: 02.04.20 | C5: 242 | D5: 3 | E5: 161000224 | F5: 59 | G5: 3626.31 | H5: 208.69 | I5: 0 | J5: 0 | K5: 0 | L5: 0 | M5: 0 | N5: 0 | Q5: 0 | R5: =K5+M5+Q5 -> 0 | S5: =R5*5% -> 0 | T5: =R5+S5 -> 0
A6: 4 | B6: 03.04.20 | C6: 243 | D6: 4 | E6: 161000225 | F6: 59 | G6: 3652.42 | H6: 188.62 | I6: 7.04 | J6: 3 | K6: 15000 | L6: 1 | M6: 8850 | N6: 0 | Q6: 0 | R6: =K6+M6+Q6 -> 23850 | S6: =R6*5% -> 1192.5 | T6: =R6+S6 -> 25042.5
A7: 5 | B7: 04.04.20 | C7: 244 | D7: 5 | E7: 161000226 | F7: 59 | G7: 3638.81 | H7: 190.76 | I7: 0.12291667 | J7: 1 | K7: 5000 | L7: 1 | M7: 8850 | N7: 0 | Q7: 0 | R7: =K7+M7+Q7 -> 13850 | S7: =R7*5% -> 692.5 | T7: =R7+S7 -> 14542.5
A8: 6 | B8: 05.04.20 | C8: 245 | D8: 6 | E8: 161000227 | F8: 59 | G8: 3676.01 | H8: 168.62 | I8: 9.63 | J8: 5 | K8: 25000 | L8: 1 | M8: 8850 | N8: 0 | Q8: 0 | R8: =K8+M8+Q8 -> 33850 | S8: =R8*5% -> 1692.5 | T8: =R8+S8 -> 35542.5
E9: TOTAL | F9: =SUM(F3:F8) -> 354 | G9: =SUM(G3:G8) -> 21751.5 | H9: =SUM(H3:H8) -> 1270.06 | I9: 16.79 | J9: =SUM(J3:J8) -> 10 | K9: =SUM(K3:K8) -> 50000 | L9: =SUM(L3:L8) -> 4 | M9: =SUM(M3:M8) -> 44250 | N9: =SUM(N3:N8) -> 0 | Q9: =SUM(Q3:Q8) -> 0 | R9: =SUM(R3:R8) -> 94250 | S9: =R9*5% -> 4712.5 | T9: =SUM(T3:T8) -> 98962.5

Sheet MAY
A1: MAY MONTH RAKE LOADING DATA
A2: SL NO | B2: LOADING DATE | C2: RAKE NO. | D2: PRIORTY NUMBER | E2: R.R NUMBER | F2: NO OF WAGON | G2: NET WEIGHT | H2: UNDER LOAD WT | I2: OVER LOAD WT | J2: O/L WAGON | K2: O/L CHARGE | L2: DETENTION HOURS | M2: DETENTION CHARGES | N2: SHUNTING HOURS | O2: SHUNTING CHARGES | P2: PILOT HOURS | Q2: PILOT CHARGES | R2: PCLA | S2: GST 5% | T2: TOTAL AMOUNT RS
A3: 1 | B3: 05.05.20 | C3: 246 | D3: 7 | E3: 161000228 | F3: 58 | G3: 3616.22 | H3: 150.6 | I3: 5.82 | J3: 3 | K3: 15000 | L3: 1 | M3: 17400 | N3: 0 | Q3: 0 | R3: =K3+M3+Q3 -> 32400 | S3: =R3*5% -> 1620 | T3: =R3+S3 -> 34020
A4: 2 | B4: 06.05.20 | C4: 247 | D4: 8 | E4: 161000229 | F4: 59 | G4: 3665.51 | H4: 175.93 | I4: 6.44 | J4: 4 | K4: 20000 | L4: 1 | M4: 8850 | N4: 0 | Q4: 0 | R4: =K4+M4+Q4 -> 28850 | S4: =R4*5% -> 1442.5 | T4: =R4+S4 -> 30292.5
A5: 3 | B5: 07.05.20 | C5: 248 | D5: 9 | E5: 161000230 | F5: 58 | G5: 3605.24 | H5: 168.27 | I5: 5.51 | J5: 2 | K5: 10000 | L5: 1 | M5: 8850 | N5: 0 | Q5: 0 | R5: =K5+M5+Q5 -> 18850 | S5: =R5*5% -> 942.5 | T5: =R5+S5 -> 19792.5
A6: 4 | B6: 08.05.20 | C6: 249 | D6: 10 | E6: 161000231 | F6: 59 | G6: 3629.81 | H6: 207.63 | I6: 2.44 | J6: 1 | K6: 5000 | L6: 1 | M6: 8850 | N6: 0 | Q6: 0 | R6: =K6+M6+Q6 -> 13850 | S6: =R6*5% -> 692.5 | T6: =R6+S6 -> 14542.5
A7: 5 | B7: 09.05.20 | C7: 250 | D7: 11 | E7: 161000232 | F7: 59 | G7: 3718.04 | H7: 131.46 | I7: 17.5 | J7: 6 | K7: 30000 | L7: 2 | M7: 17700 | N7: 0 | Q7: 0 | R7: =K7+M7+Q7 -> 47700 | S7: =R7*5% -> 2385 | T7: =R7+S7 -> 50085
A8: 6 | B8: 10.05.20 | C8: 251 | D8: 12 | E8: 161000233 | F8: 59 | G8: 3663.03 | H8: 174.63 | I8: 4.66 | J8: 2 | K8: 10000 | L8: 1 | M8: 8850 | N8: 0 | Q8: 0 | R8: =K8+M8+Q8 -> 18850 | S8: =R8*5% -> 942.5 | T8: =R8+S8 -> 19792.5
A9: 7 | B9: 11.05.20 | C9: 252 | D9: 13 | E9: 161000234 | F9: 59 | G9: 3692.01 | H9: 153 | I9: 10.01 | J9: 7 | K9: 35000 | L9: 2 | M9: 17700 | N9: 0 | Q9: 0 | R9: =K9+M9+Q9 -> 52700 | S9: =R9*5% -> 2635 | T9: =R9+S9 -> 55335
A10: 8 | B10: 12.05.20 | C10: 253 | D10: 14 | E10: 161000235 | F10: 57 | G10: 3497.35 | H10: 208.84 | I10: 3.19 | J10: 1 | K10: 5000 | L10: 1 | M10: 8850 | N10: 0 | Q10: 0 | R10: =K10+M10+Q10 -> 13850 | S10: =R10*5% -> 692.5 | T10: =R10+S10 -> 14542.5
A11: 9 | B11: 12.05.20 | C11: 254 | D11: 15 | E11: 161000236 | F11: 58 | G11: 3544.72 | H11: 225.28 | I11: 0 | J11: 0 | K11: 0 | L11: 0 | M11: 0 | N11: 0 | Q11: 0 | R11: =K11+M11+Q11 -> 0 | S11: =R11*5% -> 0 | T11: =R11+S11 -> 0
A12: 10 | B12: 13.05.20 | C12: 255 | D12: 16 | E12: 161000237 | F12: 59 | G12: 3667.02 | H12: 169.64 | I12: 2.66 | J12: 1 | K12: 5000 | L12: 1 | M12: 8850 | N12: 0 | Q12: 0 | R12: =K12+M12+Q12 -> 13850 | S12: =R12*5% -> 692.5 | T12: =R12+S12 -> 14542.5
A13: 11 | B13: 13.05.20 | C13: 256 | D13: 17 | E13: 161000238 | F13: 57 | G13: 3527.54 | H13: 179.81 | I13: 3.35 | J13: 2 | K13: 10000 | L13: 1 | M13: 8850 | N13: 0 | Q13: 0 | R13: =K13+M13+Q13 -> 18850 | S13: =R13*5% -> 942.5 | T13: =R13+S13 -> 19792.5
A14: 12 | B14: 14.05.20 | C14: 257 | D14: 18 | E14: 141000013 | F14: 58 | G14: 3583.83 | H14: 204.37 | I14: 19.2 | J14: 10 | K14: 50000 | L14: 2 | M14: 17400 | N14: 0 | Q14: 0 | R14: =K14+M14+Q14 -> 67400 | S14: =R14*5% -> 3370 | T14: =R14+S14 -> 70770
... A61: 59 | B61: 31.05.20 | C61: 304 | D61: 65 | E61: 161000274 | F61: 57 | G61: 3462.56 | H61: 241.18 | I61: 1.69 | J61: 1 | K61: 5000 | L61: 1 | M61: 8550 | N61: 0 | Q61: 0 | R61: =K61+M61+Q61 -> 13550 | S61: =R61*5% -> 677.5 | T61: =R61+S61 -> 14227.5
E62: TOTAL | G62: =SUM(G3:G61) -> 211501.89 | H62: =SUM(H3:H61) -> 12000.09 | I62: =SUM(I3:I61) -> 335.47 | J62: =SUM(J3:J61) -> 166 | K62: =SUM(K3:K61) -> 830000 | L62: =SUM(L3:L61) -> 58 | M62: =SUM(M3:M61) -> 515700 | N62: =SUM(N3:N61) -> 0 | Q62: =SUM(Q3:Q61) -> 0 | R62: =SUM(R3:R61) -> 1345700 | S62: =SUM(S3:S61) -> 67285 | T62: =SUM(T3:T61) -> 1412985

Sheet JUN
A1: JUNE MONTH RAKE LOADING DATA
A2: SL NO | B2: LOADING DATE | C2: RAKE NO. | D2: PRIORTY NUMBER | E2: R.R NUMBER | F2: NO OF WAGON | G2: NET WEIGHT | H2: UNDER LOAD WT | I2: OVER LOAD WT | J2: O/L WAGON | K2: O/L CHARGE | L2: DETENTION HOURS | M2: DETENTION CHARGES | N2: SHUNTING HOURS | O2: SHUNTING CHARGES | P2: PILOT HOURS | Q2: PILOT CHARGES | R2: PCLA | S2: GST 5% | T2: TOTAL AMOUNT RS
A3: 66 | B3: 01.06.20 | C3: 1 | D3: 66 | E3: 161000275 | F3: 57 | G3: 3468.43 | H3: 236.57 | I3: 0 | J3: 0 | K3: 0 | L3: 0 | M3: 0 | N3: 0 | O3: 0 | P3: 0 | Q3: 0 | R3: =K3+M3+Q3 -> 0 | S3: =R3*5% -> 0 | T3: =R3+S3 -> 0
A4: 67 | B4: 01.06.20 | C4: 2 | D4: 67 | E4: 161000276 | F4: 59 | G4: 3493.51 | H4: 341.49 | I4: 0 | J4: 0 | K4: 0 | L4: 0 | M4: 0 | N4: 0 | O4: 0 | P4: 0 | Q4: 0 | R4: =K4+M4+Q4 -> 0 | S4: =R4*5% -> 0 | T4: =R4+S4 -> 0
A5: 68 | B5: 02.06.20 | C5: 3 | D5: 68 | E5: 161000277 | F5: 58 | G5: 3430.43 | H5: 340.16 | I5: 1.59 | J5: 1 | K5: 5000 | L5: 1 | M5: 8700 | N5: 0 | Q5: 0 | R5: =K5+M5+Q5 -> 13700 | S5: =R5*5% -> 685 | T5: =R5+S5 -> 14385
A6: 69 | B6: 02.06.20 | C6: 4 | D6: 69 | E6: 161000278 | F6: 57 | G6: 3455.96 | H6: 246.73 | I6: 0.69 | J6: 1 | K6: 5000 | L6: 1 | M6: 8550 | N6: 0 | Q6: 0 | R6: =K6+M6+Q6 -> 13550 | S6: =R6*5% -> 677.5 | T6: =R6+S6 -> 14227.5
A7: 70 | B7: 02.06.20 | C7: 5 | D7: 70 | E7: 161000279 | F7: 59 | G7: 3581.21 | H7: 253.79 | I7: 0 | J7: 0 | K7: 0 | L7: 0 | M7: 0 | N7: 0 | Q7: 0 | R7: =K7+M7+Q7 -> 0 | S7: =R7*5% -> 0 | T7: =R7+S7 -> 0
A8: 71 | B8: 02.06.20 | C8: 6 | D8: 71 | E8: 161000280 | F8: 58 | G8: 3426.92 | H8: 340 | I8: 0 | J8: 0 | K8: 0 | L8: 0 | M8: 0 | N8: 0 | Q8: 0 | R8: =K8+M8+Q8 -> 0 | S8: =R8*5% -> 0 | T8: =R8+S8 -> 0
A9: 72 | B9: 03.06.20 | C9: 7 | D9: 72 | E9: 161000281 | F9: 58 | G9: 3315.76 | H9: 322.24 | I9: 0 | J9: 0 | K9: 0 | L9: 0 | M9: 0 | N9: 0 | Q9: 0 | R9: =K9+M9+Q9 -> 0 | S9: =R9*5% -> 0 | T9: =R9+S9 -> 0
A10: 73 | B10: 03.06.20 | C10: 8 | D10: 73 | E10: 161000282 | F10: 58 | G10: 3430.13 | H10: 341.61 | I10: 2.77 | J10: 2 | K10: 10000 | L10: 1 | M10: 8700 | N10: 0 | Q10: 0 | R10: =K10+M10+Q10 -> 18700 | S10: =R10*5% -> 935 | T10: =R10+S10 -> 19635
A11: 74 | B11: 03.06.20 | C11: 9 | D11: 74 | E11: 161000283 | F11: 58 | G11: 3330.12 | H11: 439.5 | I11: 0 | J11: 0 | K11: 0 | L11: 0 | M11: 0 | N11: 0 | Q11: 0 | R11: =K11+M11+Q11 -> 0 | S11: =R11*5% -> 0 | T11: =R11+S11 -> 0
A12: 75 | B12: 04.06.20 | C12: 10 | D12: 75 | E12: 161000284 | F12: 59 | G12: 3455.61 | H12: 379.39 | I12: 0 | J12: 0 | K12: 0 | L12: 0 | M12: 0 | N12: 0 | Q12: 0 | R12: =K12+M12+Q12 -> 0 | S12: =R12*5% -> 0 | T12: =R12+S12 -> 0
A13: 76 | B13: 04.06.20 | C13: 11 | D13: 76 | E13: 161000285 | F13: 58 | G13: 3363.13 | H13: 408.73 | I13: 2.86 | J13: 2 | K13: 10000 | L13: 1 | M13: 8700 | N13: 0 | Q13: 0 | R13: =K13+M13+Q13 -> 18700 | S13: =R13*5% -> 935 | T13: =R13+S13 -> 19635
A14: 77 | B14: 04.06.20 | C14: 12 | D14: 77 | E14: 161000286 | F14: 59 | G14: 3384.12 | H14: 450.87 | I14: 0.99 | J14: 1 | K14: 5000 | L14: 1 | M14: 8850 | N14: 0 | Q14: 0 | R14: =K14+M14+Q14 -> 13850 | S14: =R14*5% -> 692.5 | T14: =R14+S14 -> 14542.5
A15: 78 | B15: 04.06.20 | C15: 13 | D15: 78 | E15: 161000287 | F15: 55 | G15: 3146.57 | H15: 426.43 | I15: 0 | J15: 0 | K15: 0 | L15: 0 | M15: 0 | N15: 0 | Q15: 0 | R15: =K15+M15+Q15 -> 0 | S15: =R15*5% -> 0 | T15: =R15+S15 -> 0
A16: 79 | B16: 05.06.20 | C16: 14 | D16: 79 | E16: 161000288 | F16: 58 | G16: 3385.53 | H16: 386.54 | I16: 3.07 | J16: 2 | K16: 10000 | L16: 1 | M16: 8700 | N16: 0 | Q16: 0 | R16: =K16+M16+Q16 -> 18700 | S16: =R16*5% -> 935 | T16: =R16+S16 -> 19635
... A83: 146 | B83: 28.06.20 | C83: 81 | D83: 146 | E83: 161000355 | F83: 57 | G83: 3409.73 | H83: 296.56 | I83: 1.29 | J83: 1 | K83: 5000 | L83: 1 | M83: 8550 | N83: 0 | Q83: 0 | R83: =K83+M83+Q83 -> 13550 | S83: =R83*5% -> 677.5 | T83: =R83+S83 -> 14227.5
A84: 147 | B84: 28.06.20 | C84: 82 | D84: 147 | E84: 161000356 | F84: 58 | G84: 3496.32 | H84: 273.68 | I84: 0 | J84: 0 | K84: 0 | L84: 0 | M84: 0 | N84: 0 | O84: 0 | P84: 0 | Q84: 0 | R84: =K84+M84+Q84 -> 0 | S84: =R84*5% -> 0 | T84: =R84+S84 -> 0
A85: 148 | B85: 28.06.20 | C85: 83 | D85: 148 | E85: 161000357 | F85: 59 | G85: 3570.13 | H85: 263.27 | I85: 0.4 | J85: 0 | K85: 0 | L85: 0 | M85: 0 | N85: 0 | O85: 0 | P85: 0 | Q85: 0 | R85: =K85+M85+Q85 -> 0 | S85: =R85*5% -> 0 | T85: =R85+S85 -> 0
A86: 149 | B86: 29.06.20 | C86: 84 | D86: 149 | E86: 161000358 | F86: 59 | G86: 3554.42 | H86: 279.58 | I86: 0 | J86: 0 | K86: 0 | L86: 0 | M86: 0 | N86: 0 | O86: 0 | P86: 0 | Q86: 0 | R86: =K86+M86+Q86 -> 0 | S86: =R86*5% -> 0 | T86: =R86+S86 -> 0
A87: 150 | B87: 29.06.20 | C87: 85 | D87: 150 | E87: 161000359 | F87: 59 | G87: 3569.33 | H87: 266.36 | I87: 2.69 | J87: 1 | K87: 5000 | L87: 1 | M87: 8850 | N87: 0 | Q87: 0 | R87: =K87+M87+Q87 -> 13850 | S87: =R87*5% -> 692.5 | T87: =R87+S87 -> 14542.5
A88: 151 | B88: 29.06.20 | C88: 86 | D88: 151 | E88: 161000360 | F88: 59 | G88: 3625.71 | H88: 211.16 | I88: 1.07 | J88: 1 | K88: 5000 | L88: 1 | M88: 8850 | N88: 0 | Q88: 0 | R88: =K88+M88+Q88 -> 13850 | S88: =R88*5% -> 692.5 | T88: =R88+S88 -> 14542.5
A89: 152 | B89: 29.06.20 | C89: 87 | D89: 152 | E89: 161000361 | F89: 58 | G89: 3394.25 | H89: 372.75 | I89: 0 | J89: 0 | K89: 0 | L89: 0 | M89: 0 | N89: 0 | Q89: 0 | R89: =K89+M89+Q89 -> 0 | S89: =R89*5% -> 0 | T89: =R89+S89 -> 0
A90: 153 | B90: 30.06.20 | C90: 88 | D90: 153 | E90: 161000362 | F90: 57 | G90: 3456.33 | H90: 250.15 | I90: 1.4 | J90: 1 | K90: 5000 | L90: 1 | M90: 8550 | N90: 0 | Q90: 0 | R90: =K90+M90+Q90 -> 13550 | S90: =R90*5% -> 677.5 | T90: =R90+S90 -> 14227.5
A91: 154 | B91: 30.06.20 | C91: 89 | D91: 154 | E91: 161000363 | F91: 57 | G91: 3457.64 | H91: 246.36 | I91: 0 | J91: 0 | K91: 0 | L91: 0 | M91: 0 | N91: 0 | O91: 0 | P91: 0 | Q91: 0 | R91: =K91+M91+Q91 -> 0 | S91: =R91*5% -> 0 | T91: =R91+S91 -> 0
A92: 155 | B92: 30.06.20 | C92: 90 | D92: 155 | E92: 161000364 | F92: 59 | G92: 3566.23 | H92: 267.05 | I92: 0.28 | J92: 0 | K92: 0 | L92: 0 | M92: 0 | N92: 0 | O92: 0 | P92: 0 | Q92: 0 | R92: =K92+M92+Q92 -> 0 | S92: =R92*5% -> 0 | T92: =R92+S92 -> 0
A93: 156 | B93: 30.06.20 | C93: 91 | D93: 156 | E93: 161000365 | F93: 58 | G93: 3433.02 | H93: 337.37 | I93: 0.39 | J93: 0 | K93: 0 | L93: 0 | M93: 0 | N93: 0 | O93: 0 | P93: 0 | Q93: 0 | R93: =K93+M93+Q93 -> 0 | S93: =R93*5% -> 0 | T93: =R93+S93 -> 0
E94: TOTAL | F94: =SUM(F3:F93) -> 5315 | G94: =SUM(G3:G93) -> 321122.39 | H94: =SUM(H3:H93) -> 24063.08 | I94: =SUM(I3:I93) -> 286.4 | J94: =SUM(J3:J93) -> 147 | K94: =SUM(K3:K93) -> 735000 | L94: =SUM(L3:L93) -> 53 | M94: =SUM(M3:M93) -> 463200 | ... T94: =SUM(T3:T93) -> 1332135
F95: =G94/C93 -> 3528.8175

Sheet JUL
A1: JULY MONTH RAKE LOADING DATA
A2: SL NO | B2: LOADING DATE | C2: RAKE NO. | D2: PRIORTY NUMBER | E2: R.R NUMBER | F2: NO OF WAGON | G2: NET WEIGHT | H2: UNDER LOAD WT | I2: OVER LOAD WT | J2: O/L WAGON | K2: O/L CHARGE | L2: DETENTION HOURS | M2: DETENTION CHARGES | N2: SHUNTING HOURS | O2: SHUNTING CHARGES | P2: PILOT HOURS | Q2: PILOT CHARGES | R2: PCLA | S2: GST 5% | T2: TOTAL AMOUNT RS
A3: 157 | B3: 01.07.20 | C3: 1 | D3: 157 | E3: 161000366 | F3: 58 | G3: 3474.23 | H3: 237.75 | I3: 0.98 | J3: 0 | K3: 0 | L3: 0 | M3: 0 | N3: 0 | O3: 0 | P3: 0 | Q3: 0 | R3: =K3+M3+Q3 -> 0 | S3: =R3*5% -> 0 | T3: =R3+S3 -> 0
A4: 158 | B4: 01.07.20 | C4: 2 | D4: 158 | E4: 161000367 | F4: 59 | G4: 3536.45 | H4: 237.82 | I4: 2.27 | J4: 0 | K4: 0 | L4: 0 | M4: 0 | N4: 0 | O4: 0 | P4: 0 | Q4: 0 | R4: =K4+M4+Q4 -> 0 | S4: =R4*5% -> 0 | T4: =R4+S4 -> 0
A5: 159 | B5: 02.07.20 | C5: 3 | D5: 159 | E5: 161000368 | F5: 59 | G5: 3507.92 | H5: 267.76 | I5: 0.68 | J5: 0 | K5: 0 | L5: 0 | M5: 0 | N5: 0 | O5: 0 | P5: 0 | Q5: 0 | R5: =K5+M5+Q5 -> 0 | S5: =R5*5% -> 0 | T5: =R5+S5 -> 0
A6: 160 | B6: 02.07.20 | C6: 4 | D6: 160 | E6: 151000012 | F6: 59 | G6: 3486.82 | H6: 294.83 | I6: 6.65 | J6: 2 | K6: 10000 | L6: 1 | M6: 8850 | N6: 0 | Q6: 0 | R6: =K6+M6+Q6 -> 18850 | S6: =R6*5% -> 942.5 | T6: =R6+S6 -> 19792.5
A7: 161 | B7: 02.07.20 | C7: 5 | D7: 161 | E7: 161000369 | F7: 59 | G7: 3479.92 | H7: 301.85 | I7: 6.77 | J7: 1 | K7: 5000 | L7: 1 | M7: 8850 | N7: 0 | Q7: 0 | R7: =K7+M7+Q7 -> 13850 | S7: =R7*5% -> 692.5 | T7: =R7+S7 -> 14542.5
A8: 162 | B8: 03.07.20 | C8: 6 | D8: 162 | E8: 161000370 | F8: 57 | G8: 3441.43 | H8: 209.94 | I8: 3.37 | J8: 1 | K8: 5000 | L8: 1 | M8: 8550 | N8: 0 | Q8: 0 | R8: =K8+M8+Q8 -> 13550 | S8: =R8*5% -> 677.5 | T8: =R8+S8 -> 14227.5
A9: 163 | B9: 03.07.20 | C9: 7 | D9: 163 | E9: 161000371 | F9: 59 | G9: 3512.41 | H9: 265.46 | I9: 1.87 | J9: 0 | K9: 0 | L9: 0 | M9: 0 | N9: 0 | Q9: 0 | R9: =K9+M9+Q9 -> 0 | S9: =R9*5% -> 0 | T9: =R9+S9 -> 0
A10: 164 | B10: 03.07.20 | C10: 8 | D10: 164 | E10: 161000372 | F10: 59 | G10: 3516.11 | H10: 263.36 | I10: 3.47 | J10: 1 | K10: 5000 | L10: 1 | M10: 8850 | N10: 0 | Q10: 0 | R10: =K10+M10+Q10 -> 13850 | S10: =R10*5% -> 692.5 | T10: =R10+S10 -> 14542.5
A11: 165 | B11: 04.07.20 | C11: 9 | D11: 165 | E11: 161000373 | F11: 59 | G11: 3382.12 | H11: 333.06 | I11: 3.18 | J11: 1 | K11: 5000 | L11: 1 | M11: 8700 | N11: 0 | Q11: 0 | R11: =K11+M11+Q11 -> 13700 | S11: =R11*5% -> 685 | T11: =R11+S11 -> 14385
A12: 166 | B12: 04.07.20 | C12: 10 | D12: 166 | E12: 161000374 | F12: 59 | G12: 3488.92 | H12: 286.08 | I12: 0 | J12: 0 | K12: 0 | L12: 0 | M12: 0 | N12: 0 | Q12: 0 | R12: =K12+M12+Q12 -> 0 | S12: =R12*5% -> 0 | T12: =R12+S12 -> 0
A13: 167 | B13: 04.07.20 | C13: 11 | D13: 167 | E13: 161000375 | F13: 59 | G13: 3436.22 | H13: 338.78 | I13: 0 | J13: 0 | K13: 0 | L13: 0 | M13: 0 | N13: 0 | Q13: 0 | R13: =K13+M13+Q13 -> 0 | S13: =R13*5% -> 0 | T13: =R13+S13 -> 0
A14: 168 | B14: 05.07.20 | C14: 12 | D14: 168 | E14: 141000020 | F14: 59 | G14: 3441.61 | H14: 334.39 | I14: 0 | J14: 0 | K14: 0 | L14: 0 | M14: 0 | N14: 0 | Q14: 0 | R14: =K14+M14+Q14 -> 0 | S14: =R14*5% -> 0 | T14: =R14+S14 -> 0
A15: 169 | B15: 05.07.20 | C15: 13 | D15: 169 | E15: 161000376 | F15: 58 | G15: 3340.02 | H15: 371.98 | I15: 0 | J15: 0 | K15: 0 | L15: 0 | M15: 0 | N15: 0 | Q15: 0 | R15: =K15+M15+Q15 -> 0 | S15: =R15*5% -> 0 | T15: =R15+S15 -> 0
A16: 170 | B16: 05.07.20 | C16: 14 | D16: 170 | E16: 161000377 | F16: 57 | G16: 3399.43 | H16: 248.57 | I16: 0 | J16: 0 | K16: 0 | L16: 0 | M16: 0 | N16: 0 | Q16: 0 | R16: =K16+M16+Q16 -> 0 | S16: =R16*5% -> 0 | T16: =R16+S16 -> 0
A17: 171 | B17: 05.07.20 | C17: 15 | D17: 171 | E17: 161000378 | F17: 59 | G17: 3460.22 | H17: 318.36 | I17: 3.58 | J17: 1 | K17: 5000 | L17: 1 | M17: 8850 | N17: 0 | Q17: 0 | R17: =K17+M17+Q17 -> 13850 | S17: =R17*5% -> 692.5 | T17: =R17+S17 -> 14542.5
A18: 172 | B18: 06.07.20 | C18: 16 | D18: 172 | E18: 161000379 | F18: 59 | G18: 3426.42 | H18: 348.58 | I18: 0 | J18: 0 | K18: 0 | L18: 0 | M18: 0 | N18: 0 | O18: 0 | P18: 0 | Q18: 0 | R18: =K18+M18+Q18 -> 0 | S18: =R18*5% -> 0 | T18: =R18+S18 -> 0
A19: 173 | B19: 06.07.20 | C19: 17 | D19: 173 | E19: 141000021 | F19: 59 | G19: 3502.61 | H19: 273.39 | I19: 0 | J19: 0 | K19: 0 | L19: 0 | M19: 0 | N19: 0 | O19: 0 | Q19: 0 | R19: =K19+M19+Q19 -> 0 | S19: =R19*5% -> 0 | T19: =R19+S19 -> 0
A20: 174 | B20: 06.07.20 | C20: 18 | D20: 174 | E20: 151000013 | F20: 58 | G20: 3411.22 | H20: 302.95 | I20: 2.17 | J20: 0 | K20: 0 | L20: 0 | M20: 0 | N20: 0 | O20: 0 | Q20: 0 | R20: =K20+M20+Q20 -> 0 | S20: =R20*5% -> 0 | T20: =R20+S20 -> 0
A21: 175 | B21: 06.07.20 | C21: 19 | D21: 175 | E21: 161000380 | F21: 59 | G21: 3386.21 | H21: 389.79 | I21: 0 | J21: 0 | K21: 0 | L21: 0 | M21: 0 | N21: 0 | O21: 0 | Q21: 0 | R21: =K21+M21+Q21 -> 0 | S21: =R21*5% -> 0 | T21: =R21+S21 -> 0
A22: 176 | B22: 07.07.20 | C22: 20 | D22: 176 | E22: 161000381 | F22: 58 | G22: 3383.63 | H22: 327.37 | I22: 0 | J22: 0 | K22: 0 | L22: 0 | M22: 0 | N22: 0 | O22: 0 | Q22: 0 | R22: =K22+M22+Q22 -> 0 | S22: =R22*5% -> 0 | T22: =R22+S22 -> 0
A23: 177 | B23: 07.07.20 | C23: 21 | D23: 177 | E23: 161000382 | F23: 59 | G23: 3554.01 | H23: 221.99 | I23: 0 | J23: 0 | K23: 0 | L23: 0 | M23: 0 | N23: 0 | O23: 0 | Q23: 0 | R23: =K23+M23+Q23 -> 0 | S23: =R23*5% -> 0 | T23: =R23+S23 -> 0
A24: 178 | B24: 07.07.20 | C24: 22 | D24: 178 | E24: 141000022 | F24: 59 | G24: 3571.61 | H24: 206.38 | I24: 1.99 | J24: 1 | K24: 5000 | L24: 1 | M24: 8850 | N24: 0 | Q24: 0 | R24: =K24+M24+Q24 -> 13850 | S24: =R24*5% -> 692.5 | T24: =R24+S24 -> 14542.5
A25: 179 | B25: 07.07.20 | C25: 23 | D25: 179 | E25: 151000014 | F25: 58 | G25: 3385.82 | H25: 328.36 | I25: 2.18 | J25: 1 | K25: 5000 | L25: 1 | M25: 8700 | N25: 0 | Q25: 0 | R25: =K25+M25+Q25 -> 13700 | S25: =R25*5% -> 685 | T25: =R25+S25 -> 14385
A26: 180 | B26: 08.07.20 | C26: 24 | D26: 180 | E26: 161000383 | F26: 58 | G26: 3528.43 | H26: 198.89 | I26: 16.32 | J26: 4 | K26: 20000 | L26: 1 | M26: 8700 | N26: 0 | Q26: 0 | R26: =K26+M26+Q26 -> 28700 | S26: =R26*5% -> 1435 | T26: =R26+S26 -> 30135
A27: 181 | B27: 08.07.20 | C27: 25 | D27: 181 | E27: 161000384 | F27: 58 | G27: 3525.42 | H27: 195.72 | I27: 9.14 | J27: 3 | K27: 15000 | L27: 1 | M27: 8700 | N27: 0 | Q27: 0 | R27: =K27+M27+Q27 -> 23700 | S27: =R27*5% -> 1185 | T27: =R27+S27 -> 24885
A28: 182 | B28: 08.07.20 | C28: 26 | D28: 182 | E28: 151000015 | F28: 59 | G28: 3615.21 | H28: 170.52 | I28: 9.73 | J28: 3 | K28: 15000 | L28: 1 | M28: 8850 | N28: 0 | Q28: 0 | R28: =K28+M28+Q28 -> 23850 | S28: =R28*5% -> 1192.5 | T28: =R28+S28 -> 25042.5
A29: 183 | B29: 08.07.20 | C29: 27 | D29: 183 | E29: 151000016 | F29: 59 | G29: 3421.02 | H29: 353.98 | I29: 0 | J29: 0 | K29: 0 | L29: 0 | M29: 0 | N29: 0 | Q29: 0 | R29: =K29+M29+Q29 -> 0 | S29: =R29*5% -> 0 | T29: =R29+S29 -> 0
A30: 184 | B30: 09.07.20 | C30: 28 | D30: 184 | E30: 141000023 | F30: 59 | G30: 3437.61 | H30: 338.39 | I30: 0 | J30: 0 | K30: 0 | L30: 0 | M30: 0 | N30: 0 | Q30: 0 | R30: =K30+M30+Q30 -> 0 | S30: =R30*5% -> 0 | T30: =R30+S30 -> 0
A31: 185 | B31: 09.07.20 | C31: 29 | D31: 185 | E31: 141000024 | F31: 59 | G31: 3490.11 | H31: 289.18 | I31: 3.29 | J31: 1 | K31: 5000 | L31: 1 | M31: 8850 | N31: 0 | Q31: 0 | R31: =K31+M31+Q31 -> 13850 | S31: =R31*5% -> 692.5 | T31: =R31+S31 -> 14542.5
A32: 186 | B32: 10.07.20 | C32: 30 | D32: 186 | E32: 161000385 | F32: 59 | G32: 3396.61 | H32: 379.39 | I32: 0 | J32: 0 | K32: 0 | L32: 0 | M32: 0 | N32: 0 | O32: 0 | P32: 0 | Q32: 0 | R32: =K32+M32+Q32 -> 0 | S32: =R32*5% -> 0 | T32: =R32+S32 -> 0
A33: 187 | B33: 10.07.20 | C33: 31 | D33: 187 | E33: 161000386 | F33: 59 | G33: 3508.61 | H33: 268.38 | I33: 0.99 | J33: 0 | K33: 0 | L33: 0 | M33: 0 | N33: 0 | O33: 0 | P33: 0 | Q33: 0 | R33: =K33+M33+Q33 -> 0 | S33: =R33*5% -> 0 | T33: =R33+S33 -> 0
A34: 188 | B34: 10.07.20 | C34: 32 | D34: 188 | E34: 161000387 | F34: 58 | G34: 3423.22 | H34: 292.56 | I34: 3.79 | J34: 1 | K34: 5000 | L34: 1 | M34: 8700 | N34: 0 | Q34: 0 | R34: =K34+M34+Q34 -> 13700 | S34: =R34*5% -> 685 | T34: =R34+S34 -> 14385
A35: 189 | B35: 11.07.20 | C35: 33 | D35: 189 | E35: 141000025 | F35: 58 | G35: 3456.41 | H35: 319.59 | I35: 0 | J35: 0 | K35: 0 | L35: 0 | M35: 0 | N35: 0 | O35: 0 | P35: 0 | Q35: 0 | R35: =K35+M35+Q35 -> 0 | S35: =R35*5% -> 0 | T35: =R35+S35 -> 0
A36: 190 | B36: 12.07.20 | C36: 34 | D36: 190 | E36: 151000017 | F36: 59 | G36: 3501.81 | H36: 274.77 | I36: 0.58 | J36: 0 | K36: 0 | L36: 0 | M36: 0 | N36: 0 | O36: 0 | P36: 0 | Q36: 0 | R36: =K36+M36+Q36 -> 0 | S36: =R36*5% -> 0 | T36: =R36+S36 -> 0
A37: 191 | B37: 13.07.20 | C37: 35 | D37: 191 | E37: 161000388 | F37: 59 | G37: 3456.41 | H37: 319.59 | I37: 0 | J37: 0 | K37: 0 | L37: 0 | M37: 0 | N37: 0 | O37: 0 | P37: 0 | Q37: 0 | R37: =K37+M37+Q37 -> 0 | S37: =R37*5% -> 0 | T37: =R37+S37 -> 0
A38: 192 | B38: 13.07.20 | C38: 36 | D38: 192 | E38: 141000026 | F38: 59 | G38: 3501.61 | H38: 279.36 | I38: 4.97 | J38: 1 | K38: 5000 | L38: 1 | M38: 8850 | N38: 0 | Q38: 0 | R38: =K38+M38+Q38 -> 13850 | S38: =R38*5% -> 692.5 | T38: =R38+S38 -> 14542.5
A39: 193 | B39: 14.07.20 | C39: 37 | D39: 193 | E39: 161000389 | F39: 59 | G39: 3587.22 | H39: 198.14 | I39: 10.36 | J39: 1 | K39: 5000 | L39: 1 | M39: 8850 | N39: 0 | Q39: 0 | R39: =K39+M39+Q39 -> 13850 | S39: =R39*5% -> 692.5 | T39: =R39+S39 -> 14542.5
A40: 194 | B40: 14.07.20 | C40: 38 | D40: 194 | E40: 141000027 | F40: 56 | G40: 3560.24 | H40: 72.6 | I40: 48.84 | J40: 15 | K40: 75000 | L40: 2 | M40: 16800 | N40: 0 | Q40: 0 | R40: =K40+M40+Q40 -> 91800 | S40: =R40*5% -> 4590 | T40: =R40+S40 -> 96390
A41: 195 | B41: 14.07.20 | C41: 39 | D41: 195 | E41: 161000390 | F41: 58 | G41: 3478.21 | H41: 299.78 | I41: 1.99 | J41: 1 | K41: 5000 | L41: 1 | M41: 8850 | N41: 0 | Q41: 0 | R41: =K41+M41+Q41 -> 13850 | S41: =R41*5% -> 692.5 | T41: =R41+S41 -> 14542.5
A42: 196 | B42: 15.07.20 | C42: 40 | D42: 196 | E42: 151000018 | F42: 56 | G42: 3305.04 | H42: 282.33 | I42: 3.37 | J42: 1 | K42: 5000 | L42: 1 | M42: 8400 | N42: 0 | Q42: 0 | R42: =K42+M42+Q42 -> 13400 | S42: =R42*5% -> 670 | T42: =R42+S42 -> 14070
A43: 197 | B43: 15.07.20 | C43: 41 | D43: 197 | E43: 161000391 | F43: 59 | G43: 3562.82 | H43: 213.96 | I43: 0.78 | J43: 0 | K43: 0 | L43: 0 | M43: 0 | N43: 0 | O43: 0 | P43: 0 | Q43: 0 | R43: =K43+M43+Q43 -> 0 | S43: =R43*5% -> 0 | T43: =R43+S43 -> 0
A44: 198 | B44: 15.07.20 | C44: 42 | D44: 198 | E44: 161000392 | F44: 59 | G44: 3495.41 | H44: 280.98 | I44: 0.39 | J44: 0 | K44: 0 | L44: 0 | M44: 0 | N44: 0 | O44: 0 | P44: 0 | Q44: 0 | R44: =K44+M44+Q44 -> 0 | S44: =R44*5% -> 0 | T44: =R44+S44 -> 0
A45: 199 | B45: 16.07.20 | C45: 43 | D45: 199 | E45: 161000393 | F45: 59 | G45: 3481.61 | H45: 296.77 | I45: 2.38 | J45: 1 | K45: 5000 | L45: 1 | M45: 8850 | N45: 0 | Q45: 0 | R45: =K45+M45+Q45 -> 13850 | S45: =R45*5% -> 692.5 | T45: =R45+S45 -> 14542.5
A46: 200 | B46: 16.07.20 | C46: 44 | D46: 200 | E46: 161000394 | F46: 57 | G46: 3434.43 | H46: 213.76 | I46: 0.19 | J46: 0 | K46: 0 | L46: 0 | M46: 0 | N46: 0 | O46: 0 | P46: 0 | Q46: 0 | R46: =K46+M46+Q46 -> 0 | S46: =R46*5% -> 0 | T46: =R46+S46 -> 0
A47: 201 | B47: 16.07.20 | C47: 45 | D47: 201 | E47: 141000028 | F47: 56 | G47: 3370.44 | H47: 213.56 | I47: 0 | J47: 0 | K47: 0 | L47: 0 | M47: 0 | N47: 0 | O47: 0 | P47: 0 | Q47: 0 | R47: =K47+M47+Q47 -> 0 | S47: =R47*5% -> 0 | T47: =R47+S47 -> 0
A48: 202 | B48: 16.07.20 | C48: 46 | D48: 202 | E48: 151000019 | F48: 58 | G48: 3511.83 | H48: 199.37 | I48: 0.2 | J48: 0 | K48: 0 | L48: 0 | M48: 0 | N48: 0 | O48: 0 | P48: 0 | Q48: 0 | R48: =K48+M48+Q48 -> 0 | S48: =R48*5% -> 0 | T48: =R48+S48 -> 0
A49: 203 | B49: 16.07.20 | C49: 47 | D49: 203 | E49: 151000020 | F49: 57 | G49: 3385.63 | H49: 262.96 | I49: 0.59 | J49: 0 | K49: 0 | L49: 0 | M49: 0 | N49: 0 | O49: 0 | P49: 0 | Q49: 0 | R49: =K49+M49+Q49 -> 0 | S49: =R49*5% -> 0 | T49: =R49+S49 -> 0
A50: 204 | B50: 17.07.20 | C50: 48 | D50: 204 | E50: 151000021 | F50: 56 | G50: 3361.24 | H50: 223.55 | I50: 0.79 | J50: 0 | K50: 0 | L50: 0 | M50: 0 | N50: 0 | O50: 0 | P50: 0 | Q50: 0 | R50: =K50+M50+Q50 -> 0 | S50: =R50*5% -> 0 | T50: =R50+S50 -> 0
A51: 205 | B51: 17.07.20 | C51: 49 | D51: 205 | E51: 161000395 | F51: 59 | G51: 3534.41 | H51: 241.59 | I51: 0 | J51: 0 | K51: 0 | L51: 0 | M51: 0 | N51: 0 | O51: 0 | P51: 0 | Q51: 0 | R51: =K51+M51+Q51 -> 0 | S51: =R51*5% -> 0 | T51: =R51+S51 -> 0
A52: 206 | B52: 17.07.20 | C52: 50 | D52: 206 | E52: 161000396 | F52: 59 | G52: 3490.62 | H52: 285.38 | I52: 0 | J52: 0 | K52: 0 | L52: 0 | M52: 0 | N52: 0 | O52: 0 | P52: 0 | Q52: 0 | R52: =K52+M52+Q52 -> 0 | S52: =R52*5% -> 0 | T52: =R52+S52 -> 0
A53: 207 | B53: 17.07.20 | C53: 51 | D53: 207 | E53: 161000397 | F53: 58 | G53: 3457.22 | H53: 258.78 | I53: 0 | J53: 0 | K53: 0 | L53: 0 | M53: 0 | N53: 0 | O53: 0 | P53: 0 | Q53: 0 | R53: =K53+M53+Q53 -> 0 | S53: =R53*5% -> 0 | T53: =R53+S53 -> 0
A54: 208 | B54: 17.07.20 | C54: 52 | D54: 208 | E54: 161000398 | F54: 59 | G54: 3479.01 | H54: 296.99 | I54: 0 | J54: 0 | K54: 0 | L54: 0 | M54: 0 | N54: 0 | O54: 0 | P54: 0 | Q54: 0 | R54: =K54+M54+Q54 -> 0 | S54: =R54*5% -> 0 | T54: =R54+S54 -> 0
A55: 209 | B55: 18.07.20 | C55: 53 | D55: 209 | E55: 161000399 | F55: 59 | G55: 3443.43 | H55: 269.95 | I55: 2.38 | J55: 0 | K55: 0 | L55: 0 | M55: 0 | N55: 0 | O55: 0 | P55: 0 | Q55: 0 | R55: =K55+M55+Q55 -> 0 | S55: =R55*5% -> 0 | T55: =R55+S55 -> 0
A56: 210 | B56: 18.07.20 | C56: 54 | D56: 210 | E56: 141000029 | F56: 59 | G56: 3390.43 | H56: 257.57 | I56: 0 | J56: 0 | K56: 0 | L56: 0 | M56: 0 | N56: 0 | O56: 0 | P56: 0 | Q56: 0 | R56: =K56+M56+Q56 -> 0 | S56: =R56*5% -> 0 | T56: =R56+S56 -> 0
A57: 211 | B57: 18.07.20 | C57: 55 | D57: 211 | E57: 161000400 | F57: 59 | G57: 3463.84 | H57: 250.34 | I57: 0.19 | J57: 1 | K57: 5000 | L57: 1 | M57: 8700 | N57: 0 | Q57: 0 | R57: =K57+M57+Q57 -> 13700 | S57: =R57*5% -> 685 | T57: =R57+S57 -> 14385
A58: 212 | B58: 19.07.20 | C58: 56 | D58: 212 | E58: 161000401 | F58: 59 | G58: 3518.61 | H58: 257.39 | I58: 0 | J58: 0 | K58: 0 | L58: 0 | M58: 0 | N58: 9 | Q58: 79650 | R58: =K58+M58+Q58 -> 79650 | S58: =R58*5% -> 3982.5 | T58: =R58+S58 -> 83632.5
A59: 213 | B59: 19.07.20 | C59: 57 | D59: 213 | E59: 161000402 | F59: 58 | G59: 3408.82 | H59: 303.18 | I59: 0 | J59: 0 | K59: 0 | L59: 0 | M59: 0 | N59: 0 | O59: 0 | P59: 0 | Q59: 0 | R59: =K59+M59+Q59 -> 0 | S59: =R59*5% -> 0 | T59: =R59+S59 -> 0
A60: 214 | B60: 20.07.20 | C60: 58 | D60: 214 | E60: 141000030 | F60: 59 | G60: 3547.02 | H60: 227.98 | I60: 0 | J60: 0 | K60: 0 | L60: 0 | M60: 0 | N60: 0 | O60: 0 | P60: 0 | Q60: 0 | R60: =K60+M60+Q60 -> 0 | S60: =R60*5% -> 0 | T60: =R60+S60 -> 0
A61: 215 | B61: 20.07.20 | C61: 59 | D61: 215 | E61: 161000403 | F61: 58 | G61: 3490.82 | H61: 222.16 | I61: 0.98 | J61: 0 | K61: 0 | L61: 0 | M61: 0 | N61: 0 | O61: 0 | P61: 0 | Q61: 0 | R61: =K61+M61+Q61 -> 0 | S61: =R61*5% -> 0 | T61: =R61+S61 -> 0
A62: 216 | B62: 20.07.20 | C62: 60 | D62: 216 | E62: 161000404 | F62: 58 | G62: 3531.63 | H62: 122.89 | I62: 6.52 | J62: 1 | K62: 5000 | L62: 1 | M62: 8550 | N62: 0 | Q62: 0 | R62: =K62+M62+Q62 -> 13550 | S62: =R62*5% -> 677.5 | T62: =R62+S62 -> 14227.5
A63: 217 | B63: 21.07.20 | C63: 61 | D63: 217 | E63: 161000405 | F63: 58 | G63: 3515.64 | H63: 204.09 | I63: 8.73 | J63: 2 | K63: 10000 | L63: 1 | M63: 8700 | N63: 0 | Q63: 0 | R63: =K63+M63+Q63 -> 18700 | S63: =R63*5% -> 935 | T63: =R63+S63 -> 19635
A64: 218 | B64: 21.07.20 | C64: 62 | D64: 218 | E64: 161000406 | F64: 58 | G64: 3601.03 | H64: 118.89 | I64: 8.92 | J64: 1 | K64: 5000 | L64: 1 | M64: 8700 | N64: 0 | Q64: 0 | R64: =K64+M64+Q64 -> 13700 | S64: =R64*5% -> 685 | T64: =R64+S64 -> 14385
A65: 219 | B65: 21.07.20 | C65: 63 | D65: 219 | E65: 161000407 | F65: 59 | G65: 3545.21 | H65: 233.38 | I65: 2.59 | J65: 1 | K65: 5000 | L65: 1 | M65: 8850 | N65: 0 | Q65: 0 | R65: =K65+M65+Q65 -> 13850 | S65: =R65*5% -> 692.5 | T65: =R65+S65 -> 14542.5
A66: 220 | B66: 21.07.20 | C66: 64 | D66: 220 | E66: 161000408 | F66: 59 | G66: 3567.67 | H66: 149.7 | I66: 10.37 | J66: 1 | K66: 5000 | L66: 3 | M66: 26100 | N66: 0 | Q66: 0 | R66: =K66+M66+Q66 -> 31100 | S66: =R66*5% -> 1555 | T66: =R66+S66 -> 32655
A67: 221 | B67: 22.07.20 | C67: 65 | D67: 221 | E67: 161000409 | F67: 58 | G67: 3487.22 | H67: 228.55 | I67: 3.77 | J67: 1 | K67: 5000 | L67: 1 | M67: 8700 | N67: 0 | Q67: 0 | R67: =K67+M67+Q67 -> 13700 | S67: =R67*5% -> 685 | T67: =R67+S67 -> 14385
A68: 222 | B68: 22.07.20 | C68: 66 | D68: 222 | E68: 141000031 | F68: 58 | G68: 3368.42 | H68: 344.17 | I68: 0.59 | J68: 0 | K68: 0 | L68: 0 | M68: 0 | N68: 0 | O68: 0 | P68: 0 | Q68: 0 | R68: =K68+M68+Q68 -> 0 | S68: =R68*5% -> 0 | T68: =R68+S68 -> 0
A69: 223 | B69: 22.07.20 | C69: 67 | D69: 223 | E69: 161000410 | F69: 58 | G69: 3544.02 | H69: 173.12 | I69: 5.14 | J69: 1 | K69: 5000 | L69: 1 | M69: 8700 | N69: 0 | Q69: 0 | R69: =K69+M69+Q69 -> 13700 | S69: =R69*5% -> 685 | T69: =R69+S69 -> 14385
A70: 224 | B70: 22.07.20 | C70: 68 | D70: 224 | E70: 161000411 | F70: 58 | G70: 3570.83 | H70: 142.13 | I70: 1.96 | J70: 0 | K70: 0 | L70: 0 | M70: 0 | N70: 0 | Q70: 0 | R70: =K70+M70+Q70 -> 0 | S70: =R70*5% -> 0 | T70: =R70+S70 -> 0
A71: 225 | B71: 23.07.20 | C71: 69 | D71: 225 | E71: 161000412 | F71: 60 | G71: 3635.41 | H71: 156.26 | I71: 15.67 | J71: 4 | K71: 20000 | L71: 1 | M71: 8850 | N71: 0 | Q71: 0 | R71: =K71+M71+Q71 -> 28850 | S71: =R71*5% -> 1442.5 | T71: =R71+S71 -> 30292.5
A72: 226 | B72: 23.07.20 | C72: 70 | D72: 226 | E72: 161000413 | F72: 60 | G72: 3543.21 | H72: 295.79 | I72: 0 | J72: 0 | K72: 0 | L72: 0 | M72: 0 | N72: 0 | O72: 0 | P72: 0 | Q72: 0 | R72: =K72+M72+Q72 -> 0 | S72: =R72*5% -> 0 | T72: =R72+S72 -> 0
A73: 227 | B73: 23.07.20 | C73: 71 | D73: 227 | E73: 161000414 | F73: 58 | G73: 3384.69 | H73: 320.31 | I73: 0 | J73: 0 | K73: 0 | L73: 0 | M73: 0 | N73: 0 | O73: 0 | P73: 0 | Q73: 0 | R73: =K73+M73+Q73 -> 0 | S73: =R73*5% -> 0 | T73: =R73+S73 -> 0
A74: 228 | B74: 23.07.20 | C74: 72 | D74: 228 | E74: 161000415 | F74: 58 | G74: 3403.42 | H74: 309.57 | I74: 0.99 | J74: 0 | K74: 0 | L74: 0 | M74: 0 | N74: 0 | O74: 0 | P74: 0 | Q74: 0 | R74: =K74+M74+Q74 -> 0 | S74: =R74*5% -> 0 | T74: =R74+S74 -> 0
A75: 229 | B75: 24.07.20 | C75: 73 | D75: 229 | E75: 161000416 | F75: 58 | G75: 3341.02 | H75: 371.98 | I75: 0 | J75: 0 | K75: 0 | L75: 0 | M75: 0 | N75: 1 | Q75: 8700 | R75: =K75+M75+Q75 -> 8700 | S75: =R75*5% -> 435 | T75: =R75+S75 -> 9135
A76: 230 | B76: 24.07.20 | C76: 74 | D76: 230 | E76: 161000417 | F76: 57 | G76: 3382.27 | H76: 265.31 | I76: 3.58 | J76: 1 | K76: 5000 | L76: 1 | M76: 8550 | N76: 0 | Q76: 0 | R76: =K76+M76+Q76 -> 13550 | S76: =R76*5% -> 677.5 | T76: =R76+S76 -> 14227.5
A77: 231 | B77: 24.07.20 | C77: 75 | D77: 231 | E77: 161000418 | F77: 60 | G77: 3546.82 | H77: 298.95 | I77: 7.77 | J77: 2 | K77: 10000 | L77: 7 | M77: 63000 | N77: 0 | Q77: 0 | R77: =K77+M77+Q77 -> 73000 | S77: =R77*5% -> 3650 | T77: =R77+S77 -> 76650
A78: 232 | B78: 25.07.20 | C78: 76 | D78: 232 | E78: 161000419 | F78: 60 | G78: 3542.8 | H78: 297.2 | I78: 0 | J78: 0 | K78: 0 | L78: 0 | M78: 0 | N78: 0 | Q78: 0 | R78: =K78+M78+Q78 -> 0 | S78: =R78*5% -> 0 | T78: =R78+S78 -> 0
A79: 233 | B79: 25.07.20 | C79: 77 | D79: 233 | E79: 161000420 | F79: 59 | G79: 3487.22 | H79: 287.78 | I79: 0 | J79: 0 | K79: 0 | L79: 0 | M79: 0 | N79: 0 | Q79: 0 | R79: =K79+M79+Q79 -> 0 | S79: =R79*5% -> 0 | T79: =R79+S79 -> 0
A80: 234 | B80: 25.07.20 | C80: 78 | D80: 234 | E80: 161000421 | F80: 58 | G80: 3499.82 | H80: 213.56 | I80: 1.38 | J80: 0 | K80: 0 | L80: 0 | M80: 0 | N80: 0 | Q80: 0 | R80: =K80+M80+Q80 -> 0 | S80: =R80*5% -> 0 | T80: =R80+S80 -> 0
A81: 235 | B81: 26.07.20 | C81: 79 | D81: 235 | E81: 161000422 | F81: 59 | G81: 3568.62 | H81: 271.96 | I81: 1.58 | J81: 0 | K81: 0 | L81: 0 | M81: 0 | N81: 0 | Q81: 0 | R81: =K81+M81+Q81 -> 0 | S81: =R81*5% -> 0 | T81: =R81+S81 -> 0
A82: 236 | B82: 27.07.20 | C82: 80 | D82: 236 | E82: 161000423 | F82: 60 | G82: 3672.22 | H82: 173.09 | I82: 7.31 | J82: 1 | K82: 5000 | L82: 1 | M82: 9000 | N82: 0 | Q82: 0 | R82: =K82+M82+Q82 -> 14000 | S82: =R82*5% -> 700 | T82: =R82+S82 -> 14700
A83: 237 | B83: 27.07.20 | C83: 81 | D83: 237 | E83: 161000424 | F83: 59 | G83: 3545.85 | H83: 227.53 | I83: 1.38 | J83: 0 | K83: 0 | L83: 0 | M83: 0 | N83: 0 | O83: 0 | P83: 0 | Q83: 0 | R83: =K83+M83+Q83 -> 0 | S83: =R83*5% -> 0 | T83: =R83+S83 -> 0
A84: 238 | B84: 27.07.20 | C84: 82 | D84: 238 | E84: 161000425 | F84: 60 | G84: 3639.4 | H84: 202.37 | I84: 1.77 | J84: 0 | K84: 0 | L84: 0 | M84: 0 | N84: 0 | O84: 0 | P84: 0 | Q84: 0 | R84: =K84+M84+Q84 -> 0 | S84: =R84*5% -> 0 | T84: =R84+S84 -> 0
A85: 239 | B85: 27.07.20 | C85: 83 | D85: 239 | E85: 161000426 | F85: 59 | G85: 3519.23 | H85: 195.54 | I85: 3.77 | J85: 1 | K85: 5000 | L85: 1 | M85: 8700 | N85: 0 | Q85: 0 | R85: =K85+M85+Q85 -> 13700 | S85: =R85*5% -> 685 | T85: =R85+S85 -> 14385
A86: 240 | B86: 28.07.20 | C86: 84 | D86: 240 | E86: 161000427 | F86: 57 | G86: 3469.46 | H86: 181.51 | I86: 5.92 | J86: 2 | K86: 10000 | L86: 1 | M86: 8550 | N86: 0 | Q86: 0 | R86: =K86+M86+Q86 -> 18550 | S86: =R86*5% -> 927.5 | T86: =R86+S86 -> 19477.5
A87: 241 | B87: 28.07.20 | C87: 85 | D87: 241 | E87: 161000428 | F87: 57 | G87: 3443.42 | H87: 205.37 | I87: 0 | J87: 0 | K87: 0 | L87: 0 | M87: 0 | N87: 0 | Q87: 0 | R87: =K87+M87+Q87 -> 0 | S87: =R87*5% -> 0 | T87: =R87+S87 -> 0
A88: 242 | B88: 28.07.20 | C88: 86 | D88: 242 | E88: 161000429 | F88: 59 | G88: 3543.43 | H88: 230.57 | I88: 0 | J88: 0 | K88: 0 | L88: 0 | M88: 0 | N88: 0 | Q88: 0 | R88: =K88+M88+Q88 -> 0 | S88: =R88*5% -> 0 | T88: =R88+S88 -> 0
A89: 243 | B89: 28.07.20 | C89: 87 | D89: 243 | E89: 161000430 | F89: 59 | G89: 3620.42 | H89: 154.77 | I89: 0.19 | J89: 0 | K89: 0 | L89: 0 | M89: 0 | N89: 0 | Q89: 0 | R89: =K89+M89+Q89 -> 0 | S89: =R89*5% -> 0 | T89: =R89+S89 -> 0
A90: 244 | B90: 29.07.20 | C90: 88 | D90: 244 | E90: 161000431 | F90: 60 | G90: 3583.6 | H90: 256.59 | I90: 0.19 | J90: 0 | K90: 0 | L90: 0 | M90: 0 | N90: 0 | Q90: 0 | R90: =K90+M90+Q90 -> 0 | S90: =R90*5% -> 0 | T90: =R90+S90 -> 0
A91: 245 | B91: 29.07.20 | C91: 89 | D91: 245 | E91: 161000432 | F91: 59 | G91: 3611.83 | H91: 164.35 | I91: 2.18 | J91: 0 | K91: 0 | L91: 0 | M91: 0 | N91: 0 | Q91: 0 | R91: =K91+M91+Q91 -> 0 | S91: =R91*5% -> 0 | T91: =R91+S91 -> 0
A92: 246 | B92: 29.07.20 | C92: 90 | D92: 246 | E92: 161000433 | F92: 59 | G92: 3570.83 | H92: 141.56 | I92: 1.39 | J92: 0 | K92: 0 | L92: 0 | M92: 0 | N92: 0 | Q92: 0 | R92: =K92+M92+Q92 -> 0 | S92: =R92*5% -> 0 | T92: =R92+S92 -> 0
A93: 247 | B93: 29.07.20 | C93: 91 | D93: 247 | E93: 161000434 | F93: 57 | G93: 3511.27 | H93: 136.29 | I93: 3.56 | J93: 1 | K93: 5000 | L93: 1 | M93: 8550 | N93: 0 | Q93: 0 | R93: =K93+M93+Q93 -> 13550 | S93: =R93*5% -> 677.5 | T93: =R93+S93 -> 14227.5
A94: 248 | B94: 30.07.20 | C94: 92 | D94: 248 | E94: 161000435 | F94: 59 | G94: 3574.03 | H94: 199.97 | I94: 0 | J94: 0 | K94: 0 | L94: 0 | M94: 0 | N94: 0 | O94: 0 | P94: 0 | Q94: 0 | R94: =K94+M94+Q94 -> 0 | S94: =R94*5% -> 0 | T94: =R94+S94 -> 0
A95: 249 | B95: 30.07.20 | C95: 93 | D95: 249 | E95: 161000436 | F95: 59 | G95: 3548.42 | H95: 229.58 | I95: 0 | J95: 0 | K95: 0 | L95: 0 | M95: 0 | N95: 0 | O95: 0 | P95: 0 | Q95: 0 | R95: =K95+M95+Q95 -> 0 | S95: =R95*5% -> 0 | T95: =R95+S95 -> 0
A96: 250 | B96: 30.07.20 | C96: 94 | D96: 250 | E96: 161000437 | F96: 56 | G96: 3414.83 | H96: 234.75 | I96: 0 | J96: 0 | K96: 0 | L96: 0 | M96: 0 | N96: 0 | O96: 0 | P96: 0 | Q96: 0 | R96: =K96+M96+Q96 -> 0 | S96: =R96*5% -> 0 | T96: =R96+S96 -> 0
A97: 251 | B97: 31.07.20 | C97: 95 | D97: 251 | E97: 161000438 | F97: 59 | G97: 3614.21 | H97: 165.96 | I97: 4.17 | J97: 1 | K97: 5000 | L97: 1 | M97: 8850 | N97: 0 | Q97: 0 | R97: =K97+M97+Q97 -> 13850 | S97: =R97*5% -> 692.5 | T97: =R97+S97 -> 14542.5
A98: 252 | B98: 31.07.20 | C98: 96 | D98: 252 | E98: 161000439 | F98: 58 | G98: 3484.43 | H98: 226.57 | I98: 0 | J98: 0 | K98: 0 | L98: 0 | M98: 0 | N98: 0 | O98: 0 | P98: 0 | Q98: 0 | R98: =K98+M98+Q98 -> 0 | S98: =R98*5% -> 0 | T98: =R98+S98 -> 0
A99: 253 | B99: 31.07.20 | C99: 97 | D99: 253 | E99: 161000440 | F99: 60 | G99: 3569.82 | H99: 268.18 | I99: 0 | J99: 0 | K99: 0 | L99: 0 | M99: 0 | N99: 0 | O99: 0 | P99: 0 | Q99: 0 | R99: =K99+M99+Q99 -> 0 | S99: =R99*5% -> 0 | T99: =R99+S99 -> 0
A100: 254 | B100: 31.07.20 | C100: 98 | D100: 254 | E100: 161000441 | F100: 57 | G100: 3451.6 | H100: 196.96 | I100: 0.59 | J100: 0 | K100: 0 | L100: 0 | M100: 0 | N100: 0 | O100: 0 | P100: 0 | Q100: 0 | R100: =K100+M100+Q100 -> 0 | S100: =R100*5% -> 0 | T100: =R100+S100 -> 0
...

Sheet AUG
A1: AUGUST MONTH RAKE LOADING DATA
A2: SL NO | B2: LOADING DATE | C2: RAKE NO. | D2: PRIORTY NUMBER | E2: R.R NUMBER | F2: NO OF WAGON | G2: NET WEIGHT | H2: UNDER LOAD WT | I2: OVER LOAD WT | J2: O/L WAGON | K2: O/L CHARGE | L2: DETENTION HOURS | M2: DETENTION CHARGES | N2: SHUNTING HOURS | O2: SHUNTING CHARGES | P2: PILOT HOURS | Q2: PILOT CHARGES | R2: PCLA | S2: GST 5% | T2: TOTAL AMOUNT RS
A3: 255 | B3: 01.08.20 | C3: 1 | D3: 255 | E3: 161000442 | F3: 60 | G3: 3579 | H3: 261 | I3: 0 | J3: 0 | K3: 0 | L3: 0 | M3: 0 | N3: 0 | O3: 0 | P3: 0 | Q3: 0 | R3: =K3+M3+Q3 -> 0 | S3: =R3*5% -> 0 | T3: =R3+S3 -> 0
A4: 256 | B4: 01.08.20 | C4: 2 | D4: 256 | E4: 161000443 | F4: 57 | G4: 3372.84 | H4: 274.16 | I4: 0 | J4: 0 | K4: 0 | L4: 0 | M4: 0 | N4: 0 | O4: 0 | P4: 0 | Q4: 0 | R4: =K4+M4+Q4 -> 0 | S4: =R4*5% -> 0 | T4: =R4+S4 -> 0
A5: 257 | B5: 02.08.20 | C5: 3 | D5: 257 | E5: 161000444 | F5: 59 | G5: 3515.01 | H5: 260.99 | I5: 0 | J5: 0 | K5: 0 | L5: 0 | M5: 0 | N5: 0 | O5: 0 | P5: 0 | Q5: 0 | R5: =K5+M5+Q5 -> 0 | S5: =R5*5% -> 0 | T5: =R5+S5 -> 0
A6: 258 | B6: 02.08.20 | C6: 4 | D6: 258 | E6: 161000445 | F6: 60 | G6: 3623.61 | H6: 215.39 | I6: 0 | J6: 0 | K6: 0 | L6: 0 | M6: 0 | N6: 0 | O6: 0 | P6: 0 | Q6: 0 | R6: =K6+M6+Q6 -> 0 | S6: =R6*5% -> 0 | T6: =R6+S6 -> 0
A7: 259 | B7: 03.08.20 | C7: 5 | D7: 259 | E7: 161000446 | F7: 59 | G7: 3579.05 | H7: 195.14 | I7: 2.19 | J7: 1 | K7: 5000 | L7: 1 | M7: 8850 | N7: 0 | Q7: 0 | R7: =K7+M7+Q7 -> 13850 | S7: =R7*5% -> 692.5 | T7: =R7+S7 -> 14542.5
A8: 260 | B8: 04.08.20 | C8: 6 | D8: 260 | E8: 161000447 | F8: 58 | G8: 3631.41 | H8: 207.98 | I8: 0.39 | J8: 0 | K8: 0 | L8: 0 | M8: 0 | N8: 0 | Q8: 0 | R8: =K8+M8+Q8 -> 0 | S8: =R8*5% -> 0 | T8: =R8+S8 -> 0
A9: 261 | B9: 04.08.20 | C9: 7 | D9: 261 | E9: 161000448 | F9: 58 | G9: 3516.23 | H9: 194.96 | I9: 0.19 | J9: 0 | K9: 0 | L9: 0 | M9: 0 | N9: 0 | Q9: 0 | R9: =K9+M9+Q9 -> 0 | S9: =R9*5% -> 0 | T9: =R9+S9 -> 0
A10: 262 | B10: 04.08.20 | C10: 8 | D10: 262 | E10: 161000449 | F10: 60 | G10: 3627.61 | H10: 211.39 | I10: 0 | J10: 0 | K10: 0 | L10: 0 | M10: 0 | N10: 0 | Q10: 0 | R10: =K10+M10+Q10 -> 0 | S10: =R10*5% -> 0 | T10: =R10+S10 -> 0
A11: 263 | B11: 04.08.20 | C11: 9 | D11: 263 | E11: 161000450 | F11: 60 | G11: 3574.62 | H11: 263.38 | I11: 0 | J11: 0 | K11: 0 | L11: 0 | M11: 0 | N11: 0 | Q11: 0 | R11: =K11+M11+Q11 -> 0 | S11: =R11*5% -> 0 | T11: =R11+S11 -> 0
A12: 264 | B12: 05.08.20 | C12: 10 | D12: 264 | E12: 161000451 | F12: 59 | G12: 3499.43 | H12: 274.57 | I12: 0 | J12: 0 | K12: 0 | L12: 0 | M12: 0 | N12: 0 | Q12: 0 | R12: =K12+M12+Q12 -> 0 | S12: =R12*5% -> 0 | T12: =R12+S12 -> 0
A13: 265 | B13: 05.08.20 | C13: 11 | D13: 265 | E13: 161000452 | F13: 60 | G13: 3610.21 | H13: 228.98 | I13: 0.19 | J13: 0 | K13: 0 | L13: 0 | M13: 0 | N13: 0 | Q13: 0 | R13: =K13+M13+Q13 -> 0 | S13: =R13*5% -> 0 | T13: =R13+S13 -> 0
A14: 266 | B14: 06.08.20 | C14: 12 | D14: 266 | E14: 161000453 | F14: 56 | G14: 3365.45 | H14: 217.55 | I14: 0 | J14: 0 | K14: 0 | L14: 0 | M14: 0 | N14: 0 | Q14: 0 | R14: =K14+M14+Q14 -> 0 | S14: =R14*5% -> 0 | T14: =R14+S14 -> 0
A15: 267 | B15: 06.08.20 | C15: 13 | D15: 267 | E15: 161000454 | F15: 60 | G15: 3606.4 | H15: 233.6 | I15: 0 | J15: 0 | K15: 0 | L15: 0 | M15: 0 | N15: 0 | Q15: 0 | R15: =K15+M15+Q15 -> 0 | S15: =R15*5% -> 0 | T15: =R15+S15 -> 0
A16: 268 | B16: 07.08.20 | C16: 14 | D16: 268 | E16: 161000455 | F16: 60 | G16: 3638.61 | H16: 200.39 | I16: 0 | J16: 0 | K16: 0 | L16: 0 | M16: 0 | N16: 0 | Q16: 0 | R16: =K16+M16+Q16 -> 0 | S16: =R16*5% -> 0 | T16: =R16+S16 -> 0
A17: 269 | B17: 08.08.20 | C17: 15 | D17: 269 | E17: 161000456 | F17: 60 | G17: 3630.22 | H17: 207.78 | I17: 0 | J17: 0 | K17: 0 | L17: 0 | M17: 0 | N17: 0 | Q17: 0 | R17: =K17+M17+Q17 -> 0 | S17: =R17*5% -> 0 | T17: =R17+S17 -> 0
A18: 270 | B18: 08.08.20 | C18: 16 | D18: 270 | E18: 161000457 | F18: 60 | G18: 3633.6 | H18: 206.4 | I18: 0 | J18: 0 | K18: 0 | L18: 0 | M18: 0 | N18: 0 | Q18: 0 | R18: =K18+M18+Q18 -> 0 | S18: =R18*5% -> 0 | T18: =R18+S18 -> 0
... A47: 299 | B47: 17.08.20 | C47: 45 | D47: 299 | E47: 161000485 | F47: 60 | G47: 3738.3 | H47: 163.76 | I47: 2.06 | J47: 1 | K47: 5000 | L47: 1 | M47: 9000 | N47: 0 | Q47: 0 | R47: =K47+M47+Q47 -> 14000 | S47: =R47*5% -> 700 | T47: =R47+S47 -> 14700
A48: 300 | B48: 18.08.20 | C48: 46 | D48: 300 | E48: 161000486 | F48: 60 | G48: 3637.63 | H48: 259.77 | I48: 0.4 | J48: 0 | K48: 0 | L48: 0 | M48: 0 | N48: 0 | O48: 0 | P48: 0 | Q48: 0 | R48: =K48+M48+Q48 -> 0 | S48: =R48*5% -> 0 | T48: =R48+S48 -> 0
A49: 301 | B49: 18.08.20 | C49: 47 | D49: 301 | E49: 161000487 | F49: 60 | G49: 3590.81 | H49: 308.19 | I49: 0 | J49: 0 | K49: 0 | L49: 0 | M49: 0 | N49: 0 | O49: 0 | P49: 0 | Q49: 0 | R49: =K49+M49+Q49 -> 0 | S49: =R49*5% -> 0 | T49: =R49+S49 -> 0
A50: 302 | B50: 18.08.20 | C50: 48 | D50: 302 | E50: 161000488 | F50: 60 | G50: 3586.04 | H50: 309.96 | I50: 0 | J50: 0 | K50: 0 | L50: 0 | M50: 0 | N50: 0 | O50: 0 | P50: 0 | Q50: 0 | R50: =K50+M50+Q50 -> 0 | S50: =R50*5% -> 0 | T50: =R50+S50 -> 0
A51: 303 | B51: 19.08.20 | C51: 49 | D51: 303 | E51: 161000489 | F51: 60 | G51: 3737.21 | H51: 171.33 | I51: 0.69 | J51: 6 | K51: 30000 | L51: 1 | M51: 9000 | N51: 0 | Q51: 0 | R51: =K51+M51+Q51 -> 39000 | S51: =R51*5% -> 1950 | T51: =R51+S51 -> 40950
A52: 304 | B52: 19.08.20 | C52: 50 | D52: 304 | E52: 161000490 | F52: 60 | G52: 3596 | H52: 304 | I52: 0 | J52: 0 | K52: 0 | L52: 0 | M52: 0 | N52: 0 | Q52: 0 | R52: =K52+M52+Q52 -> 0 | S52: =R52*5% -> 0 | T52: =R52+S52 -> 0
A53: 305 | B53: 20.08.20 | C53: 51 | D53: 305 | E53: 161000491 | F53: 60 | G53: 3554.6 | H53: 345.4 | I53: 0 | J53: 0 | K53: 0 | L53: 0 | M53: 0 | N53: 0 | Q53: 0 | R53: =K53+M53+Q53 -> 0 | S53: =R53*5% -> 0 | T53: =R53+S53 -> 0
A54: 306 | B54: 20.08.20 | C54: 52 | D54: 306 | E54: 161000492 | F54: 60 | G54: 3581 | H54: 319 | I54: 0 | J54: 0 | K54: 0 | L54: 0 | M54: 0 | N54: 0 | Q54: 0 | R54: =K54+M54+Q54 -> 0 | S54: =R54*5% -> 0 | T54: =R54+S54 -> 0
A55: 307 | B55: 20.08.20 | C55: 53 | D55: 307 | E55: 161000493 | F55: 59 | G55: 3542.84 | H55: 289.16 | I55: 0 | J55: 0 | K55: 0 | L55: 0 | M55: 0 | N55: 0 | Q55: 54000 | R55: =K55+M55+Q55 -> 54000 | S55: =R55*5% -> 2700 | T55: =R55+S55 -> 56700
A56: 308 | B56: 20.08.20 | C56: 54 | D56: 308 | E56: 161000494 | F56: 60 | G56: 3586.04 | H56: 309.96 | I56: 0 | J56: 0 | K56: 0 | L56: 0 | M56: 0 | N56: 0 | Q56: 0 | R56: =K56+M56+Q56 -> 0 | S56: =R56*5% -> 0 | T56: =R56+S56 -> 0
A57: 309 | B57: 21.08.20 | C57: 55 | D57: 309 | E57: 161000495 | F57: 57 | G57: 3377.05 | H57: 261.95 | I57: 0 | J57: 0 | K57: 0 | L57: 0 | M57: 0 | N57: 0 | Q57: 0 | R57: =K57+M57+Q57 -> 0 | S57: =R57*5% -> 0 | T57: =R57+S57 -> 0
A58: 310 | B58: 21.08.20 | C58: 56 | D58: 310 | E58: 161000496 | F58: 60 | G58: 3577.2 | H58: 322.8 | I58: 0 | J58: 0 | K58: 0 | L58: 0 | M58: 0 | N58: 0 | Q58: 0 | R58: =K58+M58+Q58 -> 0 | S58: =R58*5% -> 0 | T58: =R58+S58 -> 0
A59: 311 | B59: 21.08.20 | C59: 57 | D59: 311 | E59: 161000497 | F59: 60 | G59: 3601.4 | H59: 298.6 | I59: 0 | J59: 0 | K59: 0 | L59: 0 | M59: 0 | N59: 0 | Q59: 0 | R59: =K59+M59+Q59 -> 0 | S59: =R59*5% -> 0 | T59: =R59+S59 -> 0
A60: 312 | B60: 23.08.20 | C60: 58 | D60: 312 | E60: 161000498 | F60: 59 | G60: 3558.61 | H60: 276.39 | I60: 0 | J60: 0 | K60: 0 | L60: 0 | M60: 0 | N60: 0 | Q60: 0 | R60: =K60+M60+Q60 -> 0 | S60: =R60*5% -> 0 | T60: =R60+S60 -> 0
A61: 313 | B61: 23.08.20 | C61: 59 | D61: 313 | E61: 161000499 | F61: 60 | G61: 3575 | H61: 325 | I61: 0 | J61: 0 | K61: 0 | L61: 0 | M61: 0 | N61: 0 | Q61: 0 | R61: =K61+M61+Q61 -> 0 | S61: =R61*5% -> 0 | T61: =R61+S61 -> 0
A62: 314 | B62: 24.08.20 | C62: 60 | D62: 314 | E62: 161000500 | F62: 57 | G62: 3442.63 | H62: 262.37 | I62: 0 | J62: 0 | K62: 0 | L62: 0 | M62: 0 | N62: 0 | Q62: 0 | R62: =K62+M62+Q62 -> 0 | S62: =R62*5% -> 0 | T62: =R62+S62 -> 0
... A80: 332 | B80: 30.08.20 | C80: 78 | D80: 332 | E80: 161000518 | F80: 60 | G80: 3682.4 | H80: 218.99 | I80: 1.39 | J80: 1 | K80: 5000 | L80: 1 | M80: 9000 | N80: 0 | Q80: 0 | R80: =K80+M80+Q80 -> 14000 | S80: =R80*5% -> 700 | T80: =R80+S80 -> 14700
A81: 333 | B81: 30.08.20 | C81: 79 | D81: 333 | E81: 161000519 | F81: 58 | G81: 3407.04 | H81: 400.96 | I81: 0 | J81: 0 | K81: 0 | L81: 0 | M81: 0 | N81: 0 | O81: 0 | P81: 0 | Q81: 0 | R81: =K81+M81+Q81 -> 0 | S81: =R81*5% -> 0 | T81: =R81+S81 -> 0
A82: 334 | B82: 31.08.20 | C82: 80 | D82: 334 | E82: 161000520 | F82: 58 | G82: 3289.33 | H82: 479.67 | I82: 0 | J82: 0 | K82: 0 | L82: 0 | M82: 0 | N82: 0 | O82: 0 | P82: 0 | Q82: 0 | R82: =K82+M82+Q82 -> 0 | S82: =R82*5% -> 0 | T82: =R82+S82 -> 0 | U82: 478800
A83: 335 | B83: 31.08.20 | C83: 81 | D83: 335 | E83: 161000521 | F83: 58 | G83: 3234.35 | H83: 532.65 | I83: 0 | J83: 0 | K83: 0 | L83: 0 | M83: 0 | N83: 0 | O83: 0 | P83: 0 | Q83: 0 | R83: =K83+M83+Q83 -> 0 | S83: =R83*5% -> 0 | T83: =R83+S83 -> 0 | U83: 37800
A84: 336 | B84: 31.08.20 | C84: 82 | D84: 336 | E84: 161000522 | F84: 58 | G84: 3299.84 | H84: 468 | I84: 0 | J84: 0 | K84: 0 | L84: 0 | M84: 0 | N84: 0 | O84: 0 | P84: 0 | Q84: 0 | R84: =K84+M84+Q84 -> 0 | S84: =R84*5% -> 0 | T84: =R84+S84 -> 0 | U84: 56700
E85: TOTAL | F85: =SUM(F3:F84) -> 4871 | G85: =SUM(G3:G84) -> 292214.44 | H85: =SUM(H3:H84) -> 21873.3 | I85: =SUM(I3:I84) -> 31.67 | J85: =SUM(J3:J84) -> 18 | K85: =SUM(K3:K84) -> 90000 | L85: =SUM(L3:L84) -> 8 | M85: =SUM(M3:M84) -> 71700 | ... T85: =SUM(T3:T84) -> 758824.5 | U85: =SUM(U82:U84) -> 573300
F86: =G85/C84 -> 3563.5907
H87: =H85/82 -> 266.74756
T88: =T85-U85 -> 185524.5

Sheet SEP
A1: SEPTEMBER MONTH RAKE LOADING DATA
A2: SL NO | B2: LOADING DATE | C2: RAKE NO. | D2: PRIORTY NUMBER | E2: R.R NUMBER | F2: NO OF WAGON | G2: NET WEIGHT | H2: UNDER LOAD WT | I2: OVER LOAD WT | J2: O/L WAGON | K2: O/L CHARGE | L2: DETENTION HOURS | M2: DETENTION CHARGES | N2: SHUNTING HOURS | O2: SHUNTING CHARGES | P2: PILOT HOURS | Q2: PILOT CHARGES | R2: PCLA | S2: GST 5% | T2: TOTAL AMOUNT RS
A3: 337 | B3: 01.09.20 | C3: 1 | D3: 337 | E3: 161000523 | F3: 60 | G3: 3563.1 | H3: 336.9 | I3: 0 | J3: 0 | K3: 0 | L3: 0 | M3: 0 | N3: 0 | O3: 0 | P3: 0 | Q3: 0 | R3: =K3+M3+Q3 -> 0 | S3: =R3*5% -> 0 | T3: =R3+S3 -> 0
A4: 338 | B4: 02.09.20 | C4: 2 | D4: 338 | E4: 161000524 | F4: 57 | G4: 3358.03 | H4: 346.97 | I4: 0 | J4: 0 | K4: 0 | L4: 0 | M4: 0 | N4: 0 | O4: 0 | P4: 0 | Q4: 0 | R4: =K4+M4+Q4 -> 0 | S4: =R4*5% -> 0 | T4: =R4+S4 -> 0
A5: 339 | B5: 02.09.20 | C5: 3 | D5: 339 | E5: 161000525 | F5: 60 | G5: 3505.84 | H5: 390.16 | I5: 0 | J5: 0 | K5: 0 | L5: 0 | M5: 0 | N5: 0 | O5: 0 | P5: 0 | Q5: 0 | R5: =K5+M5+Q5 -> 0 | S5: =R5*5% -> 0 | T5: =R5+S5 -> 0
A6: 340 | B6: 02.09.20 | C6: 4 | D6: 340 | E6: 161000526 | F6: 60 | G6: 3587.6 | H6: 312.4 | I6: 0 | J6: 0 | K6: 0 | L6: 0 | M6: 0 | N6: 0 | O6: 0 | P6: 0 | Q6: 0 | R6: =K6+M6+Q6 -> 0 | S6: =R6*5% -> 0 | T6: =R6+S6 -> 0
A7: 341 | B7: 02.09.20 | C7: 5 | D7: 341 | E7: 161000527 | F7: 60 | G7: 3345.74 | H7: 422.26 | I7: 0 | J7: 0 | K7: 0 | L7: 0 | M7: 0 | N7: 0 | O7: 0 | P7: 0 | Q7: 0 | R7: =K7+M7+Q7 -> 0 | S7: =R7*5% -> 0 | T7: =R7+S7 -> 0
A8: 342 | B8: 03.09.20 | C8: 6 | D8: 342 | E8: 161000528 | F8: 58 | G8: 3475.44 | H8: 292.56 | I8: 0 | J8: 0 | K8: 0 | L8: 0 | M8: 0 | N8: 0 | O8: 0 | P8: 0 | Q8: 0 | R8: =K8+M8+Q8 -> 0 | S8: =R8*5% -> 0 | T8: =R8+S8 -> 0
A9: 343 | B9: 03.09.20 | C9: 7 | D9: 343 | E9: 161000529 | F9: 59 | G9: 3529.92 | H9: 304.08 | I9: 0 | J9: 0 | K9: 0 | L9: 0 | M9: 0 | N9: 0 | O9: 0 | P9: 0 | Q9: 0 | R9: =K9+M9+Q9 -> 0 | S9: =R9*5% -> 0 | T9: =R9+S9 -> 0
A10: 344 | B10: 03.09.20 | C10: 8 | D10: 344 | E10: 161000530 | F10: 58 | G10: 3313.53 | H10: 391.47 | I10: 0 | J10: 0 | K10: 0 | L10: 0 | M10: 0 | N10: 0 | O10: 0 | P10: 0 | Q10: 0 | R10: =K10+M10+Q10 -> 0 | S10: =R10*5% -> 0 | T10: =R10+S10 -> 0
A11: 345 | B11: 03.09.20 | C11: 9 | D11: 345 | E11: 161000531 | F11: 60 | G11: 3431.64 | H11: 464.36 | I11: 0 | J11: 0 | K11: 0 | L11: 0 | M11: 0 | N11: 0 | O11: 0 | P11: 0 | Q11: 0 | R11: =K11+M11+Q11 -> 0 | S11: =R11*5% -> 0 | T11: =R11+S11 -> 0
A12: 346 | B12: 04.09.20 | C12: 10 | D12: 346 | E12: 161000532 | F12: 60 | G12: 3359.22 | H12: 408.78 | I12: 0 | J12: 0 | K12: 0 | L12: 0 | M12: 0 | N12: 0 | O12: 0 | P12: 0 | Q12: 0 | R12: =K12+M12+Q12 -> 0 | S12: =R12*5% -> 0 | T12: =R12+S12 -> 0
A13: 347 | B13: 04.09.20 | C13: 11 | D13: 347 | E13: 161000533 | F13: 60 | G13: 3491.6 | H13: 408.4 | I13: 0 | J13: 0 | K13: 0 | L13: 0 | M13: 0 | N13: 0 | O13: 0 | P13: 0 | Q13: 0 | R13: =K13+M13+Q13 -> 0 | S13: =R13*5% -> 0 | T13: =R13+S13 -> 0
A14: 348 | B14: 04.09.20 | C14: 12 | D14: 348 | E14: 161000534 | F14: 60 | G14: 3539.41 | H14: 359.59 | I14: 0 | J14: 0 | K14: 0 | L14: 0 | M14: 0 | N14: 0 | O14: 0 | P14: 0 | Q14: 0 | R14: =K14+M14+Q14 -> 0 | S14: =R14*5% -> 0 | T14: =R14+S14 -> 0
... A18: 352 | B18: 05.09.20 | C18: 16 | D18: 352 | E18: 161000537 | F18: 60 | G18: 3496.42 | H18: 337.58 | I18: 0 | J18: 0 | K18: 0 | L18: 0 | M18: 0 | N18: 0 | O18: 0 | P18: 0 | Q18: 0 | R18: =K18+M18+Q18 -> 0 | S18: =R18*5% -> 0 | T18: =R18+S18 -> 0
A19: 353 | B19: 06.09.20 | C19: 17 | D19: 353 | E19: 161000538 | F19: 59 | G19: 3508.21 | H19: 326.79 | I19: 0 | J19: 0 | K19: 0 | L19: 0 | M19: 0 | N19: 0 | O19: 0 | P19: 0 | Q19: 0 | R19: =K19+M19+Q19 -> 0 | S19: =R19*5% -> 0 | T19: =R19+S19 -> 0 | U19: LINK FAILED 0:30
A20: 354 | B20: 06.09.20 | C20: 18 | D20: 354 | E20: 162000002 | F20: 58 | G20: 3391.02 | H20: 378.98 | I20: 0 | J20: 0 | K20: 0 | L20: 0 | M20: 0 | N20: 0 | O20: 0 | P20: 0 | Q20: 0 | R20: =K20+M20+Q20 -> 0 | S20: =R20*5% -> 0 | T20: =R20+S20 -> 0
A21: 355 | B21: 07.09.20 | C21: 19 | D21: 355 | E21: 161000539 | F21: 56 | G21: 3338.49 | H21: 297.31 | I21: 0 | J21: 0 | K21: 0 | L21: 0 | M21: 0 | N21: 0 | O21: 0 | P21: 0 | Q21: 0 | R21: =K21+M21+Q21 -> 0 | S21: =R21*5% -> 0 | T21: =R21+S21 -> 0
A22: 356 | B22: 07.09.20 | C22: 20 | D22: 356 | E22: 161000540 | F22: 58 | G22: 3435.06 | H22: 330.94 | I22: 0 | J22: 0 | K22: 0 | L22: 0 | M22: 0 | N22: 0 | O22: 0 | P22: 0 | Q22: 0 | R22: =K22+M22+Q22 -> 0 | S22: =R22*5% -> 0 | T22: =R22+S22 -> 0
A23: 357 | B23: 07.09.20 | C23: 21 | D23: 357 | E23: 161000541 | F23: 58 | G23: 3509.83 | H23: 259.17 | I23: 0 | J23: 0 | K23: 0 | L23: 0 | M23: 0 | N23: 0 | O23: 0 | P23: 0 | Q23: 0 | R23: =K23+M23+Q23 -> 0 | S23: =R23*5% -> 0 | T23: =R23+S23 -> 0
A24: 358 | B24: 08.09.20 | C24: 22 | D24: 358 | E24: 162000003 | F24: 57 | G24: 3416.45 | H24: 286.65 | I24: 0 | J24: 0 | K24: 0 | L24: 0 | M24: 0 | N24: 0 | O24: 0 | P24: 0 | Q24: 0 | R24: =K24+M24+Q24 -> 0 | S24: =R24*5% -> 0 | T24: =R24+S24 -> 0
A25: 359 | B25: 08.09.20 | C25: 23 | D25: 359 | E25: 161000542 | F25: 59 | G25: 3510.05 | H25: 320.95 | I25: 0 | J25: 0 | K25: 0 | L25: 0 | M25: 0 | N25: 0 | O25: 0 | P25: 0 | Q25: 0 | R25: =K25+M25+Q25 -> 0 | S25: =R25*5% -> 0 | T25: =R25+S25 -> 0 | U25: BAKREHWAR | V25: 106 KM
A26: 360 | B26: 08.09.20 | C26: 24 | D26: 360 | E26: 161000543 | F26: 59 | G26: 3510.41 | H26: 324.59 | I26: 0 | J26: 0 | K26: 0 | L26: 0 | M26: 0 | N26: 0 | O26: 0 | P26: 0 | Q26: 0 | R26: =K26+M26+Q26 -> 0 | S26: =R26*5% -> 0 | T26: =R26+S26 -> 0
A27: 361 | B27: 08.09.20 | C27: 25 | D27: 361 | E27: 162000004 | F27: 59 | G27: 3545.01 | H27: 289.99 | I27: 0 | J27: 0 | K27: 0 | L27: 0 | M27: 0 | N27: 0 | O27: 0 | P27: 0 | Q27: 0 | R27: =K27+M27+Q27 -> 0 | S27: =R27*5% -> 0 | T27: =R27+S27 -> 0 | U27: SANTHALDIH | V27: 242 KM
A28: 362 | B28: 09.09.20 | C28: 26 | D28: 362 | E28: 161000544 | F28: 58 | G28: 3455.06 | H28: 310.94 | I28: 0 | J28: 0 | K28: 0 | L28: 0 | M28: 0 | N28: 0 | O28: 0 | P28: 0 | Q28: 0 | R28: =K28+M28+Q28 -> 0 | S28: =R28*5% -> 0 | T28: =R28+S28 -> 0
A29: 363 | B29: 09.09.20 | C29: 27 | D29: 363 | E29: 161000545 | F29: 57 | G29: 3388.66 | H29: 313.34 | I29: 0 | J29: 0 | K29: 0 | L29: 0 | M29: 0 | N29: 0 | O29: 0 | P29: 0 | Q29: 0 | R29: =K29+M29+Q29 -> 0 | S29: =R29*5% -> 0 | T29: =R29+S29 -> 0
A30: 364 | B30: 09.09.20 | C30: 28 | D30: 364 | E30: 161000546 | F30: 57 | G30: 3387.27 | H30: 313.73 | I30: 0 | J30: 0 | K30: 0 | L30: 0 | M30: 0 | N30: 0 | O30: 0 | P30: 0 | Q30: 0 | R30: =K30+M30+Q30 -> 0 | S30: =R30*5% -> 0 | T30: =R30+S30 -> 0
A31: 365 | B31: 10.09.20 | C31: 29 | D31: 365 | E31: 162000005 | F31: 58 | G31: 3446.63 | H31: 322.37 | I31: 0 | J31: 0 | K31: 0 | L31: 0 | M31: 0 | N31: 0 | O31: 0 | P31: 0 | Q31: 0 | R31: =K31+M31+Q31 -> 0 | S31: =R31*5% -> 0 | T31: =R31+S31 -> 0
A32: 366 | B32: 10.09.20 | C32: 30 | D32: 366 | E32: 161000547 | F32: 59 | G32: 3464.21 | H32: 370.79 | I32: 0 | J32: 0 | K32: 0 | L32: 0 | M32: 0 | N32: 0 | O32: 0 | P32: 0 | Q32: 0 | R32: =K32+M32+Q32 -> 0 | S32: =R32*5% -> 0 | T32: =R32+S32 -> 0
A33: 367 | B33: 10.09.20 | C33: 31 | D33: 367 | E33: 161000548 | F33: 55 | G33: 3241.47 | H33: 331.53 | I33: 0 | J33: 0 | K33: 0 | L33: 0 | M33: 0 | N33: 0 | O33: 0 | P33: 0 | Q33: 0 | R33: =K33+M33+Q33 -> 0 | S33: =R33*5% -> 0 | T33: =R33+S33 -> 0
A34: 368 | B34: 10.09.20 | C34: 32 | D34: 368 | E34: 161000549 | F34: 59 | G34: 3523.22 | H34: 310.78 | I34: 0 | J34: 0 | K34: 0 | L34: 0 | M34: 0 | N34: 0 | O34: 0 | P34: 0 | Q34: 0 | R34: =K34+M34+Q34 -> 0 | S34: =R34*5% -> 0 | T34: =R34+S34 -> 0
A35: 369 | B35: 11.09.20 | C35: 33 | D35: 369 | E35: 161000550 | F35: 59 | G35: 3532.45 | H35: 298.55 | I35: 0 | J35: 0 | K35: 0 | L35: 0 | M35: 0 | N35: 0 | O35: 0 | P35: 0 | Q35: 0 | R35: =K35+M35+Q35 -> 0 | S35: =R35*5% -> 0 | T35: =R35+S35 -> 0
A36: 370 | B36: 11.09.20 | C36: 34 | D36: 370 | E36: 162000006 | F36: 60 | G36: 3445.86 | H36: 384.14 | I36: 0 | J36: 0 | K36: 0 | L36: 0 | M36: 0 | N36: 0 | O36: 0 | P36: 0 | Q36: 0 | R36: =K36+M36+Q36 -> 0 | S36: =R36*5% -> 0 | T36: =R36+S36 -> 0
A37: 371 | B37: 11.09.20 | C37: 35 | D37: 371 | E37: 161000551 | F37: 58 | G37: 3399.82 | H37: 370.18 | I37: 0 | J37: 0 | K37: 0 | L37: 0 | M37: 0 | N37: 0 | O37: 0 | P37: 0 | Q37: 0 | R37: =K37+M37+Q37 -> 0 | S37: =R37*5% -> 0 | T37: =R37+S37 -> 0
A38: 372 | B38: 12.09.20 | C38: 36 | D38: 372 | E38: 161000552 | F38: 57 | G38: 3363.65 | H38: 339.35 | I38: 0 | J38: 0 | K38: 0 | L38: 0 | M38: 0 | N38: 0 | O38: 0 | P38: 0 | Q38: 0 | R38: =K38+M38+Q38 -> 0 | S38: =R38*5% -> 0 | T38: =R38+S38 -> 0
A39: 373 | B39: 12.09.20 | C39: 37 | D39: 373 | E39: 161000553 | F39: 59 | G39: 3524.02 | H39: 309.98 | I39: 0 | J39: 0 | K39: 0 | L39: 0 | M39: 0 | N39: 0 | O39: 0 | P39: 0 | Q39: 0 | R39: =K39+M39+Q39 -> 0 | S39: =R39*5% -> 0 | T39: =R39+S39 -> 0
... A81: 415 | B81: 25.09.20 | C81: 79 | D81: 415 | E81: 161000589 | F81: 58 | G81: 3465.82 | H81: 304.18 | I81: 0 | J81: 0 | K81: 0 | L81: 0 | M81: 0 | N81: 0 | O81: 0 | P81: 0 | Q81: 0 | R81: =K81+M81+Q81 -> 0 | S81: =R81*5% -> 0 | T81: =R81+S81 -> 0
A82: 416 | B82: 26.09.20 | C82: 80 | D82: 416 | E82: 161000590 | F82: 57 | G82: 3484.66 | H82: 224.9 | I82: 7.56 | J82: 4 | K82: 0 | L82: 1 | M82: 8550 | N82: 0 | Q82: 0 | R82: =K82+M82+Q82 -> 8550 | S82: =R82*5% -> 427.5 | T82: =R82+S82 -> 8977.5
A83: 417 | B83: 26.09.20 | C83: 81 | D83: 417 | E83: 161000591 | F83: 58 | G83: 3473.06 | H83: 294.53 | I83: 1.59 | J83: 1 | K83: 0 | L83: 1 | M83: 8700 | N83: 0 | Q83: 0 | R83: =K83+M83+Q83 -> 8700 | S83: =R83*5% -> 435 | T83: =R83+S83 -> 9135
A84: 418 | B84: 26.09.20 | C84: 82 | D84: 418 | E84: 141000035 | F84: 56 | G84: 3303.85 | H84: 335.15 | I84: 0 | J84: 0 | K84: 0 | L84: 0 | M84: 0 | N84: 2 | Q84: 29980 | R84: =K84+M84+Q84 -> 29980 | S84: =R84*5% -> 1499 | T84: =R84+S84 -> 31479 | U84: PILOT D.C
A85: 419 | B85: 28.09.20 | C85: 83 | D85: 419 | E85: 161000592 | F85: 59 | G85: 3520.21 | H85: 314.79 | I85: 0 | J85: 0 | K85: 0 | L85: 0 | M85: 0 | N85: 1 | Q85: 16000 | R85: =K85+M85+Q85 -> 16000 | S85: =R85*5% -> 800 | T85: =R85+S85 -> 16800 | U85: IMWB LINK FAILED
A86: 420 | B86: 28.09.20 | C86: 84 | D86: 420 | E86: 161000593 | F86: 57 | G86: 3424.86 | H86: 277.14 | I86: 0 | J86: 0 | K86: 0 | L86: 0 | M86: 0 | N86: 0 | O86: 0 | P86: 0 | Q86: 0 | R86: =K86+M86+Q86 -> 0 | S86: =R86*5% -> 0 | T86: =R86+S86 -> 0
A87: 421 | B87: 29.09.20 | C87: 85 | D87: 421 | E87: 161000594 | F87: 57 | G87: 3428.45 | H87: 274.55 | I87: 0 | J87: 0 | K87: 0 | L87: 0 | M87: 0 | N87: 0 | O87: 0 | P87: 0 | Q87: 0 | R87: =K87+M87+Q87 -> 0 | S87: =R87*5% -> 0 | T87: =R87+S87 -> 0
A88: 422 | B88: 29.09.20 | C88: 86 | D88: 422 | E88: 161000595 | F88: 58 | G88: 3492.67 | H88: 272.52 | I88: 0 | J88: 0 | K88: 0 | L88: 0 | M88: 0 | N88: 0 | O88: 0 | P88: 0 | Q88: 0 | R88: =K88+M88+Q88 -> 0 | S88: =R88*5% -> 0 | T88: =R88+S88 -> 0
A89: 423 | B89: 29.09.20 | C89: 87 | D89: 423 | E89: 161000596 | F89: 57 | G89: 3381.92 | H89: 315.48 | I89: 1.4 | J89: 1 | K89: 0 | L89: 1 | M89: 8550 | N89: 0 | Q89: 0 | R89: =K89+M89+Q89 -> 8550 | S89: =R89*5% -> 427.5 | T89: =R89+S89 -> 8977.5
A90: 424 | B90: 30.09.20 | C90: 88 | D90: 424 | E90: 161000597 | F90: 59 | G90: 3472.21 | H90: 362.79 | I90: 0 | J90: 0 | K90: 0 | L90: 0 | M90: 0 | N90: 0 | Q90: 0 | R90: =K90+M90+Q90 -> 0 | S90: =R90*5% -> 0 | T90: =R90+S90 -> 0
A91: 425 | B91: 30.09.20 | C91: 89 | D91: 425 | E91: 141000036 | F91: 58 | G91: 3474.82 | H91: 295.18 | I91: 0 | J91: 0 | K91: 0 | L91: 0 | M91: 0 | N91: 0 | Q91: 0 | R91: =K91+M91+Q91 -> 0 | S91: =R91*5% -> 0 | T91: =R91+S91 -> 0 | U91: 08.12.20
A92: 426 | B92: 30.09.20 | C92: 90 | D92: 426 | E92: 161000598 | F92: 54 | G92: 3273.07 | H92: 235.93 | I92: 0 | J92: 0 | K92: 0 | L92: 0 | M92: 0 | N92: 0 | Q92: 0 | R92: =K92+M92+Q92 -> 0 | S92: =R92*5% -> 0 | T92: =R92+S92 -> 0
A93: 427 | B93: 30.09.20 | C93: 91 | D93: 427 | E93: 161000599 | F93: 57 | G93: 3377.66 | H93: 235.93 | I93: 0 | J93: 0 | K93: 0 | L93: 0 | M93: 0 | N93: 0 | Q93: 0 | R93: =K93+M93+Q93 -> 0 | S93: =R93*5% -> 0 | T93: =R93+S93 -> 0
E94: TOTAL | F94: =SUM(F3:F93) -> 5311 | G94: =SUM(G3:G93) -> 314593.89 | H94: =SUM(H3:H93) -> 29466.34 | I94: =SUM(I3:I93) -> 10.55 | J94: =SUM(J3:J93) -> 6 | K94: =SUM(K3:K93) -> 0 | L94: =SUM(L3:L93) -> 3 | M94: =SUM(M3:M93) -> 25800 | ... S94: =SUM(S3:S93) -> 3589 | T94: =R94+S94 -> 75369
F95: =G94/C93 -> 3457.0757
S97: 16800
S98: 31479 | T98: =T94-S99 -> 27090
S99: =SUM(S97:S98) -> 48279

Sheet OCT
A1: OCTOBER MONTH RAKE LOADING DATA
A2: SL NO | B2: LOADING DATE | C2: RAKE NO. | D2: PRIORTY NUMBER | E2: R.R NUMBER | F2: NO OF WAGON | G2: NET WEIGHT | H2: UNDER LOAD WT | I2: OVER LOAD WT | J2: O/L WAGON | K2: O/L CHARGE | L2: DETENTION HOURS | M2: DETENTION CHARGES | N2: SHUNTING HOURS | O2: SHUNTING CHARGES | P2: PILOT HOURS | Q2: PILOT CHARGES | R2: PCLA | S2: GST 5% | T2: TOTAL AMOUNT RS
A3: 428 | B3: 01.10.20 | C3: 1 | D3: 428 | E3: 161000600 | F3: 58 | G3: 3449.22 | H3: 320.78 | I3: 0 | J3: 0 | K3: 0 | L3: 0 | M3: 0 | N3: 0 | O3: 0 | P3: 0 | Q3: 0 | R3: =K3+M3+Q3 -> 0 | S3: =R3*5% -> 0 | T3: =R3+S3 -> 0
A4: 429 | B4: 01.10.20 | C4: 2 | D4: 1 | E4: 141000037 | F4: 59 | G4: 3544.21 | H4: 290.79 | I4: 0 | J4: 0 | K4: 0 | L4: 0 | M4: 0 | N4: 0 | O4: 0 | P4: 0 | Q4: 0 | R4: =K4+M4+Q4 -> 0 | S4: =R4*5% -> 0 | T4: =R4+S4 -> 0
A5: 430 | B5: 01.10.20 | C5: 3 | D5: 2 | E5: 161000601 | F5: 59 | G5: 3512.63 | H5: 320.37 | I5: 0 | J5: 0 | K5: 0 | L5: 0 | M5: 0 | N5: 0 | O5: 0 | P5: 0 | Q5: 0 | R5: =K5+M5+Q5 -> 0 | S5: =R5*5% -> 0 | T5: =R5+S5 -> 0
A6: 431 | B6: 03.10.20 | C6: 4 | D6: 3 | E6: 161000602 | F6: 59 | G6: 3551.26 | H6: 278.74 | I6: 0 | J6: 0 | K6: 0 | L6: 0 | M6: 0 | N6: 0 | O6: 0 | P6: 0 | Q6: 0 | R6: =K6+M6+Q6 -> 0 | S6: =R6*5% -> 0 | T6: =R6+S6 -> 0
A7: 432 | B7: 06.10.20 | C7: 5 | D7: 4 | E7: 161000603 | F7: 59 | G7: 3484.43 | H7: 348.57 | I7: 0 | J7: 0 | K7: 0 | L7: 0 | M7: 0 | N7: 0 | O7: 0 | P7: 0 | Q7: 0 | R7: =K7+M7+Q7 -> 0 | S7: =R7*5% -> 0 | T7: =R7+S7 -> 0
A8: 433 | B8: 07.10.20 | C8: 6 | D8: 5 | E8: 161000604 | F8: 59 | G8: 3552.82 | H8: 281.18 | I8: 0 | J8: 0 | K8: 0 | L8: 0 | M8: 0 | N8: 0 | O8: 0 | P8: 0 | Q8: 0 | R8: =K8+M8+Q8 -> 0 | S8: =R8*5% -> 0 | T8: =R8+S8 -> 0
A9: 434 | B9: 07.10.20 | C9: 7 | D9: 6 | E9: 161000605 | F9: 58 | G9: 3479.25 | H9: 287.75 | I9: 0 | J9: 0 | K9: 0 | L9: 0 | M9: 0 | N9: 0 | O9: 0 | P9: 0 | Q9: 0 | R9: =K9+M9+Q9 -> 0 | S9: =R9*5% -> 0 | T9: =R9+S9 -> 0
A10: 435 | B10: 07.10.20 | C10: 8 | D10: 7 | E10: 161000606 | F10: 58 | G10: 3449.82 | H10: 320.18 | I10: 0 | J10: 0 | K10: 0 | L10: 0 | M10: 0 | N10: 0 | O10: 0 | P10: 0 | Q10: 0 | R10: =K10+M10+Q10 -> 0 | S10: =R10*5% -> 0 | T10: =R10+S10 -> 0
A11: 436 | B11: 07.10.20 | C11: 9 | D11: 8 | E11: 161000607 | F11: 59 | G11: 3563.22 | H11: 270.78 | I11: 0 | J11: 0 | K11: 0 | L11: 0 | M11: 0 | N11: 0 | O11: 0 | P11: 0 | Q11: 0 | R11: =K11+M11+Q11 -> 0 | S11: =R11*5% -> 0 | T11: =R11+S11 -> 0
A12: 437 | B12: 07.10.20 | C12: 10 | D12: 9 | E12: 161000608 | F12: 52 | G12: 3094.96 | H12: 277.83 | I12: 0 | J12: 1 | K12: 0 | L12: 1 | M12: 7800 | N12: 0 | O12: 0 | P12: 0 | Q12: 0 | R12: =K12+M12+Q12 -> 7800 | S12: =R12*5% -> 390 | T12: =R12+S12 -> 8190
A13: 438 | B13: 07.10.20 | C13: 11 | D13: 10 | E13: 161000609 | F13: 59 | G13: 3539.81 | H13: 295.19 | I13: 0 | J13: 0 | K13: 0 | L13: 0 | M13: 0 | N13: 0 | O13: 0 | P13: 0 | Q13: 0 | R13: =K13+M13+Q13 -> 0 | S13: =R13*5% -> 0 | T13: =R13+S13 -> 0
A14: 439 | B14: 08.10.20 | C14: 12 | D14: 11 | E14: 161000610 | F14: 59 | G14: 3548.22 | H14: 285.78 | I14: 0 | J14: 0 | K14: 0 | L14: 0 | M14: 0 | N14: 0 | O14: 0 | P14: 0 | Q14: 0 | R14: =K14+M14+Q14 -> 0 | S14: =R14*5% -> 0 | T14: =R14+S14 -> 0
... A30: 455 | B30: 12.10.20 | C30: 28 | D30: 27 | E30: 161000624 | F30: 58 | G30: 3474.02 | H30: 295.98 | I30: 0 | J30: 0 | K30: 0 | L30: 0 | M30: 0 | N30: 0 | O30: 0 | P30: 0 | Q30: 0 | R30: =K30+M30+Q30 -> 0 | S30: =R30*5% -> 0 | T30: =R30+S30 -> 0
A31: 456 | B31: 12.10.20 | C31: 29 | D31: 28 | E31: 141000039 | F31: 59 | G31: 3576.42 | H31: 257.58 | I31: 0 | J31: 0 | K31: 0 | L31: 0 | M31: 0 | N31: 0 | O31: 0 | P31: 0 | Q31: 0 | R31: =K31+M31+Q31 -> 0 | S31: =R31*5% -> 0 | T31: =R31+S31 -> 0 | U31: 13.10.20 | V31: SAMPLE SENT
A32: 457 | B32: 13.10.20 | C32: 30 | D32: 29 | E32: 142000001 | F32: 53 | G32: 3186.36 | H32: 249.64 | I32: 0 | J32: 0 | K32: 0 | L32: 0 | M32: 0 | N32: 0 | O32: 0 | P32: 0 | Q32: 0 | R32: =K32+M32+Q32 -> 0 | S32: =R32*5% -> 0 | T32: =R32+S32 -> 0
A33: 458 | B33: 13.10.20 | C33: 31 | D33: 30 | E33: 161000625 | F33: 59 | G33: 3556.82 | H33: 277.18 | I33: 0 | J33: 0 | K33: 0 | L33: 0 | M33: 0 | N33: 0 | O33: 0 | P33: 0 | Q33: 0 | R33: =K33+M33+Q33 -> 0 | S33: =R33*5% -> 0 | T33: =R33+S33 -> 0
A34: 459 | B34: 13.10.20 | C34: 32 | D34: 31 | E34: 161000626 | F34: 59 | G34: 3564.22 | H34: 269.78 | I34: 0 | J34: 0 | K34: 0 | L34: 0 | M34: 0 | N34: 0 | O34: 0 | P34: 0 | Q34: 0 | R34: =K34+M34+Q34 -> 0 | S34: =R34*5% -> 0 | T34: =R34+S34 -> 0
A35: 460 | B35: 13.10.20 | C35: 33 | D35: 32 | E35: 141000040 | F35: 59 | G35: 3558.01 | H35: 276.99 | I35: 0 | J35: 0 | K35: 0 | L35: 0 | M35: 0 | N35: 0 | O35: 0 | P35: 0 | Q35: 0 | R35: =K35+M35+Q35 -> 0 | S35: =R35*5% -> 0 | T35: =R35+S35 -> 0
A36: 461 | B36: 13.10.20 | C36: 34 | D36: 33 | E36: 162000012 | F36: 59 | G36: 3527.81 | H36: 307.19 | I36: 0 | J36: 0 | K36: 0 | L36: 0 | M36: 0 | N36: 0 | O36: 0 | P36: 0 | Q36: 0 | R36: =K36+M36+Q36 -> 0 | S36: =R36*5% -> 0 | T36: =R36+S36 -> 0
A37: 462 | B37: 14.10.20 | C37: 35 | D37: 34 | E37: 161000627 | F37: 58 | G37: 3486.83 | H37: 282.17 | I37: 0 | J37: 0 | K37: 0 | L37: 0 | M37: 0 | N37: 0 | O37: 0 | P37: 0 | Q37: 0 | R37: =K37+M37+Q37 -> 0 | S37: =R37*5% -> 0 | T37: =R37+S37 -> 0
A38: 463 | B38: 14.10.20 | C38: 36 | D38: 35 | E38: 161000628 | F38: 59 | G38: 3539.26 | H38: 290.74 | I38: 0 | J38: 0 | K38: 0 | L38: 0 | M38: 0 | N38: 0 | O38: 0 | P38: 0 | Q38: 0 | R38: =K38+M38+Q38 -> 0 | S38: =R38*5% -> 0 | T38: =R38+S38 -> 0
A39: 464 | B39: 14.10.20 | C39: 37 | D39: 36 | E39: 161000629 | F39: 58 | G39: 3515.42 | H39: 254.58 | I39: 0 | J39: 0 | K39: 0 | L39: 0 | M39: 0 | N39: 0 | O39: 0 | P39: 0 | Q39: 0 | R39: =K39+M39+Q39 -> 0 | S39: =R39*5% -> 0 | T39: =R39+S39 -> 0
A40: 465 | B40: 14.10.20 | C40: 38 | D40: 37 | E40: 161000630 | F40: 58 | G40: 3526.82 | H40: 243.18 | I40: 0 | J40: 0 | K40: 0 | L40: 0 | M40: 0 | N40: 0 | O40: 0 | P40: 0 | Q40: 0 | R40: =K40+M40+Q40 -> 0 | S40: =R40*5% -> 0 | T40: =R40+S40 -> 0
A41: 466 | B41: 14.10.20 | C41: 39 | D41: 38 | E41: 161000631 | F41: 58 | G41: 3462.62 | H41: 307.38 | I41: 0 | J41: 0 | K41: 0 | L41: 0 | M41: 0 | N41: 0 | O41: 0 | P41: 0 | Q41: 0 | R41: =K41+M41+Q41 -> 0 | S41: =R41*5% -> 0 | T41: =R41+S41 -> 0
A42: 467 | B42: 15.10.20 | C42: 40 | D42: 39 | E42: 161000632 | F42: 57 | G42: 3427.83 | H42: 277.17 | I42: 0 | J42: 0 | K42: 0 | L42: 0 | M42: 0 | N42: 0 | O42: 0 | P42: 0 | Q42: 0 | R42: =K42+M42+Q42 -> 0 | S42: =R42*5% -> 0 | T42: =R42+S42 -> 0
A43: 468 | B43: 15.10.20 | C43: 41 | D43: 40 | E43: 161000633 | F43: 57 | G43: 3392.23 | H43: 312.77 | I43: 0 | J43: 0 | K43: 0 | L43: 0 | M43: 0 | N43: 0 | O43: 0 | P43: 0 | Q43: 0 | R43: =K43+M43+Q43 -> 0 | S43: =R43*5% -> 0 | T43: =R43+S43 -> 0
... A57: 482 | B57: 17.10.20 | C57: 55 | D57: 54 | E57: 161000644 | F57: 57 | G57: 3407.44 | H57: 296.56 | I57: 0 | J57: 0 | K57: 0 | L57: 0 | M57: 0 | N57: 0 | O57: 0 | P57: 0 | Q57: 0 | R57: =K57+M57+Q57 -> 0 | S57: =R57*5% -> 0 | T57: =R57+S57 -> 0
A58: 483 | B58: 17.10.20 | C58: 56 | D58: 55 | E58: 141000041 | F58: 58 | G58: 3493.42 | H58: 276.58 | I58: 0 | J58: 0 | K58: 0 | L58: 0 | M58: 0 | N58: 0 | O58: 0 | P58: 0 | Q58: 0 | R58: =K58+M58+Q58 -> 0 | S58: =R58*5% -> 0 | T58: =R58+S58 -> 0 | U58: 22.10.20 SAMPLE SENT
A59: 484 | B59: 23.10.20 | C59: 57 | D59: 56 | E59: 161000645 | F59: 59 | G59: 3561.22 | H59: 272.78 | I59: 0 | J59: 0 | K59: 0 | L59: 0 | M59: 0 | N59: 0 | O59: 0 | P59: 0 | Q59: 0 | R59: =K59+M59+Q59 -> 0 | S59: =R59*5% -> 0 | T59: =R59+S59 -> 0
A60: 485 | B60: 23.10.20 | C60: 58 | D60: 57 | E60: 161000646 | F60: 57 | G60: 3433.43 | H60: 271.57 | I60: 0 | J60: 0 | K60: 0 | L60: 0 | M60: 0 | N60: 0 | O60: 0 | P60: 0 | Q60: 0 | R60: =K60+M60+Q60 -> 0 | S60: =R60*5% -> 0 | T60: =R60+S60 -> 0
A61: 486 | B61: 23.10.20 | C61: 59 | D61: 58 | E61: 161000647 | F61: 58 | G61: 3474.03 | H61: 294.97 | I61: 0 | J61: 0 | K61: 0 | L61: 0 | M61: 0 | N61: 0 | O61: 0 | P61: 0 | Q61: 0 | R61: =K61+M61+Q61 -> 0 | S61: =R61*5% -> 0 | T61: =R61+S61 -> 0
A62: 487 | B62: 23.10.20 | C62: 60 | D62: 59 | E62: 161000648 | F62: 58 | G62: 3473.02 | H62: 296.98 | I62: 0 | J62: 0 | K62: 0 | L62: 0 | M62: 0 | N62: 0 | O62: 0 | P62: 0 | Q62: 0 | R62: =K62+M62+Q62 -> 0 | S62: =R62*5% -> 0 | T62: =R62+S62 -> 0
A63: 488 | B63: 24.10.20 | C63: 61 | D63: 60 | E63: 161000649 | F63: 59 | G63: 3549.22 | H63: 284.78 | I63: 0 | J63: 0 | K63: 0 | L63: 0 | M63: 0 | N63: 0 | O63: 0 | P63: 0 | Q63: 0 | R63: =K63+M63+Q63 -> 0 | S63: =R63*5% -> 0 | T63: =R63+S63 -> 0
A64: 489 | B64: 24.10.20 | C64: 62 | D64: 61 | E64: 161000650 | F64: 58 | G64: 3401.03 | H64: 367.97 | I64: 0 | J64: 0 | K64: 0 | L64: 0 | M64: 0 | N64: 0 | O64: 0 | P64: 0 | Q64: 0 | R64: =K64+M64+Q64 -> 0 | S64: =R64*5% -> 0 | T64: =R64+S64 -> 0
A65: 490 | B65: 25.10.20 | C65: 63 | D65: 62 | E65: 161000651 | F65: 59 | G65: 3561.44 | H65: 270.56 | I65: 0 | J65: 0 | K65: 0 | L65: 0 | M65: 0 | N65: 0 | O65: 0 | P65: 0 | Q65: 0 | R65: =K65+M65+Q65 -> 0 | S65: =R65*5% -> 0 | T65: =R65+S65 -> 0
A66: 491 | B66: 25.10.20 | C66: 64 | D66: 63 | E66: 162000016 | F66: 58 | G66: 3503.33 | H66: 255.67 | I66: 0 | J66: 0 | K66: 0 | L66: 0 | M66: 0 | N66: 0 | O66: 0 | P66: 0 | Q66: 0 | R66: =K66+M66+Q66 -> 0 | S66: =R66*5% -> 0 | T66: =R66+S66 -> 0
A67: 492 | B67: 26.10.20 | C67: 65 | D67: 64 | E67: 161000652 | F67: 59 | G67: 3583.62 | H67: 250.38 | I67: 0 | J67: 0 | K67: 0 | L67: 0 | M67: 0 | N67: 0 | O67: 0 | P67: 0 | Q67: 0 | R67: =K67+M67+Q67 -> 0 | S67: =R67*5% -> 0 | T67: =R67+S67 -> 0
A68: 493 | B68: 26.10.20 | C68: 66 | D68: 65 | E68: 161000653 | F68: 55 | G68: 3331.91 | H68: 237.09 | I68: 0 | J68: 0 | K68: 0 | L68: 0 | M68: 0 | N68: 0 | O68: 0 | P68: 0 | Q68: 0 | R68: =K68+M68+Q68 -> 0 | S68: =R68*5% -> 0 | T68: =R68+S68 -> 0
A69: 494 | B69: 26.10.20 | C69: 67 | D69: 66 | E69: 161000654 | F69: 58 | G69: 3484.43 | H69: 284.57 | I69: 0 | J69: 0 | K69: 0 | L69: 0 | M69: 0 | N69: 0 | O69: 0 | P69: 0 | Q69: 0 | R69: =K69+M69+Q69 -> 0 | S69: =R69*5% -> 0 | T69: =R69+S69 -> 0
A70: 495 | B70: 26.10.20 | C70: 68 | D70: 67 | E70: 161000655 | F70: 59 | G70: 3565.61 | H70: 269.39 | I70: 0 | J70: 0 | K70: 0 | L70: 0 | M70: 0 | N70: 0 | O70: 0 | P70: 0 | Q70: 0 | R70: =K70+M70+Q70 -> 0 | S70: =R70*5% -> 0 | T70: =R70+S70 -> 0
... A75: 500 | B75: 28.10.20 | C75: 73 | D75: 72 | E75: 161000659 | F75: 59 | G75: 3574.61 | H75: 260.39 | I75: 0 | J75: 0 | K75: 0 | L75: 0 | M75: 0 | N75: 0 | O75: 0 | P75: 0 | Q75: 0 | R75: =K75+M75+Q75 -> 0 | S75: =R75*5% -> 0 | T75: =R75+S75 -> 0
A76: 501 | B76: 28.10.20 | C76: 74 | D76: 73 | E76: 162000018 | F76: 57 | G76: 3437.86 | H76: 413.34 | I76: 0 | J76: 1 | K76: 0 | L76: 1 | M76: 8500 | N76: 0 | O76: 0 | P76: 0 | Q76: 0 | R76: =K76+M76+Q76 -> 8500 | S76: =R76*5% -> 425 | T76: =R76+S76 -> 8925 | U76: 4.2
A77: 502 | B77: 28.10.20 | C77: 75 | D77: 74 | E77: 161000660 | F77: 59 | G77: 3485.87 | H77: 348.13 | I77: 0 | J77: 0 | K77: 0 | L77: 0 | M77: 0 | N77: 0 | O77: 0 | P77: 0 | Q77: 0 | R77: =K77+M77+Q77 -> 0 | S77: =R77*5% -> 0 | T77: =R77+S77 -> 0
A78: 503 | B78: 28.10.20 | C78: 76 | D78: 75 | E78: 161000661 | F78: 56 | G78: 3370.44 | H78: 269.56 | I78: 0 | J78: 0 | K78: 0 | L78: 0 | M78: 0 | N78: 0 | O78: 0 | P78: 0 | Q78: 0 | R78: =K78+M78+Q78 -> 0 | S78: =R78*5% -> 0 | T78: =R78+S78 -> 0
A79: 504 | B79: 28.10.20 | C79: 77 | D79: 76 | E79: 161000662 | F79: 59 | G79: 3577.22 | H79: 256.78 | I79: 0 | J79: 0 | K79: 0 | L79: 0 | M79: 0 | N79: 0 | O79: 0 | P79: 0 | Q79: 0 | R79: =K79+M79+Q79 -> 0 | S79: =R79*5% -> 0 | T79: =R79+S79 -> 0
A80: 505 | B80: 28.10.20 | C80: 78 | D80: 77 | E80: 162000019 | F80: 57 | G80: 3408.63 | H80: 296.37 | I80: 0 | J80: 0 | K80: 0 | L80: 0 | M80: 0 | N80: 0 | O80: 0 | P80: 0 | Q80: 0 | R80: =K80+M80+Q80 -> 0 | S80: =R80*5% -> 0 | T80: =R80+S80 -> 0
A81: 506 | B81: 28.10.20 | C81: 79 | D81: 78 | E81: 161000663 | F81: 59 | G81: 3505.22 | H81: 328.78 | I81: 0 | J81: 0 | K81: 0 | L81: 0 | M81: 0 | N81: 0 | O81: 0 | P81: 0 | Q81: 0 | R81: =K81+M81+Q81 -> 0 | S81: =R81*5% -> 0 | T81: =R81+S81 -> 0
A82: 507 | B82: 29.10.20 | C82: 80 | D82: 79 | E82: 161000664 | F82: 51 | G82: 3085.34 | H82: 224.66 | I82: 0 | J82: 0 | K82: 0 | L82: 0 | M82: 0 | N82: 0 | O82: 0 | P82: 0 | Q82: 0 | R82: =K82+M82+Q82 -> 0 | S82: =R82*5% -> 0 | T82: =R82+S82 -> 0
A83: 508 | B83: 29.10.20 | C83: 81 | D83: 80 | E83: 161000665 | F83: 55 | G83: 3301.85 | H83: 273.15 | I83: 0 | J83: 0 | K83: 0 | L83: 0 | M83: 0 | N83: 0 | O83: 0 | P83: 0 | Q83: 0 | R83: =K83+M83+Q83 -> 0 | S83: =R83*5% -> 0 | T83: =R83+S83 -> 0
A84: 509 | B84: 29.10.20 | C84: 82 | D84: 81 | E84: 161000667 | F84: 59 | G84: 3556.61 | H84: 278.39 | I84: 0 | J84: 0 | K84: 0 | L84: 0 | M84: 0 | N84: 0 | O84: 0 | P84: 0 | Q84: 0 | R84: =K84+M84+Q84 -> 0 | S84: =R84*5% -> 0 | T84: =R84+S84 -> 0
A85: 510 | B85: 29.10.20 | C85: 83 | D85: 82 | E85: 161000668 | F85: 58 | G85: 3509.62 | H85: 260.57 | I85: 0 | J85: 0 | K85: 0 | L85: 0 | M85: 0 | N85: 0 | O85: 0 | P85: 0 | Q85: 0 | R85: =K85+M85+Q85 -> 0 | S85: =R85*5% -> 0 | T85: =R85+S85 -> 0
A86: 511 | B86: 29.10.20 | C86: 84 | D86: 83 | E86: 161000666 | F86: 58 | G86: 3481.03 | H86: 287.97 | I86: 0 | J86: 0 | K86: 0 | L86: 0 | M86: 0 | N86: 0 | O86: 0 | P86: 0 | Q86: 0 | R86: =K86+M86+Q86 -> 0 | S86: =R86*5% -> 0 | T86: =R86+S86 -> 0
A87: 512 | B87: 29.10.20 | C87: 85 | D87: 84 | E87: 161000669 | F87: 59 | G87: 3561.02 | H87: 273.57 | I87: 0 | J87: 0 | K87: 0 | L87: 0 | M87: 0 | N87: 0 | O87: 0 | P87: 0 | Q87: 0 | R87: =K87+M87+Q87 -> 0 | S87: =R87*5% -> 0 | T87: =R87+S87 -> 0
A88: 513 | B88: 30.10.20 | C88: 86 | D88: 85 | E88: 161000670 | F88: 58 | G88: 3511.82 | H88: 322.18 | I88: 0 | J88: 0 | K88: 0 | L88: 0 | M88: 0 | N88: 0 | O88: 0 | P88: 0 | Q88: 0 | R88: =K88+M88+Q88 -> 0 | S88: =R88*5% -> 0 | T88: =R88+S88 -> 0
... A92: 517 | B92: 30.10.20 | C92: 90 | D92: 89 | E92: 162000020 | F92: 54 | G92: 3210.12 | H92: 293.88 | I92: 0 | J92: 0 | K92: 0 | L92: 0 | M92: 0 | N92: 0 | O92: 0 | P92: 0 | Q92: 0 | R92: =K92+M92+Q92 -> 0 | S92: =R92*5% -> 0 | T92: =R92+S92 -> 0
A93: 518 | B93: 30.10.20 | C93: 91 | D93: 90 | E93: 161000675 | F93: 59 | G93: 3534.04 | H93: 298.05 | I93: 0 | J93: 0 | K93: 0 | L93: 0 | M93: 0 | N93: 1 | O93: 0 | P93: 0 | Q93: 14990 | R93: =K93+M93+Q93 -> 14990 | S93: =R93*5% -> 749.5 | T93: =R93+S93 -> 15739.5 | U93: PILOT D.C/TRACK CLEANING
A94: 519 | B94: 30.10.20 | C94: 92 | D94: 91 | E94: 161000674 | F94: 59 | G94: 3573.12 | H94: 260.88 | I94: 0 | J94: 0 | K94: 0 | L94: 0 | M94: 0 | N94: 0 | O94: 0 | P94: 0 | Q94: 0 | R94: =K94+M94+Q94 -> 0 | S94: =R94*5% -> 0 | T94: =R94+S94 -> 0
A95: 520 | B95: 31.10.20 | C95: 93 | D95: 93 | E95: 161000677 | F95: 58 | G95: 3511.47 | H95: 253.63 | I95: 0 | J95: 0 | K95: 0 | L95: 0 | M95: 0 | N95: 4 | O95: 0 | P95: 0 | Q95: 59960 | R95: =K95+M95+Q95 -> 59960 | S95: =R95*5% -> 2998 | T95: =R95+S95 -> 62958 | U95: PILOT D.C/ELECTRIC WIRE DAMAGED
A96: 521 | B96: 31.10.20 | C96: 94 | D96: 94 | E96: 161000676 | F96: 59 | G96: 3529.28 | H96: 298.72 | I96: 0 | J96: 0 | K96: 0 | L96: 0 | M96: 0 | N96: 0 | O96: 0 | P96: 0 | Q96: 0 | R96: =K96+M96+Q96 -> 0 | S96: =R96*5% -> 0 | T96: =R96+S96 -> 0
A97: 522 | B97: 31.10.20 | C97: 95 | D97: 95 | E97: 161000678 | F97: 59 | G97: 3516.82 | H97: 317.18 | I97: 0 | J97: 0 | K97: 0 | L97: 0 | M97: 0 | N97: 0 | O97: 0 | P97: 0 | Q97: 0 | R97: =K97+M97+Q97 -> 0 | S97: =R97*5% -> 0 | T97: =R97+S97 -> 0
A98: 523 | B98: 31.10.20 | C98: 96 | D98: 96 | E98: 161000679 | F98: 60 | G98: 3621.22 | H98: 214.34 | I98: 0 | J98: 0 | K98: 0 | L98: 0 | M98: 0 | N98: 0 | O98: 0 | P98: 0 | Q98: 0 | R98: =K98+M98+Q98 -> 0 | S98: =R98*5% -> 0 | T98: =R98+S98 -> 0
A99: 524 | B99: 31.10.20 | C99: 97 | D99: 92 | E99: 162000021 | F99: 58 | G99: 3520.42 | H99: 249.58 | I99: 0 | J99: 0 | K99: 0 | L99: 0 | M99: 0 | N99: 0 | O99: 0 | P99: 0 | Q99: 0 | R99: =K99+M99+Q99 -> 0 | S99: =R99*5% -> 0 | T99: =R99+S99 -> 0
E100: TOTAL | F100: =SUM(F3:F99) -> 5620 | G100: =SUM(G3:G99) -> 337319.2 | H100: =SUM(H3:H99) -> 28058.28 | I100: =SUM(I3:I99) -> 0 | J100: =SUM(J3:J99) -> 2 | K100: =SUM(K3:K99) -> 0 | L100: =SUM(L3:L99) -> 2 | M100: =SUM(M3:M99) -> 16300 | ... T100: =SUM(T3:T99) -> 95812.5
F101: =G100/C99 -> 3477.5175 | U101: 62958
U102: 15739.5
T103: =T100-U103 -> 17115 | U103: =SUM(U101:U102) -> 78697.5

Sheet NOV
A1: NOVEMBER MONTH RAKE LOADING DATA
A2: SL NO | B2: LOADING DATE | C2: RAKE NO. | D2: PRIORTY NUMBER | E2: R.R NUMBER | F2: NO OF WAGON | G2: NET WEIGHT | H2: UNDER LOAD WT | I2: OVER LOAD WT | J2: O/L WAGON | K2: O/L CHARGE | L2: DETENTION HOURS | M2: DETENTION CHARGES | N2: SHUNTING HOURS | O2: SHUNTING CHARGES | P2: PILOT HOURS | Q2: PILOT CHARGES | R2: PCLA | S2: GST 5% | T2: TOTAL AMOUNT RS | U2: RESULT DATE
A3: 525 | B3: 01.11.20 | C3: 1 | D3: 97 | E3: 161000680 | F3: 58 | G3: 3526.43 | H3: 242.57 | I3: 0 | J3: 0 | K3: 0 | L3: 0 | M3: 0 | N3: 0 | O3: 0 | P3: 0 | Q3: 0 | R3: =K3+M3+Q3 -> 0 | S3: =R3*5% -> 0 | T3: =R3+S3 -> 0
A4: 526 | B4: 01.11.20 | C4: 2 | D4: 98 | E4: 161000681 | F4: 59 | G4: 3589.64 | H4: 242.36 | I4: 0 | J4: 0 | K4: 0 | L4: 0 | M4: 0 | N4: 0 | O4: 0 | P4: 0 | Q4: 0 | R4: =K4+M4+Q4 -> 0 | S4: =R4*5% -> 0 | T4: =R4+S4 -> 0
A5: 527 | B5: 01.11.20 | C5: 3 | D5: 99 | E5: 162000022 | F5: 59 | G5: 3592.42 | H5: 241.58 | I5: 0 | J5: 0 | K5: 0 | L5: 0 | M5: 0 | N5: 0 | O5: 0 | P5: 0 | Q5: 0 | R5: =K5+M5+Q5 -> 0 | S5: =R5*5% -> 0 | T5: =R5+S5 -> 0
A6: 528 | B6: 01.11.20 | C6: 4 | D6: 100 | E6: 161000682 | F6: 59 | G6: 3570.84 | H6: 261.16 | I6: 0 | J6: 0 | K6: 0 | L6: 0 | M6: 0 | N6: 0 | O6: 0 | P6: 0 | Q6: 0 | R6: =K6+M6+Q6 -> 0 | S6: =R6*5% -> 0 | T6: =R6+S6 -> 0
A7: 529 | B7: 01.11.20 | C7: 5 | D7: 101 | E7: 161000683 | F7: 58 | G7: 3429.04 | H7: 338.96 | I7: 0 | J7: 0 | K7: 0 | L7: 0 | M7: 0 | N7: 0 | O7: 0 | P7: 0 | Q7: 0 | R7: =K7+M7+Q7 -> 0 | S7: =R7*5% -> 0 | T7: =R7+S7 -> 0
A8: 530 | B8: 02.11.20 | C8: 6 | D8: 102 | E8: 161000684 | F8: 57 | G8: 3393.48 | H8: 306.52 | I8: 0 | J8: 0 | K8: 0 | L8: 0 | M8: 0 | N8: 0 | O8: 0 | P8: 0 | Q8: 0 | R8: =K8+M8+Q8 -> 0 | S8: =R8*5% -> 0 | T8: =R8+S8 -> 0
A9: 531 | B9: 02.11.20 | C9: 7 | D9: 103 | E9: 161000685 | F9: 58 | G9: 3492.62 | H9: 277.38 | I9: 0 | J9: 0 | K9: 0 | L9: 0 | M9: 0 | N9: 0 | O9: 0 | P9: 0 | Q9: 0 | R9: =K9+M9+Q9 -> 0 | S9: =R9*5% -> 0 | T9: =R9+S9 -> 0
A10: 532 | B10: 02.11.20 | C10: 8 | D10: 104 | E10: 162000023 | F10: 57 | G10: 3400.63 | H10: 304.37 | I10: 0 | J10: 0 | K10: 0 | L10: 0 | M10: 0 | N10: 0 | O10: 0 | P10: 0 | Q10: 0 | R10: =K10+M10+Q10 -> 0 | S10: =R10*5% -> 0 | T10: =R10+S10 -> 0
A11: 533 | B11: 02.11.20 | C11: 9 | D11: 105 | E11: 161000686 | F11: 59 | G11: 3500.04 | H11: 331.96 | I11: 0 | J11: 0 | K11: 0 | L11: 0 | M11: 0 | N11: 0 | O11: 0 | P11: 0 | Q11: 0 | R11: =K11+M11+Q11 -> 0 | S11: =R11*5% -> 0 | T11: =R11+S11 -> 0
A12: 534 | B12: 02.11.20 | C12: 10 | D12: 106 | E12: 161000687 | F12: 59 | G12: 3562.22 | H12: 271.78 | I12: 0 | J12: 0 | K12: 0 | L12: 0 | M12: 0 | N12: 0 | O12: 0 | P12: 0 | Q12: 0 | R12: =K12+M12+Q12 -> 0 | S12: =R12*5% -> 0 | T12: =R12+S12 -> 0
A13: 535 | B13: 02.11.20 | C13: 11 | D13: 107 | E13: 161000688 | F13: 59 | G13: 3492.22 | H13: 341.78 | I13: 0 | J13: 0 | K13: 0 | L13: 0 | M13: 0 | N13: 0 | O13: 0 | P13: 0 | Q13: 0 | R13: =K13+M13+Q13 -> 0 | S13: =R13*5% -> 0 | T13: =R13+S13 -> 0
A14: 536 | B14: 03.11.20 | C14: 12 | D14: 108 | E14: 161000689 | F14: 58 | G14: 3477.03 | H14: 291.97 | I14: 0 | J14: 0 | K14: 0 | L14: 0 | M14: 0 | N14: 0 | O14: 0 | P14: 0 | Q14: 0 | R14: =K14+M14+Q14 -> 0 | S14: =R14*5% -> 0 | T14: =R14+S14 -> 0
... A41: 563 | B41: 07.11.20 | C41: 39 | D41: 133 | E41: 161000708 | F41: 58 | G41: 3503.82 | H41: 266.18 | I41: 0 | J41: 0 | K41: 0 | L41: 0 | M41: 0 | N41: 0 | O41: 0 | P41: 0 | Q41: 0 | R41: =K41+M41+Q41 -> 0 | S41: =R41*5% -> 0 | T41: =R41+S41 -> 0
A42: 564 | B42: 07.11.20 | C42: 40 | D42: 135 | E42: 161000709 | F42: 58 | G42: 3503.46 | H42: 460.54 | I42: 0 | J42: 0 | K42: 0 | L42: 0 | M42: 0 | N42: 1 | O42: 0 | P42: 0 | Q42: 8700 | R42: =K42+M42+Q42 -> 8700 | S42: =R42*5% -> 435 | T42: =R42+S42 -> 9135 | V42: LOADING DELAY (ABOVE 3 HOURS)
A43: 565 | B43: 07.11.20 | C43: 41 | D43: 137 | E43: 161000710 | F43: 57 | G43: 3445.84 | H43: 258.16 | I43: 0 | J43: 0 | K43: 0 | L43: 0 | M43: 0 | N43: 0 | O43: 0 | P43: 0 | Q43: 0 | R43: =K43+M43+Q43 -> 0 | S43: =R43*5% -> 0 | T43: =R43+S43 -> 0
A44: 566 | B44: 07.11.20 | C44: 42 | D44: 138 | E44: 141000042 | F44: 59 | G44: 3578.61 | H44: 256.39 | I44: 0 | J44: 0 | K44: 0 | L44: 0 | M44: 0 | N44: 0 | O44: 0 | P44: 0 | Q44: 0 | R44: =K44+M44+Q44 -> 0 | S44: =R44*5% -> 0 | T44: =R44+S44 -> 0
A45: 567 | B45: 08.11.20 | C45: 43 | D45: 139 | E45: 161000711 | F45: 58 | G45: 3569.42 | H45: 200.58 | I45: 0 | J45: 0 | K45: 0 | L45: 0 | M45: 0 | N45: 0 | O45: 0 | P45: 0 | Q45: 0 | R45: =K45+M45+Q45 -> 0 | S45: =R45*5% -> 0 | T45: =R45+S45 -> 0
A46: 568 | B46: 08.11.20 | C46: 44 | D46: 140 | E46: 161000712 | F46: 59 | G46: 3618.42 | H46: 215.97 | I46: 0 | J46: 0 | K46: 0 | L46: 0 | M46: 0 | N46: 0 | O46: 0 | P46: 0 | Q46: 0 | R46: =K46+M46+Q46 -> 0 | S46: =R46*5% -> 0 | T46: =R46+S46 -> 0
A47: 569 | B47: 08.11.20 | C47: 45 | D47: 141 | E47: 151000022 | F47: 58 | G47: 3538.22 | H47: 232.17 | I47: 0 | J47: 0 | K47: 0 | L47: 0 | M47: 0 | N47: 0 | O47: 0 | P47: 0 | Q47: 0 | R47: =K47+M47+Q47 -> 0 | S47: =R47*5% -> 0 | T47: =R47+S47 -> 0
A48: 570 | B48: 08.11.20 | C48: 46 | D48: 142 | E48: 152000001 | F48: 59 | G48: 3596.02 | H48: 237.98 | I48: 0 | J48: 0 | K48: 0 | L48: 0 | M48: 0 | N48: 0 | O48: 0 | P48: 0 | Q48: 0 | R48: =K48+M48+Q48 -> 0 | S48: =R48*5% -> 0 | T48: =R48+S48 -> 0
A49: 571 | B49: 08.11.20 | C49: 47 | D49: 144 | E49: 151000023 | F49: 59 | G49: 3569.02 | H49: 264.98 | I49: 0 | J49: 0 | K49: 0 | L49: 0 | M49: 0 | N49: 0 | O49: 0 | P49: 0 | Q49: 0 | R49: =K49+M49+Q49 -> 0 | S49: =R49*5% -> 0 | T49: =R49+S49 -> 0
A50: 572 | B50: 09.11.20 | C50: 48 | D50: 143 | E50: 151000024 | F50: 59 | G50: 3575.03 | H50: 257.97 | I50: 0 | J50: 0 | K50: 0 | L50: 0 | M50: 0 | N50: 0 | O50: 0 | P50: 0 | Q50: 0 | R50: =K50+M50+Q50 -> 0 | S50: =R50*5% -> 0 | T50: =R50+S50 -> 0
A51: 573 | B51: 09.11.20 | C51: 49 | D51: 145 | E51: 151000025 | F51: 58 | G51: 3544.03 | H51: 224.97 | I51: 0 | J51: 0 | K51: 0 | L51: 0 | M51: 0 | N51: 0 | O51: 0 | P51: 0 | Q51: 0 | R51: =K51+M51+Q51 -> 0 | S51: =R51*5% -> 0 | T51: =R51+S51 -> 0
A52: 574 | B52: 09.11.20 | C52: 50 | D52: 146 | E52: 152000002 | F52: 58 | G52: 3491.03 | H52: 277.97 | I52: 0 | J52: 0 | K52: 0 | L52: 0 | M52: 0 | N52: 0 | O52: 0 | P52: 0 | Q52: 0 | R52: =K52+M52+Q52 -> 0 | S52: =R52*5% -> 0 | T52: =R52+S52 -> 0
A53: 575 | B53: 09.11.20 | C53: 51 | D53: 147 | E53: 161000713 | F53: 58 | G53: 3533.63 | H53: 235.37 | I53: 0 | J53: 0 | K53: 0 | L53: 0 | M53: 0 | N53: 0 | O53: 0 | P53: 0 | Q53: 0 | R53: =K53+M53+Q53 -> 0 | S53: =R53*5% -> 0 | T53: =R53+S53 -> 0
A54: 576 | B54: 09.11.20 | C54: 52 | D54: 149 | E54: 161000714 | F54: 59 | G54: 3608.82 | H54: 225.37 | I54: 0 | J54: 0 | K54: 0 | L54: 0 | M54: 0 | N54: 0 | O54: 0 | P54: 0 | Q54: 0 | R54: =K54+M54+Q54 -> 0 | S54: =R54*5% -> 0 | T54: =R54+S54 -> 0
... A61: 583 | B61: 10.11.20 | C61: 59 | D61: 155 | E61: 162000033 | F61: 57 | G61: 3415.23 | H61: 289.77 | I61: 0 | J61: 0 | K61: 0 | L61: 0 | M61: 0 | N61: 0 | O61: 0 | P61: 0 | Q61: 0 | R61: =K61+M61+Q61 -> 0 | S61: =R61*5% -> 0 | T61: =R61+S61 -> 0
A62: 584 | B62: 11.11.20 | C62: 60 | D62: 156 | E62: 161000720 | F62: 59 | G62: 3524.61 | H62: 310.39 | I62: 0 | J62: 0 | K62: 0 | L62: 0 | M62: 0 | N62: 0 | O62: 0 | P62: 0 | Q62: 0 | R62: =K62+M62+Q62 -> 0 | S62: =R62*5% -> 0 | T62: =R62+S62 -> 0 | U62: 08.12.20
A63: 585 | B63: 11.11.20 | C63: 61 | D63: 158 | E63: 162000034 | F63: 58 | G63: 3480.63 | H63: 288.37 | I63: 0 | J63: 0 | K63: 0 | L63: 0 | M63: 0 | N63: 0 | O63: 0 | P63: 0 | Q63: 0 | R63: =K63+M63+Q63 -> 0 | S63: =R63*5% -> 0 | T63: =R63+S63 -> 0
A64: 586 | B64: 11.11.20 | C64: 62 | D64: 157 | E64: 161000721 | F64: 58 | G64: 3519.42 | H64: 250.58 | I64: 0 | J64: 0 | K64: 0 | L64: 0 | M64: 0 | N64: 0 | O64: 0 | P64: 0 | Q64: 0 | R64: =K64+M64+Q64 -> 0 | S64: =R64*5% -> 0 | T64: =R64+S64 -> 0 | U64: 08.12.20
A65: 587 | B65: 11.11.20 | C65: 63 | D65: 159 | E65: 161000722 | F65: 58 | G65: 3481.43 | H65: 287.57 | I65: 0 | J65: 0 | K65: 0 | L65: 0 | M65: 0 | N65: 0 | O65: 0 | P65: 0 | Q65: 0 | R65: =K65+M65+Q65 -> 0 | S65: =R65*5% -> 0 | T65: =R65+S65 -> 0 | U65: 04.12.20
A66: 588 | B66: 11.11.20 | C66: 64 | D66: 161 | E66: 151000026 | F66: 59 | G66: 3570.04 | H66: 261.96 | I66: 0 | J66: 0 | K66: 0 | L66: 0 | M66: 0 | N66: 0 | O66: 0 | P66: 0 | Q66: 0 | R66: =K66+M66+Q66 -> 0 | S66: =R66*5% -> 0 | T66: =R66+S66 -> 0 | U66: 08.12.20
A67: 589 | B67: 11.11.20 | C67: 65 | D67: 160 | E67: 161000723 | F67: 54 | G67: 3277.69 | H67: 229.31 | I67: 0 | J67: 0 | K67: 0 | L67: 0 | M67: 0 | N67: 0 | O67: 0 | P67: 0 | Q67: 0 | R67: =K67+M67+Q67 -> 0 | S67: =R67*5% -> 0 | T67: =R67+S67 -> 0 | U67: 04.12.20
A68: 590 | B68: 11.11.20 | C68: 66 | D68: 162 | E68: 162000035 | F68: 59 | G68: 3569.23 | H68: 263.77 | I68: 0 | J68: 0 | K68: 0 | L68: 0 | M68: 0 | N68: 0 | O68: 0 | P68: 0 | Q68: 0 | R68: =K68+M68+Q68 -> 0 | S68: =R68*5% -> 0 | T68: =R68+S68 -> 0
A69: 591 | B69: 12.11.20 | C69: 67 | D69: 165 | E69: 161000724 | F69: 58 | G69: 3514.08 | H69: 249.92 | I69: 0 | J69: 0 | K69: 0 | L69: 0 | M69: 0 | N69: 0 | O69: 0 | P69: 0 | Q69: 0 | R69: =K69+M69+Q69 -> 0 | S69: =R69*5% -> 0 | T69: =R69+S69 -> 0 | U69: 08.12.20
A70: 592 | B70: 12.11.20 | C70: 68 | D70: 163 | E70: 161000725 | F70: 59 | G70: 3610.04 | H70: 221.96 | I70: 0 | J70: 0 | K70: 0 | L70: 0 | M70: 0 | N70: 0 | O70: 0 | P70: 0 | Q70: 0 | R70: =K70+M70+Q70 -> 0 | S70: =R70*5% -> 0 | T70: =R70+S70 -> 0 | U70: 04.12.20
A71: 593 | B71: 12.11.20 | C71: 69 | D71: 164 | E71: 151000027 | F71: 59 | G71: 3548.02 | H71: 285.98 | I71: 0 | J71: 0 | K71: 0 | L71: 0 | M71: 0 | N71: 0 | O71: 0 | P71: 0 | Q71: 0 | R71: =K71+M71+Q71 -> 0 | S71: =R71*5% -> 0 | T71: =R71+S71 -> 0 | U71: 08.12.20
A72: 594 | B72: 12.11.20 | C72: 70 | D72: 167 | E72: 152000003 | F72: 58 | G72: 3467.63 | H72: 301.37 | I72: 0 | J72: 0 | K72: 0 | L72: 0 | M72: 0 | N72: 0 | O72: 0 | P72: 0 | Q72: 0 | R72: =K72+M72+Q72 -> 0 | S72: =R72*5% -> 0 | T72: =R72+S72 -> 0
A73: 595 | B73: 12.11.20 | C73: 71 | D73: 166 | E73: 161000726 | F73: 57 | G73: 3467.03 | H73: 237.97 | I73: 0 | J73: 0 | K73: 0 | L73: 0 | M73: 0 | N73: 0 | O73: 0 | P73: 0 | Q73: 0 | R73: =K73+M73+Q73 -> 0 | S73: =R73*5% -> 0 | T73: =R73+S73 -> 0
A74: 596 | B74: 12.11.20 | C74: 72 | D74: 168 | E74: 161000727 | F74: 58 | G74: 3508.44 | H74: 259.56 | I74: 0 | J74: 0 | K74: 0 | L74: 0 | M74: 0 | N74: 0 | O74: 0 | P74: 0 | Q74: 0 | R74: =K74+M74+Q74 -> 0 | S74: =R74*5% -> 0 | T74: =R74+S74 -> 0 | U74: 08.12.20
A75: 597 | B75: 12.11.20 | C75: 73 | D75: 169 | E75: 161000728 | F75: 56 | G75: 3378.64 | H75: 261.36 | I75: 0 | J75: 0 | K75: 0 | L75: 0 | M75: 0 | N75: 0 | O75: 0 | P75: 0 | Q75: 0 | R75: =K75+M75+Q75 -> 0 | S75: =R75*5% -> 0 | T75: =R75+S75 -> 0
A76: 598 | B76: 13.11.20 | C76: 74 | D76: 170 | E76: 151000028 | F76: 58 | G76: 3493.82 | H76: 276.18 | I76: 0 | J76: 0 | K76: 0 | L76: 0 | M76: 0 | N76: 0 | O76: 0 | P76: 0 | Q76: 0 | R76: =K76+M76+Q76 -> 0 | S76: =R76*5% -> 0 | T76: =R76+S76 -> 0 | U76: 08.12.20
A77: 599 | B77: 13.11.20 | C77: 75 | D77: 171 | E77: 151000029 | F77: 58 | G77: 3477.42 | H77: 292.58 | I77: 0 | J77: 0 | K77: 0 | L77: 0 | M77: 0 | N77: 0 | O77: 0 | P77: 0 | Q77: 0 | R77: =K77+M77+Q77 -> 0 | S77: =R77*5% -> 0 | T77: =R77+S77 -> 0 | U77: 08.12.20
A78: 600 | B78: 13.11.20 | C78: 76 | D78: 172 | E78: 152000004 | F78: 59 | G78: 3505.81 | H78: 329.19 | I78: 0 | J78: 0 | K78: 0 | L78: 0 | M78: 0 | N78: 0 | O78: 0 | P78: 0 | Q78: 0 | R78: =K78+M78+Q78 -> 0 | S78: =R78*5% -> 0 | T78: =R78+S78 -> 0
A79: 601 | B79: 13.11.20 | C79: 77 | D79: 173 | E79: 161000729 | F79: 53 | G79: 3187.99 | H79: 255.51 | I79: 0.57 | J79: 0 | K79: 0 | L79: 1 | M79: 7950 | N79: 0 | O79: 0 | P79: 0 | Q79: 0 | R79: =K79+M79+Q79 -> 7950 | S79: =R79*5% -> 397.5 | T79: =R79+S79 -> 8347.5 | U79: 08.12.20 | V79: PAKUR WEIGHMENT,LOTT VILLAGERS ISSUE SAHIB BOLERO DEMAND
A80: 602 | B80: 13.11.20 | C80: 78 | D80: 174 | E80: 161000730 | F80: 59 | G80: 3554.21 | H80: 280.79 | I80: 0 | J80: 0 | K80: 0 | L80: 0 | M80: 0 | N80: 0 | O80: 0 | P80: 0 | Q80: 0 | R80: =K80+M80+Q80 -> 0 | S80: =R80*5% -> 0 | T80: =R80+S80 -> 0 | U80: 08.12.20 | V80: LOADING DELAY (ABOVE 3 HOURS)
A81: 603 | B81: 13.11.20 | C81: 79 | D81: 175 | E81: 141000043 | F81: 59 | G81: 3494.42 | H81: 339.58 | I81: 0 | J81: 0 | K81: 0 | L81: 0 | M81: 0 | N81: 0 | O81: 0 | P81: 0 | Q81: 0 | R81: =K81+M81+Q81 -> 0 | S81: =R81*5% -> 0 | T81: =R81+S81 -> 0 | U81: 04.12.20
A82: 604 | B82: 13.11.20 | C82: 80 | D82: 176 | E82: 161000731 | F82: 59 | G82: 3495.24 | H82: 336.76 | I82: 0 | J82: 0 | K82: 0 | L82: 0 | M82: 0 | N82: 0 | O82: 0 | P82: 0 | Q82: 0 | R82: =K82+M82+Q82 -> 0 | S82: =R82*5% -> 0 | T82: =R82+S82 -> 0 | U82: 08.12.20
A83: 605 | B83: 14.11.20 | C83: 81 | D83: 178 | E83: 161000732 | F83: 58 | G83: 3482.63 | H83: 286.37 | I83: 0 | J83: 0 | K83: 0 | L83: 0 | M83: 0 | N83: 0 | O83: 0 | P83: 0 | Q83: 0 | R83: =K83+M83+Q83 -> 0 | S83: =R83*5% -> 0 | T83: =R83+S83 -> 0 | U83: 04.12.20
A84: 606 | B84: 14.11.20 | C84: 82 | D84: 177 | E84: 162000036 | F84: 57 | G84: 3433.85 | H84: 269.15 | I84: 0 | J84: 0 | K84: 0 | L84: 0 | M84: 0 | N84: 0 | O84: 0 | P84: 0 | Q84: 0 | R84: =K84+M84+Q84 -> 0 | S84: =R84*5% -> 0 | T84: =R84+S84 -> 0 | U84: 08.12.20
A85: 607 | B85: 14.11.20 | C85: 83 | D85: 179 | E85: 161000733 | F85: 59 | G85: 3548.61 | H85: 286.39 | I85: 0 | J85: 0 | K85: 0 | L85: 0 | M85: 0 | N85: 0 | O85: 0 | P85: 0 | Q85: 0 | R85: =K85+M85+Q85 -> 0 | S85: =R85*5% -> 0 | T85: =R85+S85 -> 0 | U85: 04.12.20
A86: 608 | B86: 15.11.20 | C86: 84 | D86: 180 | E86: 161000734 | F86: 58 | G86: 3534.22 | H86: 235.78 | I86: 0 | J86: 0 | K86: 0 | L86: 0 | M86: 0 | N86: 0 | O86: 0 | P86: 0 | Q86: 0 | R86: =K86+M86+Q86 -> 0 | S86: =R86*5% -> 0 | T86: =R86+S86 -> 0 | U86: 08.12.20
A87: 609 | B87: 15.11.20 | C87: 85 | D87: 181 | E87: 161000735 | F87: 56 | G87: 3463.44 | H87: 176.56 | I87: 0 | J87: 0 | K87: 0 | L87: 0 | M87: 0 | N87: 0 | O87: 0 | P87: 0 | Q87: 0 | R87: =K87+M87+Q87 -> 0 | S87: =R87*5% -> 0 | T87: =R87+S87 -> 0
A88: 610 | B88: 15.11.20 | C88: 86 | D88: 182 | E88: 161000736 | F88: 59 | G88: 3574.23 | H88: 258.77 | I88: 0 | J88: 0 | K88: 0 | L88: 0 | M88: 0 | N88: 0 | O88: 0 | P88: 0 | Q88: 0 | R88: =K88+M88+Q88 -> 0 | S88: =R88*5% -> 0 | T88: =R88+S88 -> 0 | U88: 08.12.20
A89: 611 | B89: 16.11.20 | C89: 87 | D89: 183 | E89: 161000737 | F89: 58 | G89: 3534.03 | H89: 234.97 | I89: 0 | J89: 0 | K89: 0 | L89: 0 | M89: 0 | N89: 0 | O89: 0 | P89: 0 | Q89: 0 | R89: =K89+M89+Q89 -> 0 | S89: =R89*5% -> 0 | T89: =R89+S89 -> 0 | U89: 08.12.20
A90: 612 | B90: 16.11.20 | C90: 88 | D90: 184 | E90: 141000044 | F90: 59 | G90: 3570.62 | H90: 263.38 | I90: 0 | J90: 0 | K90: 0 | L90: 0 | M90: 0 | N90: 0 | O90: 0 | P90: 0 | Q90: 0 | R90: =K90+M90+Q90 -> 0 | S90: =R90*5% -> 0 | T90: =R90+S90 -> 0 | U90: 04.12.20
A91: 613 | B91: 16.11.20 | C91: 89 | D91: 187 | E91: 161000738 | F91: 58 | G91: 3467.44 | H91: 300.56 | I91: 0 | J91: 0 | K91: 0 | L91: 0 | M91: 0 | N91: 0 | O91: 0 | P91: 0 | Q91: 0 | R91: =K91+M91+Q91 -> 0 | S91: =R91*5% -> 0 | T91: =R91+S91 -> 0 | U91: 08.12.20
A92: 614 | B92: 16.11.20 | C92: 90 | D92: 185 | E92: 161000739 | F92: 59 | G92: 3536.26 | H92: 293.74 | I92: 0 | J92: 0 | K92: 0 | L92: 0 | M92: 0 | N92: 0 | O92: 0 | P92: 0 | Q92: 0 | R92: =K92+M92+Q92 -> 0 | S92: =R92*5% -> 0 | T92: =R92+S92 -> 0 | U92: 04.12.20
A93: 615 | B93: 16.11.20 | C93: 91 | D93: 188 | E93: 162000037 | F93: 59 | G93: 3534.04 | H93: 299.16 | I93: 0 | J93: 0 | K93: 0 | L93: 0 | M93: 0 | N93: 0 | O93: 0 | P93: 0 | Q93: 0 | R93: =K93+M93+Q93 -> 0 | S93: =R93*5% -> 0 | T93: =R93+S93 -> 0 | U93: 08.12.20
A94: 616 | B94: 16.11.20 | C94: 92 | D94: 186 | E94: 161000740 | F94: 59 | G94: 3544.01 | H94: 290.99 | I94: 0 | J94: 0 | K94: 0 | L94: 0 | M94: 0 | N94: 0 | O94: 0 | P94: 0 | Q94: 0 | R94: =K94+M94+Q94 -> 0 | S94: =R94*5% -> 0 | T94: =R94+S94 -> 0 | U94: 04.12.20
A95: 617 | B95: 17.11.20 | C95: 93 | D95: 189 | E95: 161000741 | F95: 57 | G95: 3440.03 | H95: 264.97 | I95: 0 | J95: 0 | K95: 0 | L95: 0 | M95: 0 | N95: 0 | O95: 0 | P95: 0 | Q95: 0 | R95: =K95+M95+Q95 -> 0 | S95: =R95*5% -> 0 | T95: =R95+S95 -> 0 | U95: 08.12.20
A96: 618 | B96: 17.11.20 | C96: 94 | D96: 190 | E96: 161000742 | F96: 58 | G96: 3492.22 | H96: 279.17 | I96: 1.39 | J96: 1 | K96: 0 | L96: 1 | M96: 8700 | N96: 1 | O96: 0 | P96: 0 | Q96: 14090 | R96: =K96+M96+Q96 -> 22790 | S96: =R96*5% -> 1139.5 | T96: =R96+S96 -> 23929.5
A97: 619 | B97: 17.11.20 | C97: 95 | D97: 192 | E97: 161000743 | F97: 58 | G97: 3480.62 | H97: 289.38 | I97: 0 | J97: 0 | K97: 0 | L97: 0 | M97: 0 | N97: 0 | O97: 0 | P97: 0 | Q97: 0 | R97: =K97+M97+Q97 -> 0 | S97: =R97*5% -> 0 | T97: =R97+S97 -> 0 | U97: 04.12.20
A98: 620 | B98: 17.11.20 | C98: 96 | D98: 193 | E98: 161000744 | F98: 59 | G98: 3528.22 | H98: 305.78 | I98: 0 | J98: 0 | K98: 0 | L98: 0 | M98: 0 | N98: 0 | O98: 0 | P98: 0 | Q98: 0 | R98: =K98+M98+Q98 -> 0 | S98: =R98*5% -> 0 | T98: =R98+S98 -> 0 | U98: 04.12.20
A99: 621 | B99: 17.11.20 | C99: 97 | D99: 191 | E99: 162000038 | F99: 58 | G99: 3491.23 | H99: 277.77 | I99: 0 | J99: 0 | K99: 0 | L99: 0 | M99: 0 | N99: 0 | O99: 0 | P99: 0 | Q99: 0 | R99: =K99+M99+Q99 -> 0 | S99: =R99*5% -> 0 | T99: =R99+S99 -> 0
A100: 622 | B100: 18.11.20 | C100: 98 | D100: 194 | E100: 151000030 | F100: 59 | G100: 3559.82 | H100: 274.18 | I100: 0 | J100: 0 | K100: 0 | L100: 0 | M100: 0 | N100: 0 | O100: 0 | P100: 0 | Q100: 0 | R100: =K100+M100+Q100 -> 0 | S100: =R100*5% -> 0 | T100: =R100+S100 -> 0 | U100: 08.12.20
A101: 623 | B101: 18.11.20 | C101: 99 | D101: 196 | E101: 151000031 | F101: 54 | G101: 3228.7 | H101: 278.1 | I101: 0.8 | J101: 0 | K101: 0 | L101: 0 | M101: 0 | N101: 0 | O101: 0 | P101: 0 | Q101: 0 | R101: =K101+M101+Q101 -> 0 | S101: =R101*5% -> 0 | T101: =R101+S101 -> 0 | U101: 08.12.20
A102: 624 | B102: 18.11.20 | C102: 100 | D102: 195 | E102: 151000032 | F102: 59 | G102: 3539.42 | H102: 294.58 | I102: 0 | J102: 0 | K102: 0 | L102: 0 | M102: 0 | N102: 0 | O102: 0 | P102: 0 | Q102: 0 | R102: =K102+M102+Q102 -> 0 | S102: =R102*5% -> 0 | T102: =R102+S102 -> 0 | U102: 08.12.20
A103: 625 | B103: 18.11.20 | C103: 101 | D103: 197 | E103: 152000005 | F103: 59 | G103: 3520.61 | H103: 314.39 | I103: 0 | J103: 0 | K103: 0 | L103: 0 | M103: 0 | N103: 0 | O103: 0 | P103: 0 | Q103: 0 | R103: =K103+M103+Q103 -> 0 | S103: =R103*5% -> 0 | T103: =R103+S103 -> 0
A104: 626 | B104: 18.11.20 | C104: 102 | D104: 198 | E104: 161000745 | F104: 58 | G104: 3467.24 | H104: 301.75 | I104: 0.99 | J104: 1 | K104: 0 | L104: 1 | M104: 8700 | N104: 0 | O104: 0 | P104: 0 | Q104: 0 | R104: =K104+M104+Q104 -> 8700 | S104: =R104*5% -> 435 | T104: =R104+S104 -> 9135 | U104: 08.12.20
A105: 627 | B105: 18.11.20 | C105: 103 | D105: 199 | E105: 161000746 | F105: 58 | G105: 3482.22 | H105: 287.78 | I105: 0 | J105: 0 | K105: 0 | L105: 0 | M105: 0 | N105: 0 | O105: 0 | P105: 0 | Q105: 0 | R105: =K105+M105+Q105 -> 0 | S105: =R105*5% -> 0 | T105: =R105+S105 -> 0 | U105: 04.12.20
A106: 628 | B106: 18.11.20 | C106: 104 | D106: 200 | E106: 161000747 | F106: 59 | G106: 3519.21 | H106: 315.79 | I106: 0 | J106: 0 | K106: 0 | L106: 0 | M106: 0 | N106: 0 | O106: 0 | P106: 0 | Q106: 0 | R106: =K106+M106+Q106 -> 0 | S106: =R106*5% -> 0 | T106: =R106+S106 -> 0 | U106: 08.12.20
A107: 629 | B107: 19.11.20 | C107: 105 | D107: 204 | E107: 161000748 | F107: 59 | G107: 3506.82 | H107: 327.18 | I107: 0 | J107: 0 | K107: 0 | L107: 0 | M107: 0 | N107: 0 | O107: 0 | P107: 0 | Q107: 0 | R107: =K107+M107+Q107 -> 0 | S107: =R107*5% -> 0 | T107: =R107+S107 -> 0 | U107: 04.12.20
A108: 630 | B108: 19.11.20 | C108: 106 | D108: 201 | E108: 162000039 | F108: 58 | G108: 3454.82 | H108: 315.18 | I108: 0 | J108: 0 | K108: 0 | L108: 0 | M108: 0 | N108: 0 | O108: 0 | P108: 0 | Q108: 0 | R108: =K108+M108+Q108 -> 0 | S108: =R108*5% -> 0 | T108: =R108+S108 -> 0
A109: 631 | B109: 19.11.20 | C109: 107 | D109: 202 | E109: 161000749 | F109: 59 | G109: 3494.42 | H109: 339.58 | I109: 0 | J109: 0 | K109: 0 | L109: 0 | M109: 0 | N109: 0 | O109: 0 | P109: 0 | Q109: 0 | R109: =K109+M109+Q109 -> 0 | S109: =R109*5% -> 0 | T109: =R109+S109 -> 0 | U109: 08.12.20
A110: 632 | B110: 19.11.20 | C110: 108 | D110: 203 | E110: 161000750 | F110: 57 | G110: 3346.65 | H110: 356.94 | I110: 0 | J110: 0 | K110: 0 | L110: 0 | M110: 0 | N110: 0 | O110: 0 | P110: 0 | Q110: 0 | R110: =K110+M110+Q110 -> 0 | S110: =R110*5% -> 0 | T110: =R110+S110 -> 0 | U110: 08.12.20
A111: 633 | B111: 19.11.20 | C111: 109 | D111: 205 | E111: 162000040 | F111: 57 | G111: 3446.09 | H111: 255.29 | I111: 2.38 | J111: 1 | K111: 0 | L111: 1 | M111: 8550 | N111: 0 | O111: 0 | P111: 0 | Q111: 0 | R111: =K111+M111+Q111 -> 8550 | S111: =R111*5% -> 427.5 | T111: =R111+S111 -> 8977.5
A112: 634 | B112: 19.11.20 | C112: 110 | D112: 206 | E112: 162000041 | F112: 58 | G112: 3456.02 | H112: 313.98 | I112: 0 | J112: 0 | K112: 0 | L112: 0 | M112: 0 | N112: 0 | O112: 0 | P112: 0 | Q112: 0 | R112: =K112+M112+Q112 -> 0 | S112: =R112*5% -> 0 | T112: =R112+S112 -> 0
A113: 635 | B113: 19.11.20 | C113: 111 | D113: 207 | E113: 161000751 | F113: 58 | G113: 3450.44 | H113: 317.56 | I113: 0 | J113: 0 | K113: 0 | L113: 0 | M113: 0 | N113: 0 | O113: 0 | P113: 0 | Q113: 0 | R113: =K113+M113+Q113 -> 0 | S113: =R113*5% -> 0 | T113: =R113+S113 -> 0 | U113: 08.12.20
A114: 636 | B114: 20.11.20 | C114: 112 | D114: 208 | E114: 161000752 | F114: 58 | G114: 3502.42 | H114: 267.58 | I114: 0 | J114: 0 | K114: 0 | L114: 0 | M114: 0 | N114: 0 | O114: 0 | P114: 0 | Q114: 0 | R114: =K114+M114+Q114 -> 0 | S114: =R114*5% -> 0 | T114: =R114+S114 -> 0 | U114: 08.12.20
A115: 637 | B115: 20.11.20 | C115: 113 | D115: 210 | E115: 162000042 | F115: 59 | G115: 3525.01 | H115: 309.99 | I115: 0 | J115: 0 | K115: 0 | L115: 0 | M115: 0 | N115: 0 | O115: 0 | P115: 0 | Q115: 0 | R115: =K115+M115+Q115 -> 0 | S115: =R115*5% -> 0 | T115: =R115+S115 -> 0
A116: 638 | B116: 20.11.20 | C116: 114 | D116: 209 | E116: 161000753 | F116: 58 | G116: 3473.63 | H116: 295.37 | I116: 0 | J116: 0 | K116: 0 | L116: 0 | M116: 0 | N116: 0 | O116: 0 | P116: 0 | Q116: 0 | R116: =K116+M116+Q116 -> 0 | S116: =R116*5% -> 0 | T116: =R116+S116 -> 0 | U116: 08.12.20
A117: 639 | B117: 20.11.20 | C117: 115 | D117: 212 | E117: 162000043 | F117: 59 | G117: 3524.61 | H117: 310.39 | I117: 0 | J117: 0 | K117: 0 | L117: 0 | M117: 0 | N117: 0 | O117: 0 | P117: 0 | Q117: 0 | R117: =K117+M117+Q117 -> 0 | S117: =R117*5% -> 0 | T117: =R117+S117 -> 0
A118: 640 | B118: 20.11.20 | C118: 116 | D118: 211 | E118: 161000754 | F118: 59 | G118: 3524.22 | H118: 309.78 | I118: 0 | J118: 0 | K118: 0 | L118: 0 | M118: 0 | N118: 0 | O118: 0 | P118: 0 | Q118: 0 | R118: =K118+M118+Q118 -> 0 | S118: =R118*5% -> 0 | T118: =R118+S118 -> 0 | U118: 08.12.20 | V118: 23.11.20 SENT TO SGTPP
A119: 641 | B119: 21.11.20 | C119: 117 | D119: 213 | E119: 162000044 | F119: 56 | G119: 3388.84 | H119: 251.16 | I119: 0 | J119: 0 | K119: 0 | L119: 0 | M119: 0 | N119: 0 | O119: 0 | P119: 0 | Q119: 0 | R119: =K119+M119+Q119 -> 0 | S119: =R119*5% -> 0 | T119: =R119+S119 -> 0 | U119: 16.12.20
A120: 642 | B120: 21.11.20 | C120: 118 | D120: 214 | E120: 161000755 | F120: 59 | G120: 3606.81 | H120: 232.15 | I120: 3.96 | J120: 2 | K120: 0 | L120: 1 | M120: 8850 | N120: 0 | O120: 0 | P120: 0 | Q120: 0 | R120: =K120+M120+Q120 -> 8850 | S120: =R120*5% -> 442.5 | T120: =R120+S120 -> 9292.5 | U120: 16.12.20
A121: 643 | B121: 21.11.20 | C121: 119 | D121: 215 | E121: 162000045 | F121: 59 | G121: 3504.22 | H121: 329.78 | I121: 0 | J121: 0 | K121: 0 | L121: 0 | M121: 0 | N121: 0 | O121: 0 | P121: 0 | Q121: 0 | R121: =K121+M121+Q121 -> 0 | S121: =R121*5% -> 0 | T121: =R121+S121 -> 0 | U121: 16.12.20
A122: 644 | B122: 22.11.20 | C122: 120 | D122: 216 | E122: 161000756 | F122: 57 | G122: 3351.04 | H122: 352.96 | I122: 0 | J122: 0 | K122: 0 | L122: 0 | M122: 0 | N122: 0 | O122: 0 | P122: 0 | Q122: 0 | R122: =K122+M122+Q122 -> 0 | S122: =R122*5% -> 0 | T122: =R122+S122 -> 0 | U122: 16.12.20
A123: 645 | B123: 22.11.20 | C123: 121 | D123: 217 | E123: 161000757 | F123: 58 | G123: 3438.84 | H123: 329.16 | I123: 0 | J123: 0 | K123: 0 | L123: 0 | M123: 0 | N123: 0 | O123: 0 | P123: 0 | Q123: 0 | R123: =K123+M123+Q123 -> 0 | S123: =R123*5% -> 0 | T123: =R123+S123 -> 0 | U123: 16.12.20
A124: 646 | B124: 22.11.20 | C124: 122 | D124: 218 | E124: 152000006 | F124: 59 | G124: 3539.02 | H124: 294.98 | I124: 0 | J124: 0 | K124: 0 | L124: 0 | M124: 0 | N124: 0 | O124: 0 | P124: 0 | Q124: 0 | R124: =K124+M124+Q124 -> 0 | S124: =R124*5% -> 0 | T124: =R124+S124 -> 0 | U124: 16.12.20
A125: 647 | B125: 22.11.20 | C125: 123 | D125: 221 | E125: 161000758 | F125: 59 | G125: 3490.21 | H125: 344.79 | I125: 0 | J125: 0 | K125: 0 | L125: 0 | M125: 0 | N125: 0 | O125: 0 | P125: 0 | Q125: 0 | R125: =K125+M125+Q125 -> 0 | S125: =R125*5% -> 0 | T125: =R125+S125 -> 0 | U125: 16.12.20
A126: 648 | B126: 23.11.20 | C126: 124 | D126: 219 | E126: 151000033 | F126: 58 | G126: 3409.84 | H126: 358.16 | I126: 0 | J126: 0 | K126: 0 | L126: 0 | M126: 0 | N126: 0 | O126: 0 | P126: 0 | Q126: 0 | R126: =K126+M126+Q126 -> 0 | S126: =R126*5% -> 0 | T126: =R126+S126 -> 0 | U126: 16.12.20
A127: 649 | B127: 23.11.20 | C127: 125 | D127: 220 | E127: 151000034 | F127: 59 | G127: 3455.63 | H127: 313.37 | I127: 0 | J127: 0 | K127: 0 | L127: 0 | M127: 0 | N127: 0 | O127: 0 | P127: 0 | Q127: 0 | R127: =K127+M127+Q127 -> 0 | S127: =R127*5% -> 0 | T127: =R127+S127 -> 0 | U127: 16.12.20
A128: 650 | B128: 23.11.20 | C128: 126 | D128: 222 | E128: 151000035 | F128: 58 | G128: 3501.24 | H128: 267.15 | I128: 0 | J128: 0 | K128: 0 | L128: 0 | M128: 0 | N128: 0 | O128: 0 | P128: 0 | Q128: 0 | R128: =K128+M128+Q128 -> 0 | S128: =R128*5% -> 0 | T128: =R128+S128 -> 0 | U128: 16.12.20
A129: 651 | B129: 23.11.20 | C129: 127 | D129: 223 | E129: 151000036 | F129: 59 | G129: 3535.83 | H129: 297.17 | I129: 0 | J129: 0 | K129: 0 | L129: 0 | M129: 0 | N129: 0 | O129: 0 | P129: 0 | Q129: 0 | R129: =K129+M129+Q129 -> 0 | S129: =R129*5% -> 0 | T129: =R129+S129 -> 0 | U129: 16.12.20
A130: 652 | B130: 23.11.20 | C130: 128 | D130: 224 | E130: 161000759 | F130: 58 | G130: 3483.42 | H130: 286.58 | I130: 0 | J130: 0 | K130: 0 | L130: 0 | M130: 0 | N130: 0 | O130: 0 | P130: 0 | Q130: 0 | R130: =K130+M130+Q130 -> 0 | S130: =R130*5% -> 0 | T130: =R130+S130 -> 0 | U130: 16.12.20
... A139: 661 | B139: 25.11.20 | C139: 137 | D139: 233 | E139: 161000763 | F139: 59 | G139: 3508.43 | H139: 324.57 | I139: 0 | J139: 0 | K139: 0 | L139: 0 | M139: 0 | N139: 0 | O139: 0 | P139: 0 | Q139: 0 | R139: =K139+M139+Q139 -> 0 | S139: =R139*5% -> 0 | T139: =R139+S139 -> 0 | U139: 16.12.20
A140: 662 | B140: 25.11.20 | C140: 138 | D140: 231 | E140: 161000764 | F140: 60 | G140: 3651.47 | H140: 372.53 | I140: 0 | J140: 0 | K140: 0 | L140: 0 | M140: 0 | N140: 0 | O140: 0 | P140: 0 | Q140: 0 | R140: =K140+M140+Q140 -> 0 | S140: =R140*5% -> 0 | T140: =R140+S140 -> 0 | U140: 16.12.20 | V140: BOXN
...

Sheet DEC
A1: DECEMBER MONTH RAKE LOADING DATA
A2: SL NO | B2: LOADING DATE | C2: RAKE NO. | D2: PRIORTY NUMBER | E2: R.R NUMBER | F2: NO OF WAGON | G2: NET WEIGHT | H2: UNDER LOAD WT | I2: OVER LOAD WT | J2: O/L WAGON | K2: O/L CHARGE | L2: DETENTION HOURS | M2: DETENTION CHARGES | N2: SHUNTING HOURS | O2: SHUNTING CHARGES | P2: PILOT HOURS | Q2: PILOT CHARGES | R2: PCLA | S2: GST 5% | T2: TOTAL AMOUNT RS | U2: DESTINATION | V2: RESULT DATE
A3: 1 | B3: 01.12.20 | C3: 1 | D3: 262 | E3: 151000039 | F3: 58 | G3: 3426.44 | H3: 341.56 | I3: 0 | J3: 0 | K3: 0 | L3: 0 | M3: 0 | N3: 0 | Q3: 0 | R3: =K3+M3+Q3 -> 0 | S3: =R3*5% -> 0 | T3: =R3+S3 -> 0 | U3: PSPM
A4: 2 | B4: 01.12.20 | C4: 2 | D4: 264 | E4: 151000040 | F4: 59 | G4: 3526.62 | H4: 307.38 | I4: 0 | J4: 0 | K4: 0 | L4: 0 | M4: 0 | N4: 0 | Q4: 0 | R4: =K4+M4+Q4 -> 0 | S4: =R4*5% -> 0 | T4: =R4+S4 -> 0 | U4: PSPM
A5: 3 | B5: 01.12.20 | C5: 3 | D5: 267 | E5: 152000007 | F5: 57 | G5: 3373.03 | H5: 331.97 | I5: 0 | J5: 0 | K5: 0 | L5: 0 | M5: 0 | N5: 0 | Q5: 0 | R5: =K5+M5+Q5 -> 0 | S5: =R5*5% -> 0 | T5: =R5+S5 -> 0 | U5: STPS
A6: 4 | B6: 01.12.20 | C6: 4 | D6: 265 | E6: 141000046 | F6: 59 | G6: 3508.81 | H6: 326.19 | I6: 0 | J6: 0 | K6: 0 | L6: 0 | M6: 0 | N6: 0 | Q6: 0 | R6: =K6+M6+Q6 -> 0 | S6: =R6*5% -> 0 | T6: =R6+S6 -> 0 | U6: PSPM
A7: 5 | B7: 01.12.20 | C7: 5 | D7: 269 | E7: 141000047 | F7: 57 | G7: 3399.67 | H7: 301.33 | I7: 0 | J7: 0 | K7: 0 | L7: 0 | M7: 0 | N7: 0 | Q7: 0 | R7: =K7+M7+Q7 -> 0 | S7: =R7*5% -> 0 | T7: =R7+S7 -> 0 | U7: BTPC
A8: 6 | B8: 01.12.20 | C8: 6 | D8: 268 | E8: 151000041 | F8: 58 | G8: 3453.24 | H8: 314.76 | I8: 0 | J8: 0 | K8: 0 | L8: 0 | M8: 0 | N8: 0 | Q8: 0 | R8: =K8+M8+Q8 -> 0 | S8: =R8*5% -> 0 | T8: =R8+S8 -> 0 | U8: PSPM
A9: 7 | B9: 02.12.20 | C9: 7 | D9: 270 | E9: 151000042 | F9: 59 | G9: 3529.62 | H9: 304.38 | I9: 0 | J9: 0 | K9: 0 | L9: 0 | M9: 0 | N9: 0 | Q9: 0 | R9: =K9+M9+Q9 -> 0 | S9: =R9*5% -> 0 | T9: =R9+S9 -> 0 | U9: PSPM
A10: 8 | B10: 02.12.20 | C10: 8 | D10: 271 | E10: 151000043 | F10: 55 | G10: 3290.11 | H10: 278.89 | I10: 0 | J10: 0 | K10: 0 | L10: 0 | M10: 0 | N10: 0 | Q10: 0 | R10: =K10+M10+Q10 -> 0 | S10: =R10*5% -> 0 | T10: =R10+S10 -> 0 | U10: BTPC
A11: 9 | B11: 02.12.20 | C11: 9 | D11: 272 | E11: 161000786 | F11: 58 | G11: 3452.64 | H11: 315.36 | I11: 0 | J11: 0 | K11: 0 | L11: 0 | M11: 0 | N11: 0 | Q11: 0 | R11: =K11+M11+Q11 -> 0 | S11: =R11*5% -> 0 | T11: =R11+S11 -> 0 | U11: PSPM
A12: 10 | B12: 02.12.20 | C12: 10 | D12: 273 | E12: 161000787 | F12: 57 | G12: 3370.04 | H12: 333.96 | I12: 0 | J12: 0 | K12: 0 | L12: 0 | M12: 0 | N12: 0 | Q12: 0 | R12: =K12+M12+Q12 -> 0 | S12: =R12*5% -> 0 | T12: =R12+S12 -> 0 | U12: PSPM
A13: 11 | B13: 02.12.20 | C13: 11 | D13: 276 | E13: 161000788 | F13: 59 | G13: 3572.42 | H13: 261.58 | I13: 0 | J13: 0 | K13: 0 | L13: 0 | M13: 0 | N13: 0 | Q13: 0 | R13: =K13+M13+Q13 -> 0 | S13: =R13*5% -> 0 | T13: =R13+S13 -> 0 | U13: BTPC
A14: 12 | B14: 03.12.20 | C14: 12 | D14: 274 | E14: 151000044 | F14: 58 | G14: 3490.64 | H14: 277.36 | I14: 0 | J14: 0 | K14: 0 | L14: 0 | M14: 0 | N14: 0 | Q14: 0 | R14: =K14+M14+Q14 -> 0 | S14: =R14*5% -> 0 | T14: =R14+S14 -> 0 | U14: PSPM
... A46: 44 | B46: 10.12.20 | C46: 44 | D46: 307 | E46: 161000816 | F46: 59 | G46: 3565.82 | H46: 268.18 | I46: 0 | J46: 0 | K46: 0 | L46: 0 | M46: 0 | N46: 0 | Q46: 0 | R46: =K46+M46+Q46 -> 0 | S46: =R46*5% -> 0 | T46: =R46+S46 -> 0 | U46: PSPM
A47: 45 | B47: 10.12.20 | C47: 45 | D47: 308 | E47: 161000817 | F47: 59 | G47: 3569.82 | H47: 264.18 | I47: 0 | J47: 0 | K47: 0 | L47: 0 | M47: 0 | N47: 0 | Q47: 0 | R47: =K47+M47+Q47 -> 0 | S47: =R47*5% -> 0 | T47: =R47+S47 -> 0 | U47: BTPC | V47: 45+1 SAMPLE SENT ON 14.12.20
A48: 46 | B48: 12.12.20 | C48: 46 | D48: 309 | E48: 161000818 | F48: 57 | G48: 3422.04 | H48: 281.96 | I48: 0 | J48: 0 | K48: 0 | L48: 0 | M48: 0 | N48: 0 | Q48: 0 | R48: =K48+M48+Q48 -> 0 | S48: =R48*5% -> 0 | T48: =R48+S48 -> 0 | U48: PSPM
A49: 47 | B49: 13.12.20 | C49: 47 | D49: 310 | E49: 161000819 | F49: 59 | G49: 3599.81 | H49: 235.19 | I49: 0 | J49: 0 | K49: 0 | L49: 0 | M49: 0 | N49: 0 | Q49: 0 | R49: =K49+M49+Q49 -> 0 | S49: =R49*5% -> 0 | T49: =R49+S49 -> 0 | U49: PSPM
A50: 48 | B50: 13.12.20 | C50: 48 | D50: 311 | E50: 141000050 | F50: 59 | G50: 3567.82 | H50: 266.18 | I50: 0 | J50: 0 | K50: 0 | L50: 0 | M50: 0 | N50: 0 | Q50: 0 | R50: =K50+M50+Q50 -> 0 | S50: =R50*5% -> 0 | T50: =R50+S50 -> 0 | U50: PSPM
A51: 49 | B51: 13.12.20 | C51: 49 | D51: 312 | E51: 141000051 | F51: 58 | G51: 3388.43 | H51: 380.57 | I51: 0 | J51: 0 | K51: 0 | L51: 0 | M51: 0 | N51: 0 | Q51: 0 | R51: =K51+M51+Q51 -> 0 | S51: =R51*5% -> 0 | T51: =R51+S51 -> 0 | U51: PSPM
A52: 50 | B52: 13.12.20 | C52: 50 | D52: 314 | E52: 161000820 | F52: 59 | G52: 3494.05 | H52: 336.95 | I52: 0 | J52: 0 | K52: 0 | L52: 0 | M52: 0 | N52: 0 | Q52: 0 | R52: =K52+M52+Q52 -> 0 | S52: =R52*5% -> 0 | T52: =R52+S52 -> 0 | U52: PSPM
A53: 51 | B53: 14.12.20 | C53: 51 | D53: 313 | E53: 161000821 | F53: 59 | G53: 3552.21 | H53: 282.79 | I53: 0 | J53: 0 | K53: 0 | L53: 0 | M53: 0 | N53: 0 | Q53: 0 | R53: =K53+M53+Q53 -> 0 | S53: =R53*5% -> 0 | T53: =R53+S53 -> 0 | U53: BTPC
A54: 52 | B54: 14.12.20 | C54: 52 | D54: 315 | E54: 161000822 | F54: 57 | G54: 3428.04 | H54: 275.96 | I54: 0 | J54: 0 | K54: 0 | L54: 0 | M54: 0 | N54: 0 | Q54: 0 | R54: =K54+M54+Q54 -> 0 | S54: =R54*5% -> 0 | T54: =R54+S54 -> 0 | U54: PSPM
A55: 53 | B55: 14.12.20 | C55: 53 | D55: 316 | E55: 161000823 | F55: 59 | G55: 3521.84 | H55: 310.96 | I55: 0 | J55: 0 | K55: 0 | L55: 0 | M55: 0 | N55: 0 | Q55: 0 | R55: =K55+M55+Q55 -> 0 | S55: =R55*5% -> 0 | T55: =R55+S55 -> 0 | U55: PSPM
A56: 54 | B56: 14.12.20 | C56: 54 | D56: 317 | E56: 161000824 | F56: 59 | G56: 3512.81 | H56: 322.19 | I56: 0 | J56: 0 | K56: 0 | L56: 5 | M56: 44250 | N56: 0 | Q56: 0 | R56: =K56+M56 -> 44250 | S56: =R56*5% -> 2212.5 | T56: =R56+S56 -> 46462.5 | U56: PSPM | V56: FOREST PERMIT 17:00 STOPPED LOADING BY RANGER MR.ANIL SINGH
A57: 55 | B57: 15.12.20 | C57: 55 | D57: 318 | E57: 161000825 | F57: 59 | G57: 3577.62 | H57: 256.38 | I57: 0 | J57: 0 | K57: 0 | L57: 0 | M57: 0 | N57: 0 | Q57: 0 | R57: =K57+M57+Q57 -> 0 | S57: =R57*5% -> 0 | T57: =R57+S57 -> 0 | U57: PSPM
A58: 56 | B58: 15.12.20 | C58: 56 | D58: 319 | E58: 161000826 | F58: 56 | G58: 3446.82 | H58: 323.18 | I58: 0 | J58: 0 | K58: 0 | L58: 0 | M58: 0 | N58: 0 | Q58: 0 | R58: =K58+M58+Q58 -> 0 | S58: =R58*5% -> 0 | T58: =R58+S58 -> 0 | U58: PSPM
A59: 57 | B59: 15.12.20 | C59: 57 | D59: 320 | E59: 161000827 | F59: 57 | G59: 3338.67 | H59: 362.33 | I59: 0 | J59: 0 | K59: 0 | L59: 0 | M59: 0 | N59: 0 | Q59: 0 | R59: =K59+M59+Q59 -> 0 | S59: =R59*5% -> 0 | T59: =R59+S59 -> 0 | U59: PSPM
A60: 58 | B60: 15.12.20 | C60: 58 | D60: 321 | E60: 161000828 | F60: 58 | G60: 3517.62 | H60: 252.38 | I60: 0 | J60: 0 | K60: 0 | L60: 0 | M60: 0 | N60: 0 | Q60: 0 | R60: =K60+M60+Q60 -> 0 | S60: =R60*5% -> 0 | T60: =R60+S60 -> 0 | U60: PSPM
A61: 59 | B61: 16.12.20 | C61: 59 | D61: 322 | E61: 161000829 | F61: 59 | G61: 3487.84 | H61: 344.16 | I61: 0 | J61: 0 | K61: 0 | L61: 0 | M61: 0 | N61: 0 | Q61: 0 | R61: =K61+M61+Q61 -> 0 | S61: =R61*5% -> 0 | T61: =R61+S61 -> 0 | U61: PSPM
A62: 60 | B62: 16.12.20 | C62: 60 | D62: 323 | E62: 161000830 | F62: 59 | G62: 3496.01 | H62: 338.99 | I62: 0 | J62: 0 | K62: 0 | L62: 0 | M62: 0 | N62: 0 | Q62: 0 | R62: =K62+M62+Q62 -> 0 | S62: =R62*5% -> 0 | T62: =R62+S62 -> 0 | U62: PSPM
A63: 61 | B63: 16.12.20 | C63: 61 | D63: 324 | E63: 161000831 | F63: 59 | G63: 3486.02 | H63: 350.56 | I63: 2.58 | J63: 1 | K63: 0 | L63: 0 | M63: 8850 | N63: 0 | Q63: 0 | R63: =K63+M63+Q63 -> 8850 | S63: =R63*5% -> 442.5 | T63: =R63+S63 -> 9292.5 | U63: PSPM
A64: 62 | B64: 16.12.20 | C64: 62 | D64: 325 | E64: 161000832 | F64: 59 | G64: 3577.61 | H64: 257.39 | I64: 0 | J64: 0 | K64: 0 | L64: 0 | M64: 0 | N64: 0 | Q64: 0 | R64: =K64+M64+Q64 -> 0 | S64: =R64*5% -> 0 | T64: =R64+S64 -> 0 | U64: PSPM
A65: 63 | B65: 17.12.20 | C65: 63 | D65: 326 | E65: 161000833 | F65: 59 | G65: 3582.62 | H65: 251.38 | I65: 0 | J65: 0 | K65: 0 | L65: 0 | M65: 0 | N65: 0 | Q65: 0 | R65: =K65+M65+Q65 -> 0 | S65: =R65*5% -> 0 | T65: =R65+S65 -> 0 | U65: BTPC
A66: 64 | B66: 17.12.20 | C66: 64 | D66: 327 | E66: 161000834 | F66: 57 | G66: 3408.87 | H66: 292.13 | I66: 0 | J66: 0 | K66: 0 | L66: 0 | M66: 0 | N66: 0 | Q66: 0 | R66: =K66+M66+Q66 -> 0 | S66: =R66*5% -> 0 | T66: =R66+S66 -> 0 | U66: PSPM
A67: 65 | B67: 17.12.20 | C67: 65 | D67: 328 | E67: 161000835 | F67: 58 | G67: 3468.82 | H67: 301.18 | I67: 0 | J67: 0 | K67: 0 | L67: 0 | M67: 0 | N67: 0 | Q67: 0 | R67: =K67+M67+Q67 -> 0 | S67: =R67*5% -> 0 | T67: =R67+S67 -> 0 | U67: PSPM
A68: 66 | B68: 17.12.20 | C68: 66 | D68: 329 | E68: 161000836 | F68: 59 | G68: 3528.42 | H68: 305.58 | I68: 0 | J68: 0 | K68: 0 | L68: 0 | M68: 0 | N68: 0 | Q68: 0 | R68: =K68+M68+Q68 -> 0 | S68: =R68*5% -> 0 | T68: =R68+S68 -> 0 | U68: PSPM
... A77: 75 | B77: 19.12.20 | C77: 75 | D77: 338 | E77: 161000845 | F77: 59 | G77: 3545.62 | H77: 288.38 | I77: 0 | J77: 0 | K77: 0 | L77: 0 | M77: 0 | N77: 0 | Q77: 0 | R77: =K77+M77+Q77 -> 0 | S77: =R77*5% -> 0 | T77: =R77+S77 -> 0 | U77: PSPM
A78: 76 | B78: 19.12.20 | C78: 76 | D78: 339 | E78: 161000846 | F78: 56 | G78: 3367.24 | H78: 400.76 | I78: 0 | J78: 0 | K78: 0 | L78: 2 | M78: 8700 | N78: 1 | Q78: 29980 | R78: =K78+M78+Q78 -> 38680 | S78: =R78*5% -> 1934 | T78: =R78+S78 -> 40614 | U78: PSPM | V78: DUE TO LOTT VILLAGER'S STOPPED
A79: 77 | B79: 19.12.20 | C79: 77 | D79: 340 | E79: 161000847 | F79: 59 | G79: 3554.42 | H79: 279.58 | I79: 0 | J79: 0 | K79: 0 | L79: 0 | M79: 0 | N79: 0 | Q79: 0 | R79: =K79+M79+Q79 -> 0 | S79: =R79*5% -> 0 | T79: =R79+S79 -> 0 | U79: PSPM
A80: 78 | B80: 19.12.20 | C80: 78 | D80: 341 | E80: 161000848 | F80: 59 | G80: 3534.64 | H80: 297.36 | I80: 0 | J80: 0 | K80: 0 | L80: 0 | M80: 0 | N80: 0 | Q80: 0 | R80: =K80+M80+Q80 -> 0 | S80: =R80*5% -> 0 | T80: =R80+S80 -> 0 | U80: PSPM
A81: 79 | B81: 20.12.20 | C81: 79 | D81: 342 | E81: 141000052 | F81: 55 | G81: 3302.48 | H81: 269.52 | I81: 0 | J81: 0 | K81: 0 | L81: 0 | M81: 0 | N81: 0 | Q81: 0 | R81: =K81+M81+Q81 -> 0 | S81: =R81*5% -> 0 | T81: =R81+S81 -> 0 | U81: BTPC
A82: 80 | B82: 20.12.20 | C82: 80 | D82: 343 | E82: 161000849 | F82: 59 | G82: 3577.41 | H82: 257.59 | I82: 0 | J82: 0 | K82: 0 | L82: 0 | M82: 0 | N82: 0 | Q82: 0 | R82: =K82+M82+Q82 -> 0 | S82: =R82*5% -> 0 | T82: =R82+S82 -> 0 | U82: PSPM
A83: 81 | B83: 20.12.20 | C83: 81 | D83: 344 | E83: 161000850 | F83: 58 | G83: 3498.82 | H83: 271.18 | I83: 0 | J83: 0 | K83: 0 | L83: 0 | M83: 0 | N83: 0 | Q83: 0 | R83: =K83+M83+Q83 -> 0 | S83: =R83*5% -> 0 | T83: =R83+S83 -> 0 | U83: PSPM
A84: 82 | B84: 20.12.20 | C84: 82 | D84: 345 | E84: 161000851 | F84: 59 | G84: 3558.24 | H84: 273.76 | I84: 0 | J84: 0 | K84: 0 | L84: 0 | M84: 0 | N84: 0 | Q84: 0 | R84: =K84+M84+Q84 -> 0 | S84: =R84*5% -> 0 | T84: =R84+S84 -> 0 | U84: PSPM
A85: 83 | B85: 20.12.20 | C85: 83 | D85: 347 | E85: 161000852 | F85: 59 | G85: 3583.62 | H85: 250.38 | I85: 0 | J85: 0 | K85: 0 | L85: 0 | M85: 0 | N85: 0 | Q85: 0 | R85: =K85+M85+Q85 -> 0 | S85: =R85*5% -> 0 | T85: =R85+S85 -> 0 | U85: BTPC
A86: 84 | B86: 21.12.20 | C86: 84 | D86: 346 | E86: 161000853 | F86: 59 | G86: 3562.25 | H86: 268.75 | I86: 0 | J86: 0 | K86: 0 | L86: 0 | M86: 0 | N86: 0 | Q86: 0 | R86: =K86+M86+Q86 -> 0 | S86: =R86*5% -> 0 | T86: =R86+S86 -> 0 | U86: PSPM
A87: 85 | B87: 21.12.20 | C87: 85 | D87: 348 | E87: 161000854 | F87: 57 | G87: 3444.05 | H87: 258.95 | I87: 0 | J87: 0 | K87: 0 | L87: 0 | M87: 0 | N87: 0 | Q87: 0 | R87: =K87+M87+Q87 -> 0 | S87: =R87*5% -> 0 | T87: =R87+S87 -> 0 | U87: PSPM
A88: 86 | B88: 21.12.20 | C88: 86 | D88: 349 | E88: 161000855 | F88: 59 | G88: 3582.62 | H88: 252.57 | I88: 1.19 | J88: 1 | K88: 0 | L88: 0 | M88: 8850 | N88: 0 | Q88: 0 | R88: =K88+M88+Q88 -> 8850 | S88: =R88*5% -> 442.5 | T88: =R88+S88 -> 9292.5 | U88: PSPM
A89: 87 | B89: 21.12.20 | C89: 87 | D89: 350 | E89: 161000856 | F89: 59 | G89: 3487.44 | H89: 344.56 | I89: 0 | J89: 0 | K89: 0 | L89: 0 | M89: 0 | N89: 0 | Q89: 0 | R89: =K89+M89+Q89 -> 0 | S89: =R89*5% -> 0 | T89: =R89+S89 -> 0 | U89: PSPM
A90: 88 | B90: 21.12.20 | C90: 88 | D90: 351 | E90: 161000857 | F90: 59 | G90: 3425.61 | H90: 409.39 | I90: 0 | J90: 0 | K90: 0 | L90: 0 | M90: 0 | N90: 0 | Q90: 0 | R90: =K90+M90+Q90 -> 0 | S90: =R90*5% -> 0 | T90: =R90+S90 -> 0 | U90: PSPM
... A123: 121 | B123: 26.12.20 | C123: 121 | D123: 384 | E123: 161000888 | F123: 59 | G123: 3534.01 | H123: 300.99 | I123: 0 | J123: 0 | K123: 0 | L123: 0 | M123: 0 | N123: 0 | Q123: 0 | R123: =K123+M123+Q123 -> 0 | S123: =R123*5% -> 0 | T123: =R123+S123 -> 0 | U123: PSPM
A124: 122 | B124: 27.12.20 | C124: 122 | D124: 385 | E124: 161000889 | F124: 58 | G124: 3443.62 | H124: 326.38 | I124: 0 | J124: 0 | K124: 0 | L124: 0 | M124: 0 | N124: 2 | Q124: 29980 | R124: =K124+M124+Q124 -> 29980 | S124: =R124*5% -> 1499 | T124: =R124+S124 -> 31479 | U124: PSPM | W124: D.C WAGON PR.HOSE DAMAGED
A125: 123 | B125: 27.12.20 | C125: 123 | D125: 387 | E125: 161000890 | F125: 58 | G125: 3524.64 | H125: 243.36 | I125: 0 | J125: 0 | K125: 0 | L125: 0 | M125: 0 | N125: 0 | Q125: 0 | R125: =K125+M125+Q125 -> 0 | S125: =R125*5% -> 0 | T125: =R125+S125 -> 0 | U125: PSPM
A126: 124 | B126: 27.12.20 | C126: 124 | D126: 388 | E126: 161000891 | F126: 59 | G126: 3544.24 | H126: 287.76 | I126: 0 | J126: 0 | K126: 0 | L126: 0 | M126: 0 | N126: 0 | Q126: 0 | R126: =K126+M126+Q126 -> 0 | S126: =R126*5% -> 0 | T126: =R126+S126 -> 0 | U126: PSPM
A127: 125 | B127: 27.12.20 | C127: 125 | D127: 386 | E127: 161000892 | F127: 58 | G127: 3513.03 | H127: 255.97 | I127: 0 | J127: 0 | K127: 0 | L127: 0 | M127: 0 | N127: 0 | Q127: 0 | R127: =K127+M127+Q127 -> 0 | S127: =R127*5% -> 0 | T127: =R127+S127 -> 0 | U127: BTPC
A128: 126 | B128: 27.12.20 | C128: 126 | D128: 390 | E128: 161000893 | F128: 58 | G128: 3427.63 | H128: 341.37 | I128: 0 | J128: 0 | K128: 0 | L128: 0 | M128: 0 | N128: 0 | Q128: 0 | R128: =K128+M128+Q128 -> 0 | S128: =R128*5% -> 0 | T128: =R128+S128 -> 0 | U128: PSPM
A129: 127 | B129: 27.12.20 | C129: 127 | D129: 391 | E129: 161000894 | F129: 59 | G129: 3460.24 | H129: 371.76 | I129: 0 | J129: 0 | K129: 0 | L129: 0 | M129: 0 | N129: 0 | Q129: 0 | R129: =K129+M129+Q129 -> 0 | S129: =R129*5% -> 0 | T129: =R129+S129 -> 0 | U129: PSPM
A130: 128 | B130: 28.12.20 | C130: 128 | D130: 389 | E130: 161000895 | F130: 58 | G130: 3452.43 | H130: 316.57 | I130: 0 | J130: 0 | K130: 0 | L130: 0 | M130: 0 | N130: 0 | Q130: 0 | R130: =K130+M130+Q130 -> 0 | S130: =R130*5% -> 0 | T130: =R130+S130 -> 0 | U130: BTPC
A131: 129 | B131: 28.12.20 | C131: 129 | D131: 393 | E131: 151000048 | F131: 58 | G131: 3467.63 | H131: 301.37 | I131: 0 | J131: 0 | K131: 0 | L131: 0 | M131: 0 | N131: 0 | Q131: 0 | R131: =K131+M131+Q131 -> 0 | S131: =R131*5% -> 0 | T131: =R131+S131 -> 0 | U131: PSPM
A132: 130 | B132: 28.12.20 | C132: 130 | D132: 392 | E132: 151000049 | F132: 59 | G132: 3519.42 | H132: 314.58 | I132: 0 | J132: 0 | K132: 0 | L132: 0 | M132: 0 | N132: 0 | Q132: 0 | R132: =K132+M132+Q132 -> 0 | S132: =R132*5% -> 0 | T132: =R132+S132 -> 0 | U132: BTPC
A133: 131 | B133: 28.12.20 | C133: 131 | D133: 394 | E133: 151000050 | F133: 56 | G133: 3356.05 | H133: 282.95 | I133: 0 | J133: 0 | K133: 0 | L133: 0 | M133: 0 | N133: 0 | Q133: 0 | R133: =K133+M133+Q133 -> 0 | S133: =R133*5% -> 0 | T133: =R133+S133 -> 0 | U133: PSPM
A134: 132 | B134: 28.12.20 | C134: 132 | D134: 396 | E134: 161000896 | F134: 59 | G134: 3505.45 | H134: 325.55 | I134: 0 | J134: 0 | K134: 0 | L134: 0 | M134: 0 | N134: 0 | Q134: 0 | R134: =K134+M134+Q134 -> 0 | S134: =R134*5% -> 0 | T134: =R134+S134 -> 0 | U134: PSPM
A135: 133 | B135: 28.12.20 | C135: 133 | D135: 397 | E135: 161000897 | F135: 59 | G135: 3569.01 | H135: 265.99 | I135: 0 | J135: 0 | K135: 0 | L135: 0 | M135: 0 | N135: 0 | Q135: 0 | R135: =K135+M135+Q135 -> 0 | S135: =R135*5% -> 0 | T135: =R135+S135 -> 0 | U135: PSPM
A136: 134 | B136: 28.12.20 | C136: 134 | D136: 395 | E136: 161000898 | F136: 58 | G136: 3495.83 | H136: 273.17 | I136: 0 | J136: 0 | K136: 0 | L136: 0 | M136: 0 | N136: 0 | Q136: 0 | R136: =K136+M136+Q136 -> 0 | S136: =R136*5% -> 0 | T136: =R136+S136 -> 0 | U136: BTPC
... A154: 152 | B154: 31.12.20 | C154: 152 | D154: 415 | E154: 161000916 | F154: 59 | G154: 3461.41 | H154: 373.59 | I154: 0 | J154: 0 | K154: 0 | L154: 0 | M154: 0 | N154: 0 | Q154: 0 | R154: =K154+M154+Q154 -> 0 | S154: =R154*5% -> 0 | T154: =R154+S154 -> 0 | U154: BTPC
F155: =SUM(F3:F154) -> 8852 | G155: =SUM(G3:G154) -> 528075.69 | H155: =SUM(H3:H154) -> 47425.86 | I155: =SUM(I3:I154) -> 10.15 | J155: =SUM(J3:J154) -> 3 | K155: =SUM(K3:K154) -> 0 | L155: =SUM(L3:L154) -> 7 | M155: =SUM(M3:M154) -> 79500 | N155: =SUM(N3:N154) -> 3 | Q155: =SUM(Q3:Q154) -> 74950 | R155: =SUM(R3:R154) -> 154450 | S155: =SUM(S3:S154) -> 7722.5 | T155: =SUM(T3:T154) -> 162172.5
F156: =G155/A154 -> 3474.1822 | R156: =R155-R124-R88-R72-R63 -> 82930 | U156: 31479
R157: =R155-R156 -> 71520 | U157: 40614
U158: 46462.5
U159: =SUM(U156:U158) -> 118555.5
T161: =T155-U159 -> 43617

Sheet JAN
A1: JANUARY - 21 MONTH RAKE LOADING DATA
A2: SL NO | B2: LOADING DATE | C2: RAKE NO. | D2: PRIORTY NUMBER | E2: R.R NUMBER | F2: NO OF WAGON | G2: NET WEIGHT | H2: UNDER LOAD WT | I2: OVER LOAD WT | J2: O/L WAGON | K2: O/L CHARGE | L2: DETENTION HOURS | M2: DETENTION CHARGES | N2: SHUNTING HOURS | O2: SHUNTING CHARGES | P2: PILOT HOURS | Q2: PILOT CHARGES | R2: PCLA | S2: GST 5% | T2: TOTAL AMOUNT RS | U2: DESTINATION | V2: RESULT DATE
A3: 1 | B3: 01.01.21 | C3: 1 | D3: 416 | E3: 161000917 | F3: 59 | G3: 3529.01 | H3: 305.99 | I3: 0 | J3: 0 | K3: 0 | L3: 0 | M3: 0 | N3: 0 | Q3: 0 | R3: =M3+Q3 -> 0 | S3: 0 | U3: PSPM
A4: 2 | B4: 01.01.21 | C4: 2 | D4: 417 | E4: 161000918 | F4: 58 | G4: 3480.63 | H4: 288.37 | I4: 0 | J4: 0 | K4: 0 | L4: 0 | M4: 0 | N4: 0 | Q4: 0 | R4: =M4+Q4 -> 0 | S4: 0 | U4: BTPC
A5: 3 | B5: 02.01.21 | C5: 3 | D5: 418 | E5: 161000919 | F5: 59 | G5: 3589.81 | H5: 245.19 | I5: 0 | J5: 0 | K5: 0 | L5: 0 | M5: 0 | N5: 0 | Q5: 0 | R5: =M5+Q5 -> 0 | S5: 0 | U5: PSPM
A6: 4 | B6: 02.01.21 | C6: 4 | D6: 419 | E6: 141000054 | F6: 58 | G6: 3497.63 | H6: 271.37 | I6: 0 | J6: 0 | K6: 0 | L6: 0 | M6: 0 | N6: 0 | Q6: 0 | R6: =M6+Q6 -> 0 | S6: 0 | U6: PSPM
A7: 5 | B7: 03.01.21 | C7: 5 | D7: 420 | E7: 161000920 | F7: 59 | G7: 3482.81 | H7: 352.19 | I7: 0 | J7: 0 | K7: 0 | L7: 0 | M7: 0 | N7: 0 | Q7: 0 | R7: =M7+Q7 -> 0 | S7: 0 | U7: BTPC
A8: 6 | B8: 03.01.21 | C8: 6 | D8: 421 | E8: 161000921 | F8: 59 | G8: 3437.62 | H8: 396.38 | I8: 0 | J8: 0 | K8: 0 | L8: 0 | M8: 0 | N8: 0 | Q8: 0 | R8: =M8+Q8 -> 0 | S8: 0 | U8: PSPM
A9: 7 | B9: 04.01.21 | C9: 7 | D9: 423 | E9: 161000922 | F9: 58 | G9: 3395.23 | H9: 373.77 | I9: 0 | J9: 0 | K9: 0 | L9: 0 | M9: 0 | N9: 0 | Q9: 0 | R9: =M9+Q9 -> 0 | S9: 0 | U9: BTPC
A10: 8 | B10: 04.01.21 | C10: 8 | D10: 422 | E10: 161000923 | F10: 56 | G10: 3266.65 | H10: 372.35 | I10: 0 | J10: 0 | K10: 0 | L10: 0 | M10: 0 | N10: 0 | Q10: 0 | R10: =M10+Q10 -> 0 | S10: 0 | U10: PSPM
A11: 9 | B11: 04.01.21 | C11: 9 | D11: 424 | E11: 161000924 | F11: 59 | G11: 3455.01 | H11: 379.99 | I11: 0 | J11: 0 | K11: 0 | L11: 0 | M11: 0 | N11: 0 | Q11: 0 | R11: =M11+Q11 -> 0 | S11: 0 | U11: BTPC
A12: 10 | B12: 04.01.21 | C12: 10 | D12: 425 | E12: 161000925 | F12: 58 | G12: 3417.03 | H12: 351.97 | I12: 0 | J12: 0 | K12: 0 | L12: 0 | M12: 0 | N12: 0 | Q12: 0 | R12: =M12+Q12 -> 0 | S12: 0 | U12: PSPM
A13: 11 | B13: 05.01.21 | C13: 11 | D13: 426 | E13: 161000926 | F13: 58 | G13: 3420.03 | H13: 348.97 | I13: 0 | J13: 0 | K13: 0 | L13: 0 | M13: 0 | N13: 0 | Q13: 0 | R13: =M13+Q13 -> 0 | S13: 0 | U13: PSPM
A14: 12 | B14: 05.01.21 | C14: 12 | D14: 427 | E14: 161000927 | F14: 58 | G14: 3446.63 | H14: 322.17 | I14: 0 | J14: 0 | K14: 0 | L14: 0 | M14: 0 | N14: 0 | Q14: 0 | R14: =M14+Q14 -> 0 | S14: 0 | U14: BTPC
... A17: 15 | B17: 06.01.21 | C17: 15 | D17: 430 | E17: 161000930 | F17: 57 | G17: 3483.23 | H17: 223.16 | I17: 1.39 | J17: 1 | K17: 0 | L17: 0 | M17: 8850 | N17: 0 | Q17: 14990 | R17: =M17+Q17 -> 23840 | S17: 0 | U17: BTPC
A18: 16 | B18: 06.01.21 | C18: 16 | D18: 431 | E18: 161000931 | F18: 57 | G18: 3418.64 | H18: 285.36 | I18: 0 | J18: 0 | K18: 0 | L18: 0 | M18: 0 | N18: 0 | Q18: 0 | R18: =M18+Q18 -> 0 | S18: 0 | T18: =R18*5 -> 0 | U18: PSPM
A19: 17 | B19: 06.01.21 | C19: 17 | D19: 432 | E19: 161000932 | F19: 58 | G19: 3505.43 | H19: 263.67 | I19: 0 | J19: 0 | K19: 0 | L19: 0 | M19: 0 | N19: 0 | Q19: 0 | R19: 0 | S19: 0 | T19: 0 | U19: PSPM
A20: 18 | B20: 06.01.21 | C20: 18 | D20: 433 | E20: 161000933 | F20: 59 | G20: 3471.41 | H20: 363.59 | I20: 0 | J20: 0 | K20: 0 | L20: 0 | M20: 0 | N20: 0 | Q20: 0 | R20: 0 | S20: 0 | T20: 0 | U20: PSPM
A21: 19 | B21: 07.01.21 | C21: 19 | D21: 434 | E21: 161000934 | F21: 59 | G21: 3387.84 | H21: 444.16 | I21: 0 | J21: 0 | K21: 0 | L21: 0 | M21: 0 | N21: 0 | Q21: 0 | R21: 0 | S21: 0 | T21: 0 | U21: PSPM
A22: 20 | B22: 07.01.21 | C22: 20 | D22: 435 | E22: 161000935 | F22: 57 | G22: 3438.44 | H22: 265.56 | I22: 0 | J22: 0 | K22: 0 | L22: 0 | M22: 0 | N22: 0 | Q22: 0 | R22: 0 | S22: 0 | T22: 0 | U22: PSPM
A23: 21 | B23: 07.01.21 | C23: 21 | D23: 436 | E23: 161000936 | F23: 59 | G23: 3556.42 | H23: 277.58 | I23: 0 | J23: 0 | K23: 0 | L23: 0 | M23: 0 | N23: 0 | Q23: 0 | R23: 0 | S23: 0 | T23: 0 | U23: PSPM
A24: 22 | B24: 07.01.21 | C24: 22 | D24: 437 | E24: 161000937 | F24: 58 | G24: 3417.63 | H24: 351.37 | I24: 0 | J24: 0 | K24: 0 | L24: 0 | M24: 0 | N24: 0 | Q24: 0 | R24: 0 | S24: 0 | T24: 0 | U24: PSPM
A25: 23 | B25: 08.01.21 | C25: 23 | D25: 438 | E25: 161000938 | F25: 58 | G25: 3423.43 | H25: 345.57 | I25: 0 | J25: 0 | K25: 0 | L25: 0 | M25: 0 | N25: 0 | Q25: 0 | R25: 0 | S25: 0 | T25: 0 | U25: PSPM
A26: 24 | B26: 08.01.21 | C26: 24 | D26: 439 | E26: 161000939 | F26: 59 | G26: 3550.01 | H26: 284.99 | I26: 0 | J26: 0 | K26: 0 | L26: 0 | M26: 0 | N26: 0 | Q26: 0 | R26: 0 | S26: 0 | T26: 0 | U26: PSPM
A27: 25 | B27: 08.01.21 | C27: 25 | D27: 440 | E27: 161000940 | F27: 57 | G27: 3415.26 | H27: 286.74 | I27: 0 | J27: 0 | K27: 0 | L27: 0 | M27: 0 | N27: 0 | Q27: 0 | R27: 0 | S27: 0 | T27: 0 | U27: PSPM
A28: 26 | B28: 08.01.21 | C28: 26 | D28: 441 | E28: 161000941 | F28: 58 | G28: 3429.85 | H28: 337.15 | I28: 0 | J28: 0 | K28: 0 | L28: 0 | M28: 0 | N28: 0 | Q28: 0 | R28: 0 | S28: 0 | T28: 0 | U28: PSPM
A29: 27 | B29: 08.01.21 | C29: 27 | D29: 442 | E29: 161000942 | F29: 58 | G29: 3432.43 | H29: 336.57 | I29: 0 | J29: 0 | K29: 0 | L29: 0 | M29: 0 | N29: 0 | Q29: 0 | R29: 0 | S29: 0 | T29: 0 | U29: PSPM
A30: 28 | B30: 09.01.21 | C30: 28 | D30: 443 | E30: 161000943 | F30: 59 | G30: 3519.01 | H30: 315.99 | I30: 0 | J30: 0 | K30: 0 | L30: 0 | M30: 0 | N30: 0 | Q30: 0 | R30: 0 | S30: 0 | T30: 0 | U30: PSPM
... A111: 109 | B111: 29.01.21 | C111: 109 | D111: 524 | E111: 161001009 | F111: 58 | G111: 3444.26 | H111: 321.74 | I111: 0 | J111: 0 | K111: 0 | L111: 0 | M111: 0 | N111: 0 | Q111: 0 | R111: 0 | S111: 0 | T111: 0 | U111: PSPM
A112: 110 | B112: 29.01.21 | C112: 110 | D112: 525 | E112: 161001010 | F112: 59 | G112: 3578.32 | H112: 260.21 | I112: 4.57 | J112: 2 | K112: 0 | L112: 0 | M112: 8850 | N112: 0 | Q112: 0 | R112: =Q112+M112 -> 8850 | S112: 0 | T112: 0 | U112: PSPM
A113: 111 | B113: 29.01.21 | C113: 111 | D113: 526 | E113: 161001011 | F113: 59 | G113: 3563.35 | H113: 267.65 | I113: 0 | J113: 0 | K113: 0 | L113: 0 | M113: 0 | N113: 0 | Q113: 0 | R113: 0 | S113: 0 | T113: 0 | U113: PSPM
A114: 112 | B114: 30.01.21 | C114: 112 | D114: 527 | E114: 161001012 | F114: 58 | G114: 3355.42 | H114: 414.58 | I114: 0 | J114: 0 | K114: 0 | L114: 0 | M114: 0 | N114: 0 | Q114: 0 | R114: 0 | S114: 0 | T114: 0 | U114: BTPC
A115: 113 | B115: 30.01.21 | C115: 113 | D115: 528 | E115: 161001013 | F115: 58 | G115: 3406.84 | H115: 361.16 | I115: 0 | J115: 0 | K115: 0 | L115: 0 | M115: 0 | N115: 0 | Q115: 0 | R115: 0 | S115: 0 | T115: 0 | U115: PSPM
A116: 114 | B116: 30.01.21 | C116: 114 | D116: 529 | E116: 161001014 | F116: 60 | G116: 3522.4 | H116: 377.6 | I116: 0 | J116: 0 | K116: 0 | L116: 0 | M116: 0 | N116: 0 | Q116: 0 | R116: 0 | S116: 0 | T116: 0 | U116: PSPM
A117: 115 | B117: 30.01.21 | C117: 115 | D117: 530 | E117: 161001015 | F117: 57 | G117: 3379.23 | H117: 325.97 | I117: 0 | J117: 0 | K117: 0 | L117: 0 | M117: 0 | N117: 0 | Q117: 0 | R117: 0 | S117: 0 | T117: 0 | U117: PSPM
A118: 116 | B118: 31.01.21 | C118: 116 | D118: 532 | E118: 161001016 | F118: 58 | G118: 3433.66 | H118: 332.34 | I118: 0 | J118: 0 | K118: 0 | L118: 0 | M118: 0 | N118: 0 | Q118: 0 | R118: 0 | S118: 0 | T118: 0 | U118: PSPM
A119: 117 | B119: 31.01.21 | C119: 117 | D119: 531 | E119: 161001017 | F119: 57 | G119: 3354.67 | H119: 346.33 | I119: 0 | J119: 0 | K119: 0 | L119: 0 | M119: 0 | N119: 0 | Q119: 0 | R119: 0 | S119: 0 | T119: 0 | U119: BTPC
A120: 118 | B120: 31.01.21 | C120: 118 | D120: 533 | E120: 161001018 | F120: 58 | G120: 3399.05 | H120: 367.95 | I120: 0 | J120: 0 | K120: 0 | L120: 0 | M120: 0 | N120: 0 | Q120: 0 | R120: 0 | S120: 0 | T120: 0 | U120: PSPM
A121: 119 | B121: 31.01.21 | C121: 119 | D121: 534 | E121: 161001019 | F121: 58 | G121: 3434.24 | H121: 333.76 | I121: 0 | J121: 0 | K121: 0 | L121: 0 | M121: 0 | N121: 0 | Q121: 0 | R121: 0 | S121: 0 | T121: 0 | U121: PSPM
F122: =SUM(F3:F121) -> 6945 | G122: =SUM(G3:G121) -> 415064.72 | H122: =SUM(H3:H121) -> 36145.28 | I122: =SUM(I3:I121) -> 5.96 | J122: =SUM(J3:J121) -> 3 | M122: =SUM(M3:M121) -> 17700 | R122: =SUM(R3:R121) -> 32690
F123: =G122/A121 -> 3487.9388

Sheet FEB
A1: FEBRUARY - 21 MONTH RAKE LOADING DATA
A2: SL NO | B2: LOADING DATE | C2: RAKE NO. | D2: PRIORTY NUMBER | E2: R.R NUMBER | F2: NO OF WAGON | G2: NET WEIGHT | H2: UNDER LOAD WT | I2: OVER LOAD WT | J2: O/L WAGON | K2: O/L CHARGE | L2: DETENTION HOURS | M2: DETENTION CHARGES | N2: SHUNTING HOURS | O2: SHUNTING CHARGES | P2: PILOT HOURS | Q2: PILOT CHARGES | R2: PCLA | S2: GST 5% | T2: TOTAL AMOUNT RS | U2: DESTINATION | V2: RESULT DATE
A3: 1 | B3: 01.02.21 | C3: 1 | D3: 535 | E3: 161001020 | F3: 56 | G3: 3464.04 | H3: 177.55 | I3: 1.59 | J3: 1 | K3: 0 | L3: 1 | M3: 8400 | N3: 1 | Q3: 14990 | R3: 23390 | S3: =R3*5% -> 1169.5 | T3: =R3+S3 -> 24559.5 | U3: BTPC
A4: 2 | B4: 01.02.21 | C4: 2 | D4: 536 | E4: 161001021 | F4: 59 | G4: 3481.41 | H4: 353.59 | I4: 0 | J4: 0 | K4: 0 | L4: 0 | M4: 0 | N4: 0 | Q4: 0 | R4: 0 | S4: =R4*5% -> 0 | T4: =R4+S4 -> 0 | U4: PSPM
A5: 3 | B5: 01.02.21 | C5: 3 | D5: 537 | E5: 161001022 | F5: 59 | G5: 3465.45 | H5: 365.55 | I5: 0 | J5: 0 | K5: 0 | L5: 0 | M5: 0 | N5: 0 | Q5: 0 | R5: 0 | S5: =R5*5% -> 0 | T5: =R5+S5 -> 0 | U5: PSPM
A6: 4 | B6: 02.02.21 | C6: 4 | D6: 538 | E6: 161001023 | F6: 58 | G6: 3376.42 | H6: 393.58 | I6: 0 | J6: 0 | K6: 0 | L6: 0 | M6: 0 | N6: 0 | Q6: 0 | R6: 0 | S6: =R6*5% -> 0 | T6: =R6+S6 -> 0 | U6: PSPM
A7: 5 | B7: 02.02.21 | C7: 5 | D7: 539 | E7: 161001024 | F7: 59 | G7: 3399.02 | H7: 434.98 | I7: 0 | J7: 0 | K7: 0 | L7: 0 | M7: 0 | N7: 0 | Q7: 0 | R7: 0 | S7: =R7*5% -> 0 | T7: =R7+S7 -> 0 | U7: PSPM
A8: 6 | B8: 02.02.21 | C8: 6 | D8: 540 | E8: 161001025 | F8: 58 | G8: 3335.25 | H8: 431.75 | I8: 0 | J8: 0 | K8: 0 | L8: 0 | M8: 0 | N8: 0 | Q8: 0 | R8: 0 | S8: =R8*5% -> 0 | T8: =R8+S8 -> 0 | U8: PSPM
A9: 7 | B9: 02.02.21 | C9: 7 | D9: 541 | E9: 161001026 | F9: 57 | G9: 3305.85 | H9: 397.15 | I9: 0 | J9: 0 | K9: 0 | L9: 0 | M9: 0 | N9: 0 | Q9: 0 | R9: 0 | S9: =R9*5% -> 0 | T9: =R9+S9 -> 0 | U9: PSPM
A10: 8 | B10: 03.02.21 | C10: 8 | D10: 542 | E10: 161001027 | F10: 58 | G10: 3319.43 | H10: 385.37 | I10: 0 | J10: 0 | K10: 0 | L10: 0 | M10: 0 | N10: 0 | Q10: 0 | R10: 0 | S10: =R10*5% -> 0 | T10: =R10+S10 -> 0 | U10: BTPC
A11: 9 | B11: 03.02.21 | C11: 9 | D11: 543 | E11: 161001028 | F11: 59 | G11: 3471.13 | H11: 361.07 | I11: 0 | J11: 0 | K11: 0 | L11: 0 | M11: 0 | N11: 0 | Q11: 0 | R11: 0 | S11: =R11*5% -> 0 | T11: =R11+S11 -> 0 | U11: PSPM
A12: 10 | B12: 03.02.21 | C12: 10 | D12: 544 | E12: 161001029 | F12: 59 | G12: 3352.12 | H12: 417 | I12: 0 | J12: 0 | K12: 0 | L12: 0 | M12: 0 | N12: 0 | Q12: 0 | R12: 0 | S12: =R12*5% -> 0 | T12: =R12+S12 -> 0 | U12: PSPM
A13: 11 | B13: 03.02.21 | C13: 11 | D13: 545 | E13: 161001030 | F13: 58 | G13: 3368.35 | H13: 398.65 | I13: 0 | J13: 0 | K13: 0 | L13: 0 | M13: 0 | N13: 0 | Q13: 0 | R13: 0 | S13: =R13*5% -> 0 | T13: =R13+S13 -> 0 | U13: PSPM
A14: 12 | B14: 04.02.21 | C14: 12 | D14: 546 | E14: 151000061 | F14: 59 | G14: 3578.02 | H14: 255.98 | I14: 0 | J14: 0 | K14: 0 | L14: 0 | M14: 0 | N14: 0 | Q14: 0 | R14: 0 | S14: =R14*5% -> 0 | T14: =R14+S14 -> 0 | U14: PSPM
... A86: 84 | B86: 22.02.21 | C86: 84 | D86: 618 | E86: 141000066 | F86: 58 | G86: 3466.04 | H86: 301.96 | I86: 0 | J86: 0 | K86: 0 | L86: 0 | M86: 0 | N86: 0 | Q86: 0 | R86: 0 | S86: =R86*5% -> 0 | T86: =R86+S86 -> 0 | U86: PSPM
A87: 85 | B87: 22.02.21 | C87: 85 | D87: 619 | E87: 161001081 | F87: 59 | G87: 3626.06 | H87: 205.03 | I87: 1.42 | J87: 1 | K87: 0 | L87: 0 | M87: 8850 | N87: 0 | Q87: 0 | R87: =M87 -> 8850 | S87: =R87*5% -> 442.5 | T87: =R87+S87 -> 9292.5 | U87: PSPM | V87: PAKUR IMWB WEIGHMENT - TMS LINK FAILED
A88: 86 | B88: 22.02.21 | C88: 86 | D88: 620 | E88: 161001082 | F88: 59 | G88: 3540.02 | H88: 293.98 | I88: 0 | J88: 0 | K88: 0 | L88: 0 | M88: 0 | N88: 0 | Q88: 0 | R88: 0 | S88: =R88*5% -> 0 | T88: =R88+S88 -> 0 | U88: BTPC
A89: 87 | B89: 22.02.21 | C89: 87 | D89: 621 | E89: 161001083 | F89: 59 | G89: 3496.84 | H89: 335.16 | I89: 0 | J89: 0 | K89: 0 | L89: 0 | M89: 0 | N89: 0 | Q89: 0 | R89: 0 | S89: =R89*5% -> 0 | T89: =R89+S89 -> 0 | U89: PSPM
A90: 88 | B90: 23.02.21 | C90: 88 | D90: 622 | E90: 161001084 | F90: 58 | G90: 3463.22 | H90: 305.78 | I90: 0 | J90: 0 | K90: 0 | L90: 0 | M90: 0 | N90: 0 | Q90: 0 | R90: 0 | S90: =R90*5% -> 0 | T90: =R90+S90 -> 0 | U90: PSPM
A91: 89 | B91: 23.02.21 | C91: 89 | D91: 624 | E91: 161001085 | F91: 59 | G91: 3520.22 | H91: 313.78 | I91: 0 | J91: 0 | K91: 0 | L91: 0 | M91: 0 | N91: 0 | Q91: 0 | R91: 0 | S91: =R91*5% -> 0 | T91: =R91+S91 -> 0 | U91: BTPC
A92: 90 | B92: 23.02.21 | C92: 90 | D92: 623 | E92: 161001086 | F92: 58 | G92: 3363.63 | H92: 405.37 | I92: 0 | J92: 0 | K92: 0 | L92: 0 | M92: 0 | N92: 0 | Q92: 0 | R92: 0 | S92: =R92*5% -> 0 | T92: =R92+S92 -> 0 | U92: PSPM
A93: 91 | B93: 23.02.21 | C93: 91 | D93: 625 | E93: 161001087 | F93: 58 | G93: 3400.85 | H93: 366.15 | I93: 0 | J93: 0 | K93: 0 | L93: 0 | M93: 0 | N93: 0 | Q93: 0 | R93: 0 | S93: =R93*5% -> 0 | T93: =R93+S93 -> 0 | U93: PSPM
A94: 92 | B94: 23.02.21 | C94: 92 | D94: 626 | E94: 161001088 | F94: 58 | G94: 3387.44 | H94: 380.56 | I94: 0 | J94: 0 | K94: 0 | L94: 0 | M94: 0 | N94: 0 | Q94: 0 | R94: 0 | S94: =R94*5% -> 0 | T94: =R94+S94 -> 0 | U94: PSPM
A95: 93 | B95: 24.02.21 | C95: 93 | D95: 627 | E95: 161001089 | F95: 59 | G95: 3448.02 | H95: 385.98 | I95: 0 | J95: 0 | K95: 0 | L95: 0 | M95: 0 | N95: 0 | Q95: 0 | R95: 0 | S95: =R95*5% -> 0 | T95: =R95+S95 -> 0 | U95: PSPM
A96: 94 | B96: 24.02.21 | C96: 94 | D96: 628 | E96: 161001090 | F96: 59 | G96: 3521.06 | H96: 308.94 | I96: 0 | J96: 0 | K96: 0 | L96: 0 | M96: 0 | N96: 0 | Q96: 0 | R96: 0 | S96: =R96*5% -> 0 | T96: =R96+S96 -> 0 | U96: PSPM
A97: 95 | B97: 24.02.21 | C97: 95 | D97: 629 | E97: 161001091 | F97: 59 | G97: 3461.24 | H97: 370.76 | I97: 0 | J97: 0 | K97: 0 | L97: 0 | M97: 0 | N97: 0 | Q97: 0 | R97: 0 | S97: =R97*5% -> 0 | T97: =R97+S97 -> 0 | U97: PSPM
A98: 96 | B98: 24.02.21 | C98: 96 | D98: 630 | E98: 141000067 | F98: 58 | G98: 3474.02 | H98: 295.98 | I98: 0 | J98: 0 | K98: 0 | L98: 0 | M98: 0 | N98: 0 | Q98: 0 | R98: 0 | S98: =R98*5% -> 0 | T98: =R98+S98 -> 0 | U98: BTPC
A99: 97 | B99: 24.02.21 | C99: 97 | D99: 631 | E99: 161001092 | F99: 58 | G99: 3482.83 | H99: 286.17 | I99: 0 | J99: 0 | K99: 0 | L99: 0 | M99: 0 | N99: 0 | Q99: 0 | R99: 0 | S99: =R99*5% -> 0 | T99: =R99+S99 -> 0 | U99: PSPM
... A119: 117 | B119: 28.02.21 | C119: 117 | D119: 651 | E119: 161001111 | F119: 58 | G119: 3444.83 | H119: 324.17 | I119: 0 | J119: 0 | K119: 0 | L119: 0 | M119: 0 | N119: 0 | Q119: 0 | R119: 0 | S119: =R119*5% -> 0 | T119: =R119+S119 -> 0 | U119: PSPM
F120: =SUM(F3:F119) -> 6822 | G120: =SUM(G3:G119) -> 402314.15 | H120: =SUM(H3:H119) -> 40780.65 | I120: =SUM(I3:I119) -> 3.01 | M120: =SUM(M3:M119) -> 17250 | T120: =SUM(T3:T119) -> 33852
F121: =G120/A119 -> 3438.5825
H122: =H120/117 -> 348.55256

Sheet MAR
A1: MARCH - 21 MONTH RAKE LOADING DATA
A2: SL NO | B2: LOADING DATE | C2: RAKE NO. | D2: PRIORTY NUMBER | E2: R.R NUMBER | F2: NO OF WAGON | G2: NET WEIGHT | H2: UNDER LOAD WT | I2: OVER LOAD WT | J2: O/L WAGON | K2: O/L CHARGE | L2: DETENTION HOURS | M2: DETENTION CHARGES | N2: SHUNTING HOURS | O2: SHUNTING CHARGES | P2: PILOT HOURS | Q2: PILOT CHARGES | R2: PCLA | S2: GST 5% | T2: TOTAL AMOUNT RS | U2: DESTINATION | V2: RESULT DATE
A3: 1 | B3: 01.03.21 | C3: 1 | D3: 652 | E3: 161001112 | F3: 59 | G3: 3489.46 | H3: 340.54 | I3: 0 | J3: 0 | K3: 0 | L3: 0 | M3: 0 | N3: 0 | Q3: 0 | R3: 0 | S3: 0 | T3: 0 | U3: PSPM
A4: 2 | B4: 01.03.21 | C4: 2 | D4: 653 | E4: 161001113 | F4: 59 | G4: 3454.21 | H4: 380.79 | I4: 0 | J4: 0 | K4: 0 | L4: 0 | M4: 0 | N4: 0 | Q4: 0 | R4: 0 | S4: 0 | T4: 0 | U4: PSPM
A5: 3 | B5: 01.03.21 | C5: 3 | D5: 655 | E5: 161001114 | F5: 59 | G5: 3493.24 | H5: 338.76 | I5: 0 | J5: 0 | K5: 0 | L5: 0 | M5: 0 | N5: 0 | Q5: 0 | R5: 0 | S5: 0 | T5: 0 | U5: PSPM
A6: 4 | B6: 01.03.21 | C6: 4 | D6: 654 | E6: 161001115 | F6: 59 | G6: 3506.81 | H6: 328.19 | I6: 0 | J6: 0 | K6: 0 | L6: 0 | M6: 0 | N6: 0 | Q6: 0 | R6: 0 | S6: 0 | T6: 0 | U6: BTPC
A7: 5 | B7: 01.03.21 | C7: 5 | D7: 656 | E7: 161001116 | F7: 59 | G7: 3472.82 | H7: 361.18 | I7: 0 | J7: 0 | K7: 0 | L7: 0 | M7: 0 | N7: 0 | Q7: 0 | R7: 0 | S7: 0 | T7: 0 | U7: PSPM
A8: 6 | B8: 02.03.21 | C8: 6 | D8: 657 | E8: 161001117 | F8: 59 | G8: 3506.22 | H8: 327.78 | I8: 0 | J8: 0 | K8: 0 | L8: 0 | M8: 0 | N8: 0 | Q8: 0 | R8: 0 | S8: 0 | T8: 0 | U8: PSPM
A9: 7 | B9: 02.03.21 | C9: 7 | D9: 658 | E9: 161001118 | F9: 56 | G9: 3320.27 | H9: 316.73 | I9: 0 | J9: 0 | K9: 0 | L9: 0 | M9: 0 | N9: 0 | Q9: 0 | R9: 0 | S9: 0 | T9: 0 | U9: BTPC
A10: 8 | B10: 02.03.21 | C10: 8 | D10: 659 | E10: 161001119 | F10: 58 | G10: 3401.44 | H10: 366.56 | I10: 0 | J10: 0 | K10: 0 | L10: 0 | M10: 0 | N10: 0 | Q10: 0 | R10: 0 | S10: 0 | T10: 0 | U10: PSPM
A11: 9 | B11: 02.03.21 | C11: 9 | D11: 660 | E11: 161001120 | F11: 58 | G11: 3485.82 | H11: 284.18 | I11: 0 | J11: 0 | K11: 0 | L11: 0 | M11: 0 | N11: 0 | Q11: 0 | R11: 0 | S11: 0 | T11: 0 | U11: PSPM
A12: 10 | B12: 02.03.21 | C12: 10 | D12: 661 | E12: 161001121 | F12: 59 | G12: 3515.86 | H12: 314.14 | I12: 0 | J12: 0 | K12: 0 | L12: 0 | M12: 0 | N12: 0 | Q12: 0 | R12: 0 | S12: 0 | T12: 0 | U12: PSPM
A13: 11 | B13: 03.03.21 | C13: 11 | D13: 662 | E13: 161001122 | F13: 59 | G13: 3511.41 | H13: 323.59 | I13: 0 | J13: 0 | K13: 0 | L13: 0 | M13: 0 | N13: 0 | Q13: 0 | R13: 0 | S13: 0 | T13: 0 | U13: PSPM
A14: 12 | B14: 03.03.21 | C14: 12 | D14: 663 | E14: 161001123 | F14: 59 | G14: 3436.64 | H14: 395.36 | I14: 0 | J14: 0 | K14: 0 | L14: 0 | M14: 0 | N14: 0 | Q14: 0 | R14: 0 | S14: 0 | T14: 0 | U14: PSPM
... A111: 109 | B111: 23.03.21 | C111: 109 | D111: 760 | E111: 161001213 | F111: 58 | G111: 3478.26 | H111: 287.74 | I111: 0 | J111: 0 | K111: 0 | L111: 0 | M111: 0 | N111: 0 | Q111: 0 | R111: 0 | S111: 0 | T111: 0 | U111: PSPM
A112: 110 | B112: 23.03.21 | C112: 110 | D112: 761 | E112: 161001214 | F112: 59 | G112: 3576.82 | H112: 258.57 | I112: 1.39 | J112: 0 | K112: 0 | L112: 0 | M112: 8850 | N112: 0 | Q112: 0 | R112: 8850 | S112: =5%*R112 -> 442.5 | T112: =R112+S112 -> 9292.5 | U112: PSPM
A113: 111 | B113: 24.03.21 | C113: 111 | D113: 762 | E113: 161001215 | F113: 54 | G113: 3273.87 | H113: 235.13 | I113: 0 | J113: 0 | K113: 0 | L113: 0 | M113: 0 | N113: 0 | Q113: 0 | R113: 0 | S113: 0 | T113: 0 | U113: PSPM
A114: 112 | B114: 24.03.21 | C114: 112 | D114: 763 | E114: 161001216 | F114: 58 | G114: 3476.63 | H114: 292.37 | I114: 0 | J114: 0 | K114: 0 | L114: 0 | M114: 0 | N114: 0 | Q114: 0 | R114: 0 | S114: 0 | T114: 0 | U114: PSPM
A115: 113 | B115: 24.03.21 | C115: 113 | D115: 764 | E115: 161001217 | F115: 59 | G115: 3539.01 | H115: 295.99 | I115: 0 | J115: 0 | K115: 0 | L115: 0 | M115: 0 | N115: 0 | Q115: 0 | R115: 0 | S115: 0 | T115: 0 | U115: PSPM
A116: 114 | B116: 24.03.21 | C116: 114 | D116: 765 | E116: 161001218 | F116: 58 | G116: 3459.23 | H116: 309.77 | I116: 0 | J116: 0 | K116: 0 | L116: 0 | M116: 0 | N116: 0 | Q116: 0 | R116: 0 | S116: 0 | T116: 0 | U116: PSPM
A117: 115 | B117: 24.03.21 | C117: 115 | D117: 766 | E117: 161001219 | F117: 59 | G117: 3539.44 | H117: 292.56 | I117: 0 | J117: 0 | K117: 0 | L117: 0 | M117: 0 | N117: 0 | Q117: 0 | R117: 0 | S117: 0 | T117: 0 | U117: PSPM
A118: 116 | B118: 25.03.21 | C118: 116 | D118: 767 | E118: 161001220 | F118: 59 | G118: 3532.21 | H118: 302.79 | I118: 0 | J118: 0 | K118: 0 | L118: 0 | M118: 0 | N118: 0 | Q118: 0 | R118: 0 | S118: 0 | T118: 0 | U118: PSPM
A119: 117 | B119: 25.03.21 | C119: 117 | D119: 768 | E119: 161001221 | F119: 59 | G119: 3561.04 | H119: 270.96 | I119: 0 | J119: 0 | K119: 0 | L119: 0 | M119: 0 | N119: 0 | Q119: 0 | R119: 0 | S119: 0 | T119: 0 | U119: PSPM
A120: 118 | B120: 25.03.21 | C120: 118 | D120: 769 | E120: 161001222 | F120: 59 | G120: 3522.01 | H120: 312.99 | I120: 0 | J120: 0 | K120: 0 | L120: 0 | M120: 0 | N120: 0 | Q120: 0 | R120: 0 | S120: 0 | T120: 0 | U120: PSPM
A121: 119 | B121: 26.03.21 | C121: 119 | D121: 770 | E121: 161001223 | F121: 59 | G121: 3428.84 | H121: 275.16 | I121: 0 | J121: 0 | K121: 0 | L121: 0 | M121: 0 | N121: 0 | Q121: 0 | R121: 0 | S121: 0 | T121: 0 | U121: PSPM
A122: 120 | B122: 26.03.21 | C122: 120 | D122: 771 | E122: 161001224 | F122: 59 | G122: 3500.81 | H122: 334.19 | I122: 0 | J122: 0 | K122: 0 | L122: 0 | M122: 0 | N122: 0 | Q122: 0 | R122: 0 | S122: 0 | T122: 0 | U122: PSPM
A123: 121 | B123: 26.03.21 | C123: 121 | D123: 772 | E123: 161001225 | F123: 59 | G123: 3482.01 | H123: 352.99 | I123: 0 | J123: 0 | K123: 0 | L123: 0 | M123: 0 | N123: 0 | Q123: 0 | R123: 0 | S123: 0 | T123: 0 | U123: PSPM
A124: 122 | B124: 26.03.21 | C124: 122 | D124: 773 | E124: 161001226 | F124: 58 | G124: 3506.21 | H124: 328.79 | I124: 0 | J124: 0 | K124: 0 | L124: 0 | M124: 0 | N124: 0 | Q124: 0 | R124: 0 | S124: 0 | T124: 0 | U124: PSPM
... A135: 133 | B135: 30.03.21 | C135: 133 | D135: 784 | E135: 161001237 | F135: 58 | G135: 3439.83 | H135: 329.17 | I135: 0 | J135: 0 | K135: 0 | L135: 0 | M135: 0 | N135: 0 | Q135: 0 | R135: 0 | S135: 0 | T135: 0 | U135: PSPM
A136: 134 | B136: 31.03.21 | C136: 134 | D136: 785 | E136: 161001238 | F136: 52 | G136: 3349.6 | H136: 290.4 | I136: 0 | J136: 0 | K136: 0 | L136: 0 | M136: 0 | N136: 0 | Q136: 0 | R136: 0 | S136: 0 | T136: 0 | U136: PSPM | V136: BOXN
A137: 135 | B137: 31.03.21 | C137: 135 | D137: 786 | E137: 161001239 | F137: 58 | G137: 3441.24 | H137: 326.76 | I137: 0 | J137: 0 | K137: 0 | L137: 0 | M137: 0 | N137: 0 | Q137: 0 | R137: 0 | S137: 0 | T137: 0 | U137: PSPM
A138: 136 | B138: 31.03.21 | C138: 136 | D138: 787 | E138: 161001240 | F138: 58 | G138: 3386.44 | H138: 381.56 | I138: 0 | J138: 0 | K138: 0 | L138: 0 | M138: 0 | N138: 0 | Q138: 0 | R138: 0 | S138: 0 | T138: 0 | U138: PSPM
A139: 137 | B139: 31.03.21 | C139: 137 | D139: 788 | E139: 161001241 | F139: 57 | G139: 3347.47 | H139: 353.53 | I139: 0 | J139: 0 | K139: 0 | L139: 0 | M139: 0 | N139: 0 | Q139: 0 | R139: 0 | S139: 0 | T139: 0 | U139: PSPM
A140: 138 | B140: 31.03.21 | C140: 138 | D140: 789 | E140: 161001242 | F140: 59 | G140: 3504.84 | H140: 327.16 | I140: 0 | J140: 0 | K140: 0 | L140: 0 | M140: 0 | N140: 0 | Q140: 0 | R140: 0 | S140: 0 | T140: 0 | U140: PSPM
A141: 139 | B141: 31.03.21 | C141: 139 | D141: 790 | E141: 161001243 | F141: 59 | G141: 3510.01 | H141: 324.99 | I141: 0 | J141: 0 | K141: 0 | L141: 0 | M141: 0 | N141: 0 | Q141: 0 | R141: 0 | S141: 0 | T141: 0 | U141: PSPM
A142: 140 | B142: 31.03.21 | C142: 140 | D142: 791 | E142: 161001244 | F142: 59 | G142: 3498.22 | H142: 335.78 | I142: 0 | J142: 0 | K142: 0 | L142: 0 | M142: 0 | N142: 0 | Q142: 0 | R142: 0 | S142: 0 | T142: 0 | U142: PSPM
A143: 141 | B143: 31.03.21 | C143: 141 | D143: 792 | E143: 161001245 | F143: 59 | G143: 3492.22 | H143: 341.78 | I143: 0 | J143: 0 | K143: 0 | L143: 0 | M143: 0 | N143: 0 | Q143: 0 | R143: 0 | S143: 0 | T143: 0 | U143: PSPM | W143: SGTPP ON 07.04.21
G144: =SUM(G3:G143) -> 486462.73 | H144: =SUM(H3:H143) -> 45898.66 | I144: =SUM(I3:I143) -> 1.39 | T144: =SUM(T3:T143) -> 9292.5
G145: =G144/A143 -> 3450.0903
H146: =H144/141 -> 325.52241

Sheet APR21
A1: APRIL - 21 MONTH RAKE LOADING DATA
A2: SL NO | B2: LOADING DATE | C2: RAKE NO. | D2: PRIORTY NUMBER | E2: R.R NUMBER | F2: NO OF WAGON | G2: NET WEIGHT | H2: UNDER LOAD WT | I2: OVER LOAD WT | J2: O/L WAGON | K2: O/L CHARGE | L2: DETENTION HOURS | M2: DETENTION CHARGES | N2: SHUNTING HOURS | O2: SHUNTING CHARGES | P2: PILOT HOURS | Q2: SHUNTING CHARGES | R2: PCLA | S2: GST 5% | T2: TOTAL AMOUNT RS | U2: DESTINATION | V2: RESULT DATE
A3: 1 | B3: 01.04.21 | C3: 1 | D3: 793 | E3: 161001246 | F3: 58 | G3: 3461.03 | H3: 307.97 | I3: 0 | J3: 0 | K3: 0 | L3: 0 | M3: 0 | N3: 0 | Q3: 0 | R3: 0 | S3: =R3*5% -> 0 | T3: =R3+S3 -> 0 | U3: PSPM
A4: 2 | B4: 01.04.21 | C4: 2 | D4: 1 | E4: 161001247 | F4: 58 | G4: 3451.42 | H4: 318.58 | I4: 0 | J4: 0 | K4: 0 | L4: 0 | M4: 0 | N4: 0 | Q4: 0 | R4: 0 | S4: =R4*5% -> 0 | T4: =R4+S4 -> 0 | U4: PSPM
A5: 3 | B5: 01.04.21 | C5: 3 | D5: 2 | E5: 161001248 | F5: 58 | G5: 3437.63 | H5: 331.37 | I5: 0 | J5: 0 | K5: 0 | L5: 0 | M5: 0 | N5: 0 | Q5: 0 | R5: 0 | S5: =R5*5% -> 0 | T5: =R5+S5 -> 0 | U5: PSPM
A6: 4 | B6: 01.04.21 | C6: 4 | D6: 3 | E6: 161001249 | F6: 58 | G6: 3430.64 | H6: 337.36 | I6: 0 | J6: 0 | K6: 0 | L6: 0 | M6: 0 | N6: 0 | Q6: 0 | R6: 0 | S6: =R6*5% -> 0 | T6: =R6+S6 -> 0 | U6: PSPM
A7: 5 | B7: 02.04.21 | C7: 5 | D7: 4 | E7: 151000084 | F7: 58 | G7: 3433.83 | H7: 335.17 | I7: 0 | J7: 0 | K7: 0 | L7: 0 | M7: 0 | N7: 0 | Q7: 0 | R7: 0 | S7: =R7*5% -> 0 | T7: =R7+S7 -> 0 | U7: PSPM
A8: 6 | B8: 02.04.21 | C8: 6 | D8: 5 | E8: 151000085 | F8: 58 | G8: 3359.43 | H8: 409.57 | I8: 0 | J8: 0 | K8: 0 | L8: 0 | M8: 0 | N8: 0 | Q8: 0 | R8: 0 | S8: =R8*5% -> 0 | T8: =R8+S8 -> 0 | U8: PSPM
A9: 7 | B9: 02.04.21 | C9: 7 | D9: 6 | E9: 141000069 | F9: 59 | G9: 3426.42 | H9: 407.58 | I9: 0 | J9: 0 | K9: 0 | L9: 0 | M9: 0 | N9: 0 | Q9: 0 | R9: 0 | S9: =R9*5% -> 0 | T9: =R9+S9 -> 0 | U9: PSPM
A10: 8 | B10: 02.04.21 | C10: 8 | D10: 7 | E10: 151000086 | F10: 58 | G10: 3412.65 | H10: 354.35 | I10: 0 | J10: 0 | K10: 0 | L10: 0 | M10: 0 | N10: 0 | Q10: 0 | R10: 0 | S10: =R10*5% -> 0 | T10: =R10+S10 -> 0 | U10: PSPM
A11: 9 | B11: 03.04.21 | C11: 9 | D11: 8 | E11: 151000087 | F11: 59 | G11: 3480.81 | H11: 354.19 | I11: 0 | J11: 0 | K11: 0 | L11: 0 | M11: 0 | N11: 0 | Q11: 0 | R11: 0 | S11: =R11*5% -> 0 | T11: =R11+S11 -> 0 | U11: PSPM
A12: 10 | B12: 03.04.21 | C12: 10 | D12: 9 | E12: 151000088 | F12: 59 | G12: 3480.82 | H12: 353.18 | I12: 0 | J12: 0 | K12: 0 | L12: 0 | M12: 0 | N12: 0 | Q12: 0 | R12: 0 | S12: =R12*5% -> 0 | T12: =R12+S12 -> 0 | U12: PSPM
A13: 11 | B13: 03.04.21 | C13: 11 | D13: 10 | E13: 161001250 | F13: 57 | G13: 3347.03 | H13: 357.97 | I13: 0 | J13: 0 | K13: 0 | L13: 0 | M13: 0 | N13: 0 | Q13: 0 | R13: 0 | S13: =R13*5% -> 0 | T13: =R13+S13 -> 0 | U13: PSPM
A14: 12 | B14: 04.04.21 | C14: 12 | D14: 11 | E14: 161001251 | F14: 59 | G14: 3460.42 | H14: 373.58 | I14: 0 | J14: 0 | K14: 0 | L14: 0 | M14: 0 | N14: 0 | Q14: 0 | R14: 0 | S14: =R14*5% -> 0 | T14: =R14+S14 -> 0 | U14: PSPM
... A20: 18 | B20: 05.04.21 | C20: 18 | D20: 17 | E20: 151000089 | F20: 58 | G20: 3467.82 | H20: 302.18 | I20: 0 | J20: 0 | K20: 0 | L20: 0 | M20: 0 | N20: 0 | Q20: 0 | R20: 0 | S20: =R20*5% -> 0 | T20: =R20+S20 -> 0 | U20: PSPM
A21: 19 | B21: 05.04.21 | C21: 19 | D21: 18 | E21: 151000090 | F21: 59 | G21: 3529.21 | H21: 305.79 | I21: 0 | J21: 0 | K21: 0 | L21: 0 | M21: 0 | N21: 0 | Q21: 0 | R21: 0 | S21: =R21*5% -> 0 | T21: =R21+S21 -> 0 | U21: PSPM | W21: SGTPP ON 07.04.21
A22: 20 | B22: 06.04.21 | C22: 20 | D22: 19 | E22: 161001256 | F22: 55 | G22: 3310.27 | H22: 262.73 | I22: 0 | J22: 0 | K22: 0 | L22: 0 | M22: 0 | N22: 0 | Q22: 0 | R22: 0 | S22: =R22*5% -> 0 | T22: =R22+S22 -> 0 | U22: PSPM
A23: 21 | B23: 06.04.21 | C23: 21 | D23: 20 | E23: 161001257 | F23: 58 | G23: 3441.42 | H23: 328.58 | I23: 0 | J23: 0 | K23: 0 | L23: 0 | M23: 0 | N23: 0 | Q23: 0 | R23: 0 | S23: =R23*5% -> 0 | T23: =R23+S23 -> 0 | U23: PSPM
A24: 22 | B24: 06.04.21 | C24: 22 | D24: 21 | E24: 161001258 | F24: 58 | G24: 3406.03 | H24: 362.97 | I24: 0 | J24: 0 | K24: 0 | L24: 0 | M24: 0 | N24: 0 | Q24: 0 | R24: 0 | S24: =R24*5% -> 0 | T24: =R24+S24 -> 0 | U24: PSPM
A25: 23 | B25: 06.04.21 | C25: 23 | D25: 22 | E25: 161001259 | F25: 54 | G25: 3147.66 | H25: 362.34 | I25: 0 | J25: 0 | K25: 0 | L25: 0 | M25: 0 | N25: 0 | Q25: 0 | R25: 0 | S25: =R25*5% -> 0 | T25: =R25+S25 -> 0 | U25: PSPM
A26: 24 | B26: 07.04.21 | C26: 24 | D26: 23 | E26: 161001260 | F26: 59 | G26: 3433.41 | H26: 401.59 | I26: 0 | J26: 0 | K26: 0 | L26: 0 | M26: 0 | N26: 0 | Q26: 0 | R26: 0 | S26: =R26*5% -> 0 | T26: =R26+S26 -> 0 | U26: PSPM
A27: 25 | B27: 07.04.21 | C27: 25 | D27: 24 | E27: 161001261 | F27: 57 | G27: 3367.84 | H27: 336.16 | I27: 0 | J27: 0 | K27: 0 | L27: 0 | M27: 0 | N27: 0 | Q27: 0 | R27: 0 | S27: =R27*5% -> 0 | T27: =R27+S27 -> 0 | U27: PSPM
A28: 26 | B28: 07.04.21 | C28: 26 | D28: 25 | E28: 161001262 | F28: 58 | G28: 3469.63 | H28: 299.37 | I28: 0 | J28: 0 | K28: 0 | L28: 0 | M28: 0 | N28: 0 | Q28: 0 | R28: 0 | S28: =R28*5% -> 0 | T28: =R28+S28 -> 0 | U28: PSPM
A29: 27 | B29: 07.04.21 | C29: 27 | D29: 26 | E29: 161001263 | F29: 56 | G29: 3297.66 | H29: 340.34 | I29: 0 | J29: 0 | K29: 0 | L29: 0 | M29: 0 | N29: 0 | Q29: 0 | R29: 0 | S29: =R29*5% -> 0 | T29: =R29+S29 -> 0 | U29: PSPM
A30: 28 | B30: 07.04.21 | C30: 28 | D30: 27 | E30: 161001264 | F30: 57 | G30: 3296.29 | H30: 402.71 | I30: 0 | J30: 0 | K30: 0 | L30: 0 | M30: 0 | N30: 0 | Q30: 0 | R30: 0 | S30: =R30*5% -> 0 | T30: =R30+S30 -> 0 | U30: PSPM
A31: 29 | B31: 08.04.21 | C31: 29 | D31: 28 | E31: 161001265 | F31: 58 | G31: 3365.63 | H31: 403.37 | I31: 0 | J31: 0 | K31: 0 | L31: 0 | M31: 0 | N31: 0 | Q31: 0 | R31: 0 | S31: =R31*5% -> 0 | T31: =R31+S31 -> 0 | U31: PSPM
A32: 30 | B32: 08.04.21 | C32: 30 | D32: 29 | E32: 161001266 | F32: 58 | G32: 3364.62 | H32: 405.38 | I32: 0 | J32: 0 | K32: 0 | L32: 0 | M32: 0 | N32: 0 | Q32: 0 | R32: 0 | S32: =R32*5% -> 0 | T32: =R32+S32 -> 0 | U32: PSPM
A33: 31 | B33: 08.04.21 | C33: 31 | D33: 30 | E33: 161001267 | F33: 59 | G33: 3505.84 | H33: 326.16 | I33: 0 | J33: 0 | K33: 0 | L33: 0 | M33: 0 | N33: 0 | Q33: 0 | R33: 0 | S33: =R33*5% -> 0 | T33: =R33+S33 -> 0 | U33: PSPM
... A126: 124 | B126: 25.04.21 | C126: 124 | D126: 123 | E126: 161001351 | F126: 59 | G126: 3515.81 | H126: 319.19 | I126: 0 | J126: 0 | K126: 0 | L126: 0 | M126: 0 | N126: 0 | Q126: 0 | R126: 0 | S126: =R126*5% -> 0 | T126: =R126+S126 -> 0 | U126: PSPM
A127: 125 | B127: 25.04.21 | C127: 125 | D127: 124 | E127: 161001353 | F127: 55 | G127: 3240.31 | H127: 334.88 | I127: 0 | J127: 2 | K127: 0 | L127: 1 | M127: 8250 | N127: 1 | Q127: 14990 | R127: =M127+Q127 -> 23240 | S127: =R127*5% -> 1162 | T127: =R127+S127 -> 24402 | U127: PSPM | V127: DUE TO WBPDCL BADHAL WAS HAPPENED SHUNTING CHARGES
A128: 126 | B128: 25.04.21 | C128: 126 | D128: 125 | E128: 161001354 | F128: 59 | G128: 3535.73 | H128: 297.27 | I128: 0 | J128: 0 | K128: 0 | L128: 0 | M128: 0 | N128: 0 | Q128: 0 | R128: 0 | S128: =R128*5% -> 0 | T128: =R128+S128 -> 0 | U128: PSPM
A129: 127 | B129: 25.04.21 | C129: 127 | D129: 126 | E129: 161001355 | F129: 59 | G129: 3415.01 | H129: 419.99 | I129: 0 | J129: 0 | K129: 0 | L129: 0 | M129: 0 | N129: 0 | Q129: 0 | R129: 0 | S129: =R129*5% -> 0 | T129: =R129+S129 -> 0 | U129: PSPM
A130: 128 | B130: 25.04.21 | C130: 128 | D130: 127 | E130: 161001356 | F130: 59 | G130: 3408.81 | H130: 426.19 | I130: 0 | J130: 0 | K130: 0 | L130: 0 | M130: 0 | N130: 0 | Q130: 0 | R130: 0 | S130: =R130*5% -> 0 | T130: =R130+S130 -> 0 | U130: PSPM
A131: 129 | B131: 25.04.21 | C131: 129 | D131: 128 | E131: 161001357 | F131: 59 | G131: 3443.21 | H131: 391.79 | I131: 0 | J131: 0 | K131: 0 | L131: 0 | M131: 0 | N131: 0 | Q131: 0 | R131: 0 | S131: =R131*5% -> 0 | T131: =R131+S131 -> 0 | U131: PSPM
A132: 130 | B132: 25.04.21 | C132: 130 | D132: 129 | E132: 161001358 | F132: 58 | G132: 3362.06 | H132: 403.94 | I132: 0 | J132: 0 | K132: 0 | L132: 0 | M132: 0 | N132: 0 | Q132: 0 | R132: 0 | S132: =R132*5% -> 0 | T132: =R132+S132 -> 0 | U132: PSPM
A133: 131 | B133: 26.04.21 | C133: 131 | D133: 130 | E133: 161001359 | F133: 56 | G133: 3218.48 | H133: 417.52 | I133: 0 | J133: 0 | K133: 0 | L133: 0 | M133: 5700 | N133: 0 | Q133: 0 | R133: 5700 | S133: =R133*5% -> 285 | T133: 0 | U133: PSPM | V133: COLLECTED AGAINST 161001347 BAL AMOUNT
A134: 132 | B134: 26.04.21 | C134: 132 | D134: 131 | E134: 161001360 | F134: 59 | G134: 3379.83 | H134: 453.17 | I134: 0 | J134: 0 | K134: 0 | L134: 0 | M134: 0 | N134: 0 | Q134: 0 | R134: 0 | S134: =R134*5% -> 0 | T134: =R134+S134 -> 0 | U134: PSPM
A135: 133 | B135: 26.04.21 | C135: 133 | D135: 132 | E135: 161001361 | F135: 59 | G135: 3450.03 | H135: 382.97 | I135: 0 | J135: 0 | K135: 0 | L135: 0 | M135: 0 | N135: 0 | Q135: 0 | R135: 0 | S135: =R135*5% -> 0 | T135: =R135+S135 -> 0 | U135: PSPM
A136: 134 | B136: 26.04.21 | C136: 134 | D136: 133 | E136: 161001362 | F136: 59 | G136: 3440.21 | H136: 394.79 | I136: 0 | J136: 0 | K136: 0 | L136: 0 | M136: 0 | N136: 0 | Q136: 0 | R136: 0 | S136: =R136*5% -> 0 | T136: =R136+S136 -> 0 | U136: PSPM
A137: 135 | B137: 26.04.21 | C137: 135 | D137: 134 | E137: 161001363 | F137: 58 | G137: 3399.84 | H137: 368.16 | I137: 0 | J137: 0 | K137: 0 | L137: 0 | M137: 0 | N137: 0 | Q137: 0 | R137: 0 | S137: =R137*5% -> 0 | T137: =R137+S137 -> 0 | U137: PSPM
A138: 136 | B138: 27.04.21 | C138: 136 | D138: 135 | E138: 161001364 | F138: 56 | G138: 3299.3 | H138: 398.7 | I138: 0 | J138: 0 | K138: 0 | L138: 0 | M138: 0 | N138: 0 | Q138: 0 | R138: 0 | S138: =R138*5% -> 0 | T138: =R138+S138 -> 0 | U138: PSPM
A139: 137 | B139: 27.04.21 | C139: 137 | D139: 136 | E139: 161001365 | F139: 59 | G139: 3475.81 | H139: 359.19 | I139: 0 | J139: 0 | K139: 0 | L139: 0 | M139: 0 | N139: 0 | Q139: 0 | R139: 0 | S139: =R139*5% -> 0 | T139: =R139+S139 -> 0 | U139: PSPM
A140: 138 | B140: 27.04.21 | C140: 138 | D140: 137 | E140: 161001366 | F140: 59 | G140: 3503.61 | H140: 331.39 | I140: 0 | J140: 0 | K140: 0 | L140: 0 | M140: 0 | N140: 0 | Q140: 0 | R140: 0 | S140: =R140*5% -> 0 | T140: =R140+S140 -> 0 | U140: PSPM
A141: 139 | B141: 27.04.21 | C141: 139 | D141: 138 | E141: 161001367 | F141: 55 | G141: 3194.49 | H141: 376.51 | I141: 0 | J141: 0 | K141: 0 | L141: 0 | M141: 0 | N141: 0 | Q141: 0 | R141: 0 | S141: =R141*5% -> 0 | T141: =R141+S141 -> 0 | U141: PSPM
A142: 140 | B142: 27.04.21 | C142: 140 | D142: 139 | E142: 161001368 | F142: 58 | G142: 3400.84 | H142: 367.16 | I142: 0 | J142: 0 | K142: 0 | L142: 0 | M142: 0 | N142: 0 | Q142: 0 | R142: 0 | S142: =R142*5% -> 0 | T142: =R142+S142 -> 0 | U142: PSPM
A143: 141 | B143: 27.04.21 | C143: 141 | D143: 140 | E143: 161001369 | F143: 59 | G143: 3438.63 | H143: 394.37 | I143: 0 | J143: 0 | K143: 0 | L143: 0 | M143: 0 | N143: 0 | Q143: 0 | R143: 0 | S143: =R143*5% -> 0 | T143: =R143+S143 -> 0 | U143: PSPM
A144: 142 | B144: 27.04.21 | C144: 142 | D144: 141 | E144: 161001370 | F144: 59 | G144: 3438.41 | H144: 396.59 | I144: 0 | J144: 0 | K144: 0 | L144: 0 | M144: 0 | N144: 0 | Q144: 0 | R144: 8850 | S144: =R144*5% -> 442.5 | T144: =R144+S144 -> 9292.5 | U144: PSPM | V144: LOADING DELAY D.C | X144: DUE TO 3 LOADERS ONLY WORKED
A145: 143 | B145: 28.04.21 | C145: 143 | D145: 142 | E145: 161001371 | F145: 59 | G145: 3470.41 | H145: 364.59 | I145: 0 | J145: 0 | K145: 0 | L145: 0 | M145: 0 | N145: 0 | Q145: 0 | R145: 0 | S145: =R145*5% -> 0 | T145: =R145+S145 -> 0 | U145: PSPM
A146: 144 | B146: 28.04.21 | C146: 144 | D146: 143 | E146: 161001372 | F146: 59 | G146: 3437.23 | H146: 395.77 | I146: 0 | J146: 0 | K146: 0 | L146: 0 | M146: 0 | N146: 0 | Q146: 0 | R146: 0 | S146: =R146*5% -> 0 | T146: =R146+S146 -> 0 | U146: PSPM
A147: 145 | B147: 28.04.21 | C147: 145 | D147: 144 | E147: 161001373 | F147: 58 | G147: 3392.86 | H147: 373.14 | I147: 0 | J147: 0 | K147: 0 | L147: 0 | M147: 0 | N147: 0 | Q147: 0 | R147: 0 | S147: =R147*5% -> 0 | T147: =R147+S147 -> 0 | U147: PSPM
A148: 146 | B148: 28.04.21 | C148: 146 | D148: 145 | E148: 161001374 | F148: 59 | G148: 3431.21 | H148: 403.79 | I148: 0 | J148: 0 | K148: 0 | L148: 0 | M148: 0 | N148: 0 | Q148: 0 | R148: 0 | S148: =R148*5% -> 0 | T148: =R148+S148 -> 0 | U148: PSPM
A149: 147 | B149: 28.04.21 | C149: 147 | D149: 146 | E149: 161001375 | F149: 58 | G149: 3392.03 | H149: 376.97 | I149: 0 | J149: 0 | K149: 0 | L149: 0 | M149: 0 | N149: 0 | Q149: 0 | R149: 0 | S149: =R149*5% -> 0 | T149: =R149+S149 -> 0 | U149: PSPM
A150: 148 | B150: 28.04.21 | C150: 148 | D150: 147 | E150: 161001376 | F150: 59 | G150: 3470.21 | H150: 364.79 | I150: 0 | J150: 0 | K150: 0 | L150: 0 | M150: 0 | N150: 0 | Q150: 0 | R150: 0 | S150: =R150*5% -> 0 | T150: =R150+S150 -> 0 | U150: PSPM
A151: 149 | B151: 29.04.21 | C151: 149 | D151: 148 | E151: 161001377 | F151: 54 | G151: 3140.9 | H151: 365.1 | I151: 0 | J151: 0 | K151: 0 | L151: 0 | M151: 0 | N151: 0 | Q151: 0 | R151: 0 | S151: =R151*5% -> 0 | T151: =R151+S151 -> 0 | U151: PSPM
A152: 150 | B152: 29.04.21 | C152: 150 | D152: 149 | E152: 161001378 | F152: 59 | G152: 3459.01 | H152: 375.99 | I152: 0 | J152: 0 | K152: 0 | L152: 0 | M152: 0 | N152: 0 | Q152: 0 | R152: 0 | S152: =R152*5% -> 0 | T152: =R152+S152 -> 0 | U152: PSPM
A153: 151 | B153: 29.04.21 | C153: 151 | D153: 150 | E153: 161001379 | F153: 59 | G153: 3453.43 | H153: 379.57 | I153: 0 | J153: 0 | K153: 0 | L153: 0 | M153: 0 | N153: 0 | Q153: 0 | R153: 0 | S153: =R153*5% -> 0 | T153: =R153+S153 -> 0 | U153: PSPM
A154: 152 | B154: 29.04.21 | C154: 152 | D154: 151 | E154: 161001380 | F154: 58 | G154: 3335.44 | H154: 432.56 | I154: 0 | J154: 0 | K154: 0 | L154: 0 | M154: 0 | N154: 0 | Q154: 0 | R154: 0 | S154: =R154*5% -> 0 | T154: =R154+S154 -> 0 | U154: PSPM
A155: 153 | B155: 29.04.21 | C155: 153 | D155: 152 | E155: 161001381 | F155: 58 | G155: 3358.84 | H155: 409.16 | I155: 0 | J155: 0 | K155: 0 | L155: 0 | M155: 0 | N155: 0 | Q155: 0 | R155: 0 | S155: =R155*5% -> 0 | T155: =R155+S155 -> 0 | U155: PSPM
A156: 154 | B156: 29.04.21 | C156: 154 | D156: 153 | E156: 151000096 | F156: 59 | G156: 3473.81 | H156: 361.19 | I156: 0 | J156: 0 | K156: 0 | L156: 0 | M156: 0 | N156: 0 | Q156: 0 | R156: 0 | S156: =R156*5% -> 0 | T156: =R156+S156 -> 0 | U156: PSPM
... A163: 161 | B163: 30.04.21 | C163: 161 | D163: 162 | E163: 161001383 | F163: 59 | G163: 3424.62 | H163: 345.38 | I163: 0 | J163: 0 | K163: 0 | L163: 0 | M163: 0 | N163: 0 | Q163: 0 | R163: 0 | S163: =R163*5% -> 0 | T163: =R163+S163 -> 0 | U163: PSPM
F164: =SUM(F3:F163) -> 9331 | G164: =SUM(G3:G163) -> 549431.08 | H164: =SUM(H3:H163) -> 56848.26 | J164: =SUM(J3:J163) -> 3 | K164: =SUM(K3:K163) -> 0 | L164: =SUM(L3:L163) -> 3 | M164: =SUM(M3:M163) -> 25350 | N164: =SUM(N3:N163) -> 1 | Q164: =SUM(Q3:Q163) -> 14990 | R164: =SUM(R3:R163) -> 49190 | S164: =R164*5% -> 2459.5 | T164: =R164+S164 -> 51649.5
F165: =G164/A163 -> 3412.6154

Sheet MAY21
A1: MAY - 21 MONTH RAKE LOADING DATA
A2: SL NO | B2: LOADING DATE | C2: RAKE NO. | D2: PRIORTY NUMBER | E2: R.R NUMBER | F2: NO OF WAGON | G2: NET WEIGHT | H2: UNDER LOAD WT | I2: OVER LOAD WT | J2: O/L WAGON | K2: O/L CHARGE | L2: Loading Time (hr mm) | N2: DETENTION HOURS | O2: DETENTION CHARGES | P2: SHUNTING HOURS | Q2: SHUNTING CHARGES | R2: PILOT HOURS | S2: SHUNTING CHARGES | T2: PCLA | U2: GST 5% | V2: TOTAL AMOUNT RS | W2: DESTINATION | X2: RESULT DATE
A3: 1 | B3: 01.05.21 | C3: 1 | D3: 161 | E3: 161001384 | F3: 56 | G3: 3270.26 | H3: 367.74 | I3: 0 | J3: 0 | K3: 0 | N3: 2 | O3: 16800 | P3: 0 | S3: 0 | T3: 0 | U3: =O3*5% -> 840 | V3: =O3+U3 -> 17640 | W3: PSPM | X3: LOADING DELAY D.C 2 HOURS
A4: 2 | B4: 01.05.21 | C4: 2 | D4: 162 | E4: 161001385 | F4: 59 | G4: 3419.41 | H4: 415.59 | I4: 0 | J4: 0 | K4: 0 | N4: 0 | O4: 0 | P4: 0 | S4: 0 | T4: 0 | U4: 0 | V4: 0 | W4: PSPM
A5: 3 | B5: 01.05.21 | C5: 3 | D5: 163 | E5: 161001386 | F5: 59 | G5: 3464.68 | H5: 363.32 | I5: 0 | J5: 0 | K5: 0 | N5: 0 | O5: 0 | P5: 0 | S5: 0 | T5: 0 | U5: 0 | V5: 0 | W5: PSPM
A6: 4 | B6: 01.05.21 | C6: 4 | D6: 164 | E6: 161001387 | F6: 59 | G6: 3429.63 | H6: 403.37 | I6: 0 | J6: 0 | K6: 0 | N6: 0 | O6: 0 | P6: 0 | S6: 0 | T6: 0 | U6: 0 | V6: 0 | W6: PSPM
A7: 5 | B7: 02.05.21 | C7: 5 | D7: 165 | E7: 161001388 | F7: 59 | G7: 3487.41 | H7: 347.59 | I7: 0 | J7: 0 | K7: 0 | N7: 0 | O7: 0 | P7: 0 | S7: 0 | T7: 0 | U7: 0 | V7: 0 | W7: PSPM
A8: 6 | B8: 02.05.21 | C8: 6 | D8: 166 | E8: 161001389 | F8: 59 | G8: 3424.82 | H8: 409.18 | I8: 0 | J8: 0 | K8: 0 | N8: 0 | O8: 0 | P8: 0 | S8: 0 | T8: 0 | U8: 0 | V8: 0 | W8: PSPM
A9: 7 | B9: 02.05.21 | C9: 7 | D9: 167 | E9: 161001390 | F9: 58 | G9: 3351.64 | H9: 416.36 | I9: 0 | J9: 0 | K9: 0 | N9: 0 | O9: 0 | P9: 0 | S9: 0 | T9: 0 | U9: 0 | V9: 0 | W9: PSPM
A10: 8 | B10: 02.05.21 | C10: 8 | D10: 168 | E10: 161001391 | F10: 59 | G10: 3415.41 | H10: 419.59 | I10: 0 | J10: 0 | K10: 0 | N10: 0 | O10: 0 | P10: 0 | S10: 0 | T10: 0 | U10: 0 | V10: 0 | W10: PSPM
A11: 9 | B11: 02.05.21 | C11: 9 | D11: 169 | E11: 161001392 | F11: 57 | G11: 3289.24 | H11: 414.76 | I11: 0 | J11: 0 | K11: 0 | N11: 0 | O11: 0 | P11: 0 | S11: 0 | T11: 0 | U11: 0 | V11: 0 | W11: PSPM
A12: 10 | B12: 03.05.21 | C12: 10 | D12: 170 | E12: 161001393 | F12: 59 | G12: 3383.88 | H12: 444.12 | I12: 0 | J12: 0 | K12: 0 | N12: 0 | O12: 0 | P12: 0 | S12: 0 | T12: 0 | U12: 0 | V12: 0 | W12: PSPM
A13: 11 | B13: 03.05.21 | C13: 11 | D13: 172 | E13: 161001394 | F13: 59 | G13: 3455.82 | H13: 378.18 | I13: 0 | J13: 0 | K13: 0 | N13: 0 | O13: 0 | P13: 0 | S13: 0 | T13: 0 | U13: 0 | V13: 0 | W13: PSPM
A14: 12 | B14: 03.05.21 | C14: 12 | D14: 173 | E14: 161001395 | F14: 59 | G14: 3408.03 | H14: 424.97 | I14: 0 | J14: 0 | K14: 0 | N14: 0 | O14: 0 | P14: 0 | S14: 0 | T14: 0 | U14: 0 | V14: 0 | W14: PSPM
A15: 13 | B15: 03.05.21 | C15: 13 | D15: 174 | E15: 161001396 | F15: 59 | G15: 3430.41 | H15: 404.59 | I15: 0 | J15: 0 | K15: 0 | N15: 0 | O15: 0 | P15: 0 | S15: 0 | T15: 0 | U15: 0 | V15: 0 | W15: PSPM
... A18: 16 | B18: 04.05.21 | C18: 16 | D18: 177 | E18: 161001399 | F18: 59 | G18: 3400.21 | H18: 434.79 | I18: 0 | J18: 0 | K18: 0 | N18: 0 | O18: 0 | P18: 0 | S18: 0 | T18: 0 | U18: 0 | V18: 0 | W18: PSPM
A19: 17 | B19: 04.05.21 | C19: 17 | D19: 171 | E19: 161001400 | F19: 55 | G19: 3456.95 | H19: 367.05 | I19: 0 | J19: 0 | K19: 0 | N19: 0 | O19: 0 | P19: 0 | S19: 0 | T19: 0 | U19: 0 | V19: 0 | W19: BTMT | X19: BOXN
A20: 18 | B20: 04.05.21 | C20: 18 | D20: 179 | E20: 161001401 | F20: 55 | G20: 3341.57 | H20: 415.43 | I20: 0 | J20: 0 | K20: 0 | N20: 1 | O20: 8250 | P20: 0 | S20: 0 | T20: 0 | U20: =O20*5% -> 412.5 | V20: =O20+U20 -> 8662.5 | W20: BTMT | X20: BOXN | Y20: LOADING DC - 1HOUR/DUE TO TWO BOX DOOR OPENED
A21: 19 | B21: 04.05.21 | C21: 19 | D21: 178 | E21: 161001402 | F21: 58 | G21: 3344.82 | H21: 425.18 | I21: 0 | J21: 0 | K21: 0 | N21: 0 | O21: 0 | P21: 0 | S21: 0 | T21: 0 | U21: 0 | V21: 0 | W21: PSPM | Y21: SGTPP ON 07.04.21
A22: 20 | B22: 04.05.21 | C22: 20 | D22: 180 | E22: 161001403 | F22: 59 | G22: 3440.81 | H22: 394.19 | I22: 0 | J22: 0 | K22: 0 | N22: 0 | O22: 0 | P22: 0 | S22: 0 | T22: 0 | U22: 0 | V22: 0 | W22: PSPM
A23: 21 | B23: 04.05.21 | C23: 21 | D23: 181 | E23: 161001404 | F23: 59 | G23: 3406.02 | H23: 427.98 | I23: 0 | J23: 0 | K23: 0 | N23: 0 | O23: 0 | P23: 0 | S23: 0 | T23: 0 | U23: 0 | V23: 0 | W23: PSPM
A24: 22 | B24: 05.05.21 | C24: 22 | D24: 182 | E24: 161001405 | F24: 56 | G24: 3238.08 | H24: 397.92 | I24: 0 | J24: 0 | K24: 0 | N24: 0 | O24: 0 | P24: 0 | S24: 0 | T24: 0 | U24: 0 | V24: 0 | W24: PSPM
A25: 23 | B25: 05.05.21 | C25: 23 | D25: 183 | E25: 161001406 | F25: 59 | G25: 3415.43 | H25: 415.57 | I25: 0 | J25: 0 | K25: 0 | N25: 0 | O25: 0 | P25: 0 | S25: 0 | T25: 0 | U25: 0 | V25: 0 | W25: PSPM
A26: 24 | B26: 05.05.21 | C26: 24 | D26: 184 | E26: 161001407 | F26: 58 | G26: 3396.43 | H26: 372.57 | I26: 0 | J26: 0 | K26: 0 | N26: 0 | O26: 0 | P26: 0 | S26: 0 | T26: 0 | U26: 0 | V26: 0 | W26: PSPM
A27: 25 | B27: 05.05.21 | C27: 25 | D27: 185 | E27: 161001408 | F27: 59 | G27: 3480.24 | H27: 351.76 | I27: 0 | J27: 0 | K27: 0 | N27: 0 | O27: 0 | P27: 0 | S27: 0 | T27: 0 | U27: 0 | V27: 0 | W27: PSPM
A28: 26 | B28: 05.05.21 | C28: 26 | D28: 186 | E28: 161001409 | F28: 59 | G28: 3450.61 | H28: 384.39 | I28: 0 | J28: 0 | K28: 0 | N28: 0 | O28: 0 | P28: 0 | S28: 0 | T28: 0 | U28: 0 | V28: 0 | W28: PSPM
A29: 27 | B29: 05.05.21 | C29: 27 | D29: 187 | E29: 161001410 | F29: 58 | G29: 3442.03 | H29: 326.97 | I29: 0 | J29: 0 | K29: 0 | N29: 0 | O29: 0 | P29: 0 | S29: 0 | T29: 0 | U29: 0 | V29: 0 | W29: PSPM
A30: 28 | B30: 05.05.21 | C30: 28 | D30: 188 | E30: 161001411 | F30: 58 | G30: 3361.46 | H30: 404.54 | I30: 0 | J30: 0 | K30: 0 | N30: 0 | O30: 0 | P30: 0 | S30: 0 | T30: 0 | U30: 0 | V30: 0 | W30: PSPM
A31: 29 | B31: 05.05.21 | C31: 29 | D31: 189 | E31: 161001412 | F31: 58 | G31: 3328.82 | H31: 441.18 | I31: 0 | J31: 0 | K31: 0 | N31: 0 | O31: 0 | P31: 0 | S31: 0 | T31: 0 | U31: 0 | V31: 0 | W31: PSPM
A32: 30 | B32: 06.05.21 | C32: 30 | D32: 190 | E32: 161001413 | F32: 59 | G32: 3432.61 | H32: 402.39 | I32: 0 | J32: 0 | K32: 0 | N32: 0 | O32: 0 | P32: 0 | S32: 0 | T32: 0 | U32: 0 | V32: 0 | W32: PSPM
A33: 31 | B33: 06.05.21 | C33: 31 | D33: 192 | E33: 161001414 | F33: 59 | G33: 3470.45 | H33: 360.55 | I33: 0 | J33: 0 | K33: 0 | N33: 0 | O33: 0 | P33: 0 | S33: 0 | T33: 0 | U33: 0 | V33: 0 | W33: PSPM
A34: 32 | B34: 06.05.21 | C34: 32 | D34: 193 | E34: 161001415 | F34: 58 | G34: 3389.84 | H34: 378.16 | I34: 0 | J34: 0 | K34: 0 | N34: 0 | O34: 0 | P34: 0 | S34: 0 | T34: 0 | U34: 0 | V34: 0 | W34: PSPM
A35: 33 | B35: 06.05.21 | C35: 33 | D35: 191 | E35: 161001416 | F35: 50 | G35: 3165.5 | H35: 295.5 | I35: 0 | J35: 0 | K35: 0 | N35: 0 | O35: 0 | P35: 0 | S35: 0 | T35: 0 | U35: 0 | V35: 0 | W35: BTPC | X35: BOXN
A36: 34 | B36: 06.05.21 | C36: 34 | D36: 194 | E36: 161001417 | F36: 59 | G36: 3416.01 | H36: 418.99 | I36: 0 | J36: 0 | K36: 0 | N36: 0 | O36: 0 | P36: 0 | S36: 0 | T36: 0 | U36: 0 | V36: 0 | W36: PSPM
A37: 35 | B37: 06.05.21 | C37: 35 | D37: 195 | E37: 161001418 | F37: 59 | G37: 3406.82 | H37: 427.18 | I37: 0 | J37: 0 | K37: 0 | N37: 0 | O37: 0 | P37: 0 | S37: 0 | T37: 0 | U37: 0 | V37: 0 | W37: PSPM
A38: 36 | B38: 07.05.21 | C38: 36 | D38: 196 | E38: 161001419 | F38: 57 | G38: 3296.83 | H38: 408.17 | I38: 0 | J38: 0 | K38: 0 | N38: 0 | O38: 0 | P38: 0 | S38: 0 | T38: 0 | U38: 0 | V38: 0 | W38: PSPM
A39: 37 | B39: 07.05.21 | C39: 37 | D39: 197 | E39: 161001420 | F39: 58 | G39: 3404.83 | H39: 364.17 | I39: 0 | J39: 0 | K39: 0 | N39: 0 | O39: 0 | P39: 0 | S39: 0 | T39: 0 | U39: 0 | V39: 0 | W39: PSPM
A40: 38 | B40: 07.05.21 | C40: 38 | D40: 198 | E40: 161001421 | F40: 57 | G40: 3360.64 | H40: 343.36 | I40: 0 | J40: 0 | K40: 0 | N40: 0 | O40: 0 | P40: 0 | S40: 0 | T40: 0 | U40: 0 | V40: 0 | W40: PSPM
A41: 39 | B41: 07.05.21 | C41: 39 | D41: 200 | E41: 161001422 | F41: 58 | G41: 3394.63 | H41: 374.37 | I41: 0 | J41: 0 | K41: 0 | N41: 0 | O41: 0 | P41: 0 | S41: 0 | T41: 0 | U41: 0 | V41: 0 | W41: PSPM
A42: 40 | B42: 07.05.21 | C42: 40 | D42: 199 | E42: 161001423 | F42: 59 | G42: 3460.43 | H42: 372.57 | I42: 0 | J42: 0 | K42: 0 | N42: 0 | O42: 0 | P42: 0 | S42: 0 | T42: 0 | U42: 0 | V42: 0 | W42: BTPC
A43: 41 | B43: 07.05.21 | C43: 41 | D43: 201 | E43: 161001424 | F43: 58 | G43: 3363.82 | H43: 406.18 | I43: 0 | J43: 0 | K43: 0 | N43: 0 | O43: 0 | P43: 0 | S43: 0 | T43: 0 | U43: 0 | V43: 0 | W43: PSPM
A44: 42 | B44: 07.05.21 | C44: 42 | D44: 202 | E44: 161001425 | F44: 58 | G44: 3323.44 | H44: 444.56 | I44: 0 | J44: 0 | K44: 0 | N44: 0 | O44: 0 | P44: 0 | S44: 0 | T44: 0 | U44: 0 | V44: 0 | W44: PSPM
A45: 43 | B45: 08.05.21 | C45: 43 | D45: 203 | E45: 161001426 | F45: 59 | G45: 3424.61 | H45: 410.39 | I45: 0 | J45: 0 | K45: 0 | N45: 0 | O45: 0 | P45: 0 | S45: 0 | T45: 0 | U45: 0 | V45: 0 | W45: BTPC
A46: 44 | B46: 08.05.21 | C46: 44 | D46: 204 | E46: 161001427 | F46: 59 | G46: 3396.62 | H46: 437.38 | I46: 0 | J46: 0 | K46: 0 | N46: 0 | O46: 0 | P46: 0 | S46: 0 | T46: 0 | U46: 0 | V46: 0 | W46: PSPM
A47: 45 | B47: 08.05.21 | C47: 45 | D47: 205 | E47: 161001428 | F47: 58 | G47: 3376.23 | H47: 392.77 | I47: 0 | J47: 0 | K47: 0 | N47: 0 | O47: 0 | P47: 0 | S47: 0 | T47: 0 | U47: 0 | V47: 0 | W47: PSPM
... A66: 64 | B66: 11.05.21 | C66: 64 | D66: 224 | E66: 161001447 | F66: 59 | G66: 3380.42 | H66: 453.58 | I66: 0 | J66: 0 | K66: 0 | N66: 0 | O66: 0 | P66: 0 | S66: 0 | T66: 0 | U66: 0 | V66: 0 | W66: PSPM
A67: 65 | B67: 11.05.21 | C67: 65 | D67: 225 | E67: 161001448 | F67: 58 | G67: 3339.63 | H67: 429.37 | I67: 0 | J67: 0 | K67: 0 | N67: 1 | O67: 8700 | P67: 0 | S67: 0 | T67: 0 | U67: =O67*5% -> 435 | V67: =O67+U67 -> 9135 | W67: PSPM | X67: 3 LOADERS ONLY WORKING LOADING DELAY
A68: 66 | B68: 11.05.21 | C68: 66 | D68: 226 | E68: 161001449 | F68: 58 | G68: 3308.43 | H68: 460.57 | I68: 0 | J68: 0 | K68: 0 | N68: 0 | O68: 0 | P68: 0 | S68: 0 | T68: 0 | U68: 0 | V68: 0 | W68: PSPM
A69: 67 | B69: 11.05.21 | C69: 67 | D69: 227 | E69: 161001450 | F69: 59 | G69: 3349.23 | H69: 483.77 | I69: 0 | J69: 0 | K69: 0 | N69: 0 | O69: 0 | P69: 0 | S69: 0 | T69: 0 | U69: 0 | V69: 0 | W69: PSPM
A70: 68 | B70: 11.05.21 | C70: 68 | D70: 228 | E70: 161001451 | F70: 58 | G70: 3334.82 | H70: 435.18 | I70: 0 | J70: 0 | K70: 0 | N70: 2 | O70: 17400 | P70: 0 | S70: 0 | T70: 0 | U70: =O70*5% -> 870 | V70: =O70+U70 -> 18270 | W70: PSPM | X70: TRUCK TOPPLED ON RACK COAL JAM AT TRACK 30 TON APPROX. - SUNIL KISKU
A71: 69 | B71: 11.05.21 | C71: 69 | D71: 229 | E71: 161001452 | F71: 58 | G71: 3272.09 | H71: 490.91 | I71: 0 | J71: 0 | K71: 0 | N71: 0 | O71: 0 | P71: 0 | S71: 0 | T71: 0 | U71: 0 | V71: 0 | W71: PSPM
A72: 70 | B72: 12.05.21 | C72: 70 | D72: 231 | E72: 161001453 | F72: 59 | G72: 3307.47 | H72: 521.53 | I72: 0 | J72: 0 | K72: 0 | N72: 0 | O72: 0 | P72: 0 | S72: 0 | T72: 0 | U72: 0 | V72: 0 | W72: PSPM
A73: 71 | B73: 12.05.21 | C73: 71 | D73: 230 | E73: 161001454 | F73: 59 | G73: 3357.42 | H73: 476.58 | I73: 0 | J73: 0 | K73: 0 | N73: 0 | O73: 0 | P73: 0 | S73: 0 | T73: 0 | U73: 0 | V73: 0 | W73: BTPC
A74: 72 | B74: 12.05.21 | C74: 72 | D74: 232 | E74: 161001455 | F74: 59 | G74: 3424.85 | H74: 406.15 | I74: 0 | J74: 0 | K74: 0 | N74: 0 | O74: 0 | P74: 0 | S74: 0 | T74: 0 | U74: 0 | V74: 0 | W74: PSPM
A75: 73 | B75: 12.05.21 | C75: 73 | D75: 239 | E75: 161001456 | F75: 59 | G75: 3349.43 | H75: 483.57 | I75: 0 | J75: 0 | K75: 0 | N75: 0 | O75: 0 | P75: 0 | S75: 0 | T75: 0 | U75: 0 | V75: 0 | W75: BTPC
A76: 74 | B76: 12.05.21 | C76: 74 | D76: 240 | E76: 161001457 | F76: 58 | G76: 3479.2 | H76: 580.8 | I76: 0 | J76: 0 | K76: 0 | N76: 0 | O76: 0 | P76: 0 | S76: 0 | T76: 0 | U76: 0 | V76: 0 | W76: BTMT
A77: 75 | B77: 12.05.21 | C77: 75 | D77: 233 | E77: 161001458 | F77: 58 | G77: 3283.63 | H77: 485.37 | I77: 0 | J77: 0 | K77: 0 | N77: 0 | O77: 0 | P77: 0 | S77: 0 | T77: 0 | U77: 0 | V77: 0 | W77: PSPM
A78: 76 | B78: 12.05.21 | C78: 76 | D78: 234 | E78: 161001459 | F78: 59 | G78: 3390.02 | H78: 443.98 | I78: 0 | J78: 0 | K78: 0 | N78: 0 | O78: 0 | P78: 0 | S78: 0 | T78: 0 | U78: 0 | V78: 0 | W78: PSPM
A79: 77 | B79: 13.05.21 | C79: 77 | D79: 235 | E79: 161001460 | F79: 58 | G79: 3372.03 | H79: 396.97 | I79: 0 | J79: 0 | K79: 0 | M79: 2.35 | N79: 0 | O79: 0 | P79: 0 | S79: 0 | T79: 0 | U79: 0 | V79: 0 | W79: PSPM
A80: 78 | B80: 13.05.21 | C80: 78 | D80: 236 | E80: 161001461 | F80: 58 | G80: 3278.04 | H80: 489.96 | I80: 0 | J80: 0 | K80: 0 | M80: 2.1 | N80: 0 | O80: 0 | P80: 0 | S80: 0 | T80: 0 | U80: 0 | V80: 0 | W80: PSPM
A81: 79 | B81: 13.05.21 | C81: 79 | D81: 237 | E81: 161001462 | F81: 59 | G81: 3098.25 | H81: 476.75 | I81: 0 | J81: 0 | K81: 0 | M81: 2 | N81: 0 | O81: 0 | P81: 0 | S81: 0 | T81: 0 | U81: 0 | V81: 0 | W81: PSPM
A82: 80 | B82: 13.05.21 | C82: 80 | D82: 238 | E82: 161001463 | F82: 58 | G82: 3440.33 | H82: 577.67 | I82: 0 | J82: 0 | K82: 0 | M82: 1.45 | N82: 0 | O82: 0 | P82: 0 | S82: 0 | T82: 0 | U82: 0 | V82: 0 | W82: PSPM
A83: 81 | B83: 13.05.21 | C83: 81 | D83: 241 | E83: 161001464 | F83: 59 | G83: 3317.07 | H83: 511.93 | I83: 0 | J83: 0 | K83: 0 | M83: 1.45 | N83: 0 | O83: 0 | P83: 0 | S83: 0 | T83: 0 | U83: 0 | V83: 0 | W83: PSPM
A84: 82 | B84: 13.05.21 | C84: 82 | D84: 242 | E84: 161001465 | F84: 57 | G84: 3308.27 | H84: 392.73 | I84: 0 | J84: 0 | K84: 0 | M84: 1.4 | N84: 0 | O84: 0 | P84: 0 | S84: 0 | T84: 0 | U84: 0 | V84: 0 | W84: PSPM
A85: 83 | B85: 13.05.21 | C85: 83 | D85: 243 | E85: 161001466 | F85: 59 | G85: 3389.81 | H85: 445.19 | I85: 0 | J85: 0 | K85: 0 | M85: 2 | N85: 0 | O85: 0 | P85: 0 | S85: 0 | T85: 0 | U85: 0 | V85: 0 | W85: PSPM
A86: 84 | B86: 14.05.21 | C86: 84 | D86: 244 | E86: 161001467 | F86: 59 | G86: 3399.85 | H86: 431.15 | I86: 0 | J86: 0 | K86: 0 | M86: 1.5 | N86: 0 | O86: 0 | P86: 0 | S86: 0 | T86: 0 | U86: 0 | V86: 0 | W86: PSPM
A87: 85 | B87: 14.05.21 | C87: 85 | D87: 245 | E87: 161001468 | F87: 59 | G87: 3393.61 | H87: 441.39 | I87: 0 | J87: 0 | K87: 0 | M87: 2.05 | N87: 0 | O87: 0 | P87: 0 | S87: 0 | T87: 0 | U87: 0 | V87: 0 | W87: PSPM
A88: 86 | B88: 14.05.21 | C88: 86 | D88: 246 | E88: 161001469 | F88: 58 | G88: 3404.43 | H88: 364.57 | I88: 0 | J88: 0 | K88: 0 | M88: 2 | N88: 0 | O88: 0 | P88: 0 | S88: 0 | T88: 0 | U88: 0 | V88: 0 | W88: PSPM
A89: 87 | B89: 14.05.21 | C89: 87 | D89: 247 | E89: 161001470 | F89: 57 | G89: 3371.64 | H89: 332.36 | I89: 0 | J89: 0 | K89: 0 | M89: 1.5 | N89: 0 | O89: 0 | P89: 0 | S89: 0 | T89: 0 | U89: 0 | V89: 0 | W89: PSPM
A90: 88 | B90: 14.05.21 | C90: 88 | D90: 248 | E90: 161001471 | F90: 59 | G90: 3433.82 | H90: 400.18 | I90: 0 | J90: 0 | K90: 0 | M90: 2.05 | N90: 0 | O90: 0 | P90: 0 | S90: 0 | T90: 0 | U90: 0 | V90: 0 | W90: PSPM
... A94: 92 | B94: 14.05.21 | C94: 92 | D94: 252 | E94: 141000074 | F94: 59 | G94: 3526.22 | H94: 307.78 | I94: 0 | J94: 0 | K94: 0 | M94: 2.35 | N94: 0 | O94: 0 | P94: 0 | S94: 0 | T94: 0 | U94: 0 | V94: 0 | W94: PSPM
A95: 93 | B95: 15.05.21 | C95: 93 | D95: 253 | E95: 161001475 | F95: 59 | G95: 3439.87 | H95: 389.13 | I95: 0 | J95: 0 | K95: 0 | L95: 2 | M95: 50 | N95: 0 | O95: 0 | P95: 0 | S95: 0 | T95: 0 | U95: 0 | V95: 0 | W95: PSPM
A96: 94 | B96: 15.05.21 | C96: 94 | D96: 254 | E96: 161001476 | F96: 59 | G96: 3338.42 | H96: 431.58 | I96: 0 | J96: 0 | K96: 0 | L96: 2 | M96: 25 | N96: 0 | O96: 0 | P96: 0 | S96: 0 | T96: 0 | U96: 0 | V96: 0 | W96: PSPM
A97: 95 | B97: 15.05.21 | C97: 95 | D97: 255 | E97: 161001477 | F97: 59 | G97: 3405.85 | H97: 425.15 | I97: 0 | J97: 0 | K97: 0 | L97: 2 | M97: 15 | N97: 0 | O97: 0 | P97: 0 | S97: 0 | T97: 0 | U97: 0 | V97: 0 | W97: PSPM
A98: 96 | B98: 15.05.21 | C98: 96 | D98: 256 | E98: 161001478 | F98: 58 | G98: 3460.62 | H98: 309.38 | I98: 0 | J98: 0 | K98: 0 | L98: 2 | M98: 15 | N98: 0 | O98: 0 | P98: 0 | S98: 0 | T98: 0 | U98: 0 | V98: 0 | W98: PSPM
A99: 97 | B99: 16.05.21 | C99: 97 | D99: 257 | E99: 161001479 | F99: 58 | G99: 3454.22 | H99: 315.78 | I99: 0 | J99: 0 | K99: 0 | L99: 2 | M99: 30 | N99: 0 | O99: 0 | P99: 0 | S99: 0 | T99: 0 | U99: 0 | V99: 0 | W99: PSPM
A100: 98 | B100: 16.05.21 | C100: 98 | D100: 258 | E100: 161001480 | F100: 58 | G100: 3432.23 | H100: 336.77 | I100: 0 | J100: 0 | K100: 0 | L100: 2 | M100: 50 | N100: 0 | O100: 0 | P100: 0 | S100: 0 | T100: 0 | U100: 0 | V100: 0 | W100: PSPM
A101: 99 | B101: 16.05.21 | C101: 99 | D101: 259 | E101: 161001481 | F101: 59 | G101: 3408.63 | H101: 424.37 | I101: 0 | J101: 0 | K101: 0 | L101: 2 | M101: 10 | N101: 0 | O101: 0 | P101: 0 | S101: 0 | T101: 0 | U101: 0 | V101: 0 | W101: PSPM
A102: 100 | B102: 16.05.21 | C102: 100 | D102: 260 | E102: 161001482 | F102: 58 | G102: 3389.04 | H102: 378.96 | I102: 0 | J102: 0 | K102: 0 | L102: 2 | M102: 20 | N102: 0 | O102: 0 | P102: 0 | S102: 0 | T102: 0 | U102: 0 | V102: 0 | W102: PSPM
A103: 101 | B103: 16.05.21 | C103: 101 | D103: 261 | E103: 161001483 | F103: 56 | G103: 3243.04 | H103: 396.96 | I103: 0 | J103: 0 | K103: 0 | L103: 1 | M103: 50 | N103: 0 | O103: 0 | P103: 0 | S103: 0 | T103: 0 | U103: 0 | V103: 0 | W103: PSPM
A104: 102 | B104: 16.05.21 | C104: 102 | D104: 262 | E104: 161001484 | F104: 56 | G104: 3269.64 | H104: 370.36 | I104: 0 | J104: 0 | K104: 0 | L104: 2 | M104: 10 | N104: 0 | O104: 0 | P104: 0 | S104: 0 | T104: 0 | U104: 0 | V104: 0 | W104: PSPM
A105: 103 | B105: 17.05.21 | C105: 103 | D105: 263 | E105: 161001485 | F105: 59 | G105: 3357.67 | H105: 407.33 | I105: 0 | J105: 0 | K105: 0 | L105: 2 | M105: 45 | N105: 0 | O105: 0 | P105: 0 | S105: 0 | T105: 0 | U105: 0 | V105: 0 | W105: PSPM
A106: 104 | B106: 17.05.21 | C106: 104 | D106: 264 | E106: 161001486 | F106: 59 | G106: 3287.87 | H106: 349.13 | I106: 0 | J106: 0 | K106: 0 | L106: 2 | M106: 5 | N106: 0 | O106: 0 | P106: 0 | S106: 0 | T106: 0 | U106: 0 | V106: 0 | W106: PSPM
... A122: 120 | B122: 19.05.21 | C122: 120 | D122: 281 | E122: 161001502 | F122: 59 | G122: 3360.52 | H122: 473.48 | I122: 0 | J122: 0 | K122: 0 | L122: 2 | M122: 0 | N122: 0 | O122: 0 | P122: 0 | S122: 0 | T122: 0 | U122: 0 | V122: 0 | W122: PSPM
A123: 121 | B123: 19.05.21 | C123: 121 | D123: 275 | E123: 161001503 | F123: 58 | G123: 3506 | H123: 325 | I123: 17.92 | J123: 5 | K123: 0 | L123: 2 | M123: 55 | N123: 0 | O123: 9 | P123: 157860 | S123: 0 | T123: 0 | U123: =P123*5% -> 7893 | V123: =P123+U123 -> 165753 | W123: BTPC | X123: COAL LOADED IN TO THE 4 DAMAGED WAGON 134910
A124: 122 | B124: 20.05.21 | C124: 122 | D124: 282 | E124: 161001504 | F124: 58 | G124: 3475.41 | H124: 359.59 | I124: 0 | J124: 0 | K124: 0 | L124: 2 | M124: 0 | N124: 0 | O124: 0 | P124: 0 | S124: 0 | T124: 0 | U124: 0 | V124: 0 | W124: PSPM | X124: O.L ADJUSTMENT 3 HOURS 22950/
A125: 123 | B125: 20.05.21 | C125: 123 | D125: 283 | E125: 161001505 | F125: 59 | G125: 3495.02 | H125: 338.98 | I125: 0 | J125: 0 | K125: 0 | L125: 2 | M125: 0 | N125: 0 | O125: 0 | P125: 0 | S125: 0 | T125: 0 | U125: 0 | V125: 0 | W125: PSPM
A126: 124 | B126: 20.05.21 | C126: 124 | D126: 284 | E126: 161001506 | F126: 58 | G126: 3351.22 | H126: 418.97 | I126: 0 | J126: 0 | K126: 0 | L126: 2 | M126: 5 | N126: 0 | O126: 0 | P126: 0 | S126: 0 | T126: 0 | U126: 0 | V126: 0 | W126: PSPM
A127: 125 | B127: 20.05.21 | C127: 125 | D127: 286 | E127: 161001507 | F127: 58 | G127: 3254.23 | H127: 514.77 | I127: 0 | J127: 0 | K127: 0 | L127: 2 | M127: 0 | N127: 0 | O127: 0 | P127: 0 | S127: 0 | T127: 0 | U127: 0 | V127: 0 | W127: PSPM
A128: 126 | B128: 20.05.21 | C128: 126 | D128: 287 | E128: 161001508 | F128: 59 | G128: 3342.03 | H128: 490.97 | I128: 0 | J128: 0 | K128: 0 | L128: 1 | M128: 40 | N128: 0 | O128: 0 | P128: 0 | S128: 0 | T128: 0 | U128: 0 | V128: 0 | W128: PSPM
A129: 127 | B129: 20.05.21 | C129: 127 | D129: 288 | E129: 161001509 | F129: 55 | G129: 3095.07 | H129: 477.93 | I129: 0 | J129: 0 | K129: 0 | L129: 2 | M129: 10 | N129: 0 | O129: 0 | P129: 0 | S129: 0 | T129: 0 | U129: 0 | V129: 0 | W129: PSPM
A130: 128 | B130: 20.05.21 | C130: 128 | D130: 289 | E130: 161001510 | F130: 58 | G130: 3321.22 | H130: 448.78 | I130: 0 | J130: 0 | K130: 0 | L130: 1 | M130: 50 | N130: 0 | O130: 0 | P130: 0 | S130: 0 | T130: 0 | U130: 0 | V130: 0 | W130: PSPM
A131: 129 | B131: 20.05.21 | C131: 129 | D131: 290 | E131: 161001511 | F131: 59 | G131: 3508.41 | H131: 326.59 | I131: 0 | J131: 0 | K131: 0 | L131: 1 | M131: 55 | N131: 0 | O131: 0 | P131: 0 | S131: 0 | T131: 0 | U131: 0 | V131: 0 | W131: PSPM
A132: 130 | B132: 21.05.21 | C132: 130 | D132: 285 | E132: 161001512 | F132: 59 | G132: 3404.22 | H132: 429.78 | I132: 0 | J132: 0 | K132: 0 | L132: 2 | M132: 10 | N132: 0 | O132: 0 | P132: 0 | S132: 0 | T132: 0 | U132: 0 | V132: 0 | W132: BTPC
A133: 131 | B133: 21.05.21 | C133: 131 | D133: 291 | E133: 161001513 | F133: 57 | G133: 3330.45 | H133: 372.55 | I133: 0 | J133: 0 | K133: 0 | L133: 2 | M133: 25 | N133: 0 | O133: 0 | P133: 0 | S133: 0 | T133: 0 | U133: 0 | V133: 0 | W133: PSPM
A134: 132 | B134: 21.05.21 | C134: 132 | D134: 292 | E134: 161001514 | F134: 58 | G134: 3304.02 | H134: 465.98 | I134: 0 | J134: 0 | K134: 0 | L134: 2 | M134: 10 | N134: 0 | O134: 0 | P134: 0 | S134: 0 | T134: 0 | U134: 0 | V134: 0 | W134: PSPM
A135: 133 | B135: 21.05.21 | C135: 133 | D135: 293 | E135: 161001515 | F135: 59 | G135: 3423.41 | H135: 411.59 | I135: 0 | J135: 0 | K135: 0 | L135: 1 | M135: 55 | N135: 0 | O135: 0 | P135: 0 | S135: 0 | T135: 0 | U135: 0 | V135: 0 | W135: PSPM
A136: 134 | B136: 21.05.21 | C136: 134 | D136: 294 | E136: 161001516 | F136: 58 | G136: 3307.29 | H136: 455.71 | I136: 0 | J136: 0 | K136: 0 | L136: 2 | M136: 55 | N136: 0 | O136: 0 | P136: 0 | S136: 0 | T136: 0 | U136: 0 | V136: 0 | W136: PSPM
... A141: 139 | B141: 22.05.21 | C141: 139 | D141: 299 | E141: 161001521 | F141: 57 | G141: 3312.85 | H141: 390.15 | I141: 0 | J141: 0 | K141: 0 | L141: 2 | M141: 25 | N141: 0 | O141: 0 | P141: 0 | S141: 0 | T141: 0 | U141: 0 | V141: 0 | W141: PSPM
A142: 140 | B142: 22.05.21 | C142: 140 | D142: 300 | E142: 161001522 | F142: 56 | G142: 3226.08 | H142: 409.92 | I142: 0 | J142: 0 | K142: 0 | L142: 1 | M142: 50 | N142: 0 | O142: 0 | P142: 0 | S142: 0 | T142: 0 | U142: 0 | V142: 0 | W142: PSPM | X142: DUE TO RAIN WITH THUNDER WEIGHMENT DONE AT PAKUR
...

Sheet JUN21
A1: JUNE - 21 MONTH RAKE LOADING DATA
A2: SL NO | B2: LOADING DATE | C2: RAKE NO. | D2: PRIORTY NUMBER | E2: R.R NUMBER | F2: NO OF WAGON | G2: NET WEIGHT | H2: UNDER LOAD WT | I2: OVER LOAD WT | J2: O/L WAGON | K2: O/L CHARGE | L2: Loading Time (hr mm) | N2: DETENTION HOURS | O2: DETENTION CHARGES | P2: SHUNTING HOURS | Q2: SHUNTING CHARGES | R2: PILOT HOURS | S2: SHUNTING CHARGES | T2: PCLA/PENALTY | U2: GST 5% | V2: TOTAL AMOUNT RS | W2: DESTINATION | X2: RESULT DATE
A3: 1 | B3: 01.06.21 | C3: 1 | D3: 362 | E3: 161001579 | F3: 59 | G3: 3285.73 | H3: 547.27 | I3: 0 | J3: 0 | K3: 0 | L3: 2 | M3: 15 | N3: 0 | O3: 0 | P3: 0 | S3: 0 | T3: 0 | U3: 0 | V3: 0 | W3: PSPM
A4: 2 | B4: 01.06.21 | C4: 2 | D4: 363 | E4: 161001580 | F4: 59 | G4: 3344.53 | H4: 488.47 | I4: 0 | J4: 0 | K4: 0 | L4: 2 | M4: 15 | N4: 0 | O4: 0 | P4: 0 | S4: 0 | T4: 0 | U4: 0 | V4: 0 | W4: PSPM
A5: 3 | B5: 01.06.21 | C5: 3 | D5: 365 | E5: 161001581 | F5: 59 | G5: 3337.51 | H5: 497.49 | I5: 0 | J5: 0 | K5: 0 | L5: 2 | M5: 0 | N5: 0 | O5: 0 | P5: 0 | S5: 0 | T5: 0 | U5: 0 | V5: 0 | W5: PSPM
A6: 4 | B6: 01.06.21 | C6: 4 | D6: 364 | E6: 161001582 | F6: 57 | G6: 3274.18 | H6: 425.82 | I6: 0 | J6: 0 | K6: 0 | L6: 2 | M6: 20 | N6: 0 | O6: 0 | P6: 0 | S6: 0 | T6: 0 | U6: 0 | V6: 0 | W6: BTPC
A7: 5 | B7: 01.06.21 | C7: 5 | D7: 366 | E7: 161001583 | F7: 58 | G7: 3191.63 | H7: 577.37 | I7: 0 | J7: 0 | K7: 0 | L7: 2 | M7: 40 | N7: 0 | O7: 0 | P7: 0 | S7: 0 | T7: 0 | U7: 0 | V7: 0 | W7: PSPM
A8: 6 | B8: 01.06.21 | C8: 6 | D8: 367 | E8: 161001584 | F8: 57 | G8: 3056.93 | H8: 648.07 | I8: 0 | J8: 0 | K8: 0 | L8: 1 | M8: 45 | N8: 0 | O8: 0 | P8: 0 | S8: 0 | T8: 0 | U8: 0 | V8: 0 | W8: PSPM
A9: 57 | B9: 02.06.21 | C9: 7 | D9: 368 | E9: 161001585 | F9: 59 | G9: 3431.77 | H9: 397.23 | I9: 0 | J9: 0 | K9: 0 | L9: 2 | M9: 25 | N9: 0 | O9: 0 | P9: 0 | S9: 0 | T9: 0 | U9: 0 | V9: 0 | W9: PSPM
A10: 8 | B10: 02.06.21 | C10: 8 | D10: 369 | E10: 161001586 | F10: 59 | G10: 3373.81 | H10: 461.19 | I10: 0 | J10: 0 | K10: 0 | L10: 2 | M10: 10 | N10: 0 | O10: 0 | P10: 0 | S10: 0 | T10: 0 | U10: 0 | V10: 0 | W10: PSPM
A11: 9 | B11: 02.06.21 | C11: 9 | D11: 370 | E11: 161001587 | F11: 57 | G11: 3215.83 | H11: 489.17 | I11: 0 | J11: 0 | K11: 0 | L11: 2 | M11: 0 | N11: 0 | O11: 0 | P11: 0 | S11: 0 | T11: 0 | U11: 0 | V11: 0 | W11: PSPM
A12: 10 | B12: 02.06.21 | C12: 10 | D12: 371 | E12: 161001588 | F12: 59 | G12: 3231.31 | H12: 603.69 | I12: 0 | J12: 0 | K12: 0 | L12: 1 | M12: 55 | N12: 0 | O12: 0 | P12: 0 | S12: 0 | T12: 0 | U12: 0 | V12: 0 | W12: PSPM
A13: 11 | B13: 03.06.21 | C13: 11 | D13: 373 | E13: 161001589 | F13: 58 | G13: 3250.93 | H13: 518.07 | I13: 0 | J13: 0 | K13: 0 | L13: 2 | M13: 5 | N13: 0 | O13: 0 | P13: 0 | S13: 0 | T13: 0 | U13: 0 | V13: 0 | W13: PSPM
A14: 12 | B14: 03.06.21 | C14: 12 | D14: 372 | E14: 161001590 | F14: 54 | G14: 2898.96 | H14: 611.04 | I14: 0 | J14: 0 | K14: 0 | L14: 2 | M14: 40 | N14: 0 | O14: 0 | P14: 0 | S14: 0 | T14: 40000 | U14: =T14*5% -> 2000 | V14: =T14+U14 -> 42000 | W14: BTPC | X14: 22.05.21 TO 31.05.21 PER DAY RS.4000/ + TAX
A15: 13 | B15: 03.06.21 | C15: 13 | D15: 374 | E15: 161001591 | F15: 58 | G15: 3189.33 | H15: 579.67 | I15: 0 | J15: 0 | K15: 0 | L15: 1 | M15: 45 | N15: 0 | O15: 0 | P15: 0 | S15: 0 | T15: 0 | U15: =T15*5% -> 0 | V15: =T15+U15 -> 0 | W15: PSPM
A16: 14 | B16: 03.06.21 | C16: 14 | D16: 375 | E16: 161001592 | F16: 57 | G16: 3230.23 | H16: 474.77 | I16: 0 | J16: 0 | K16: 0 | L16: 1 | M16: 40 | N16: 0 | O16: 0 | P16: 0 | S16: 0 | T16: 0 | U16: =T16*5% -> 0 | V16: =T16+U16 -> 0 | W16: PSPM
A17: 15 | B17: 03.06.21 | C17: 15 | D17: 376 | E17: 161001593 | F17: 59 | G17: 3348.31 | H17: 486.69 | I17: 0 | J17: 0 | K17: 0 | L17: 2 | M17: 20 | N17: 0 | O17: 0 | P17: 0 | S17: 0 | T17: 0 | U17: =T17*5% -> 0 | V17: =T17+U17 -> 0 | W17: BTPC
A18: 16 | B18: 04.06.21 | C18: 16 | D18: 377 | E18: 161001594 | F18: 59 | G18: 3314.81 | H18: 520.19 | I18: 0 | J18: 0 | K18: 0 | L18: 2 | M18: 10 | N18: 0 | O18: 0 | P18: 0 | S18: 0 | T18: 0 | U18: =T18*5% -> 0 | V18: =T18+U18 -> 0 | W18: PSPM
A19: 17 | B19: 04.06.21 | C19: 17 | D19: 378 | E19: 161001595 | F19: 59 | G19: 3332.71 | H19: 502.29 | I19: 0 | J19: 0 | K19: 0 | L19: 2 | M19: 5 | N19: 0 | O19: 0 | P19: 0 | S19: 0 | T19: 0 | U19: =T19*5% -> 0 | V19: =T19+U19 -> 0 | W19: BTPC
A20: 18 | B20: 04.06.21 | C20: 18 | D20: 379 | E20: 161001596 | F20: 57 | G20: 3180.44 | H20: 523.56 | I20: 0 | J20: 0 | K20: 0 | L20: 1 | M20: 55 | N20: 0 | O20: 0 | P20: 0 | S20: 0 | T20: 0 | U20: =T20*5% -> 0 | V20: =T20+U20 -> 0 | W20: PSPM
A21: 19 | B21: 04.06.21 | C21: 19 | D21: 380 | E21: 161001597 | F21: 56 | G21: 3053.34 | H21: 586.66 | I21: 0 | J21: 0 | K21: 0 | L21: 1 | M21: 55 | N21: 0 | O21: 0 | P21: 0 | S21: 0 | T21: 0 | U21: =T21*5% -> 0 | V21: =T21+U21 -> 0 | W21: PSPM
A22: 20 | B22: 05.06.21 | C22: 20 | D22: 381 | E22: 161001598 | F22: 59 | G22: 3324.35 | H22: 506.65 | I22: 0 | J22: 0 | K22: 0 | L22: 1 | M22: 50 | N22: 0 | O22: 0 | P22: 0 | S22: 0 | T22: 0 | U22: =T22*5% -> 0 | V22: =T22+U22 -> 0 | W22: BTPC
A23: 21 | B23: 05.06.21 | C23: 21 | D23: 382 | E23: 161001599 | F23: 57 | G23: 3291.53 | H23: 413.47 | I23: 0 | J23: 0 | K23: 0 | L23: 1 | M23: 50 | N23: 0 | O23: 0 | P23: 0 | S23: 0 | T23: 0 | U23: =T23*5% -> 0 | V23: =T23+U23 -> 0 | W23: PSPM
A24: 22 | B24: 05.06.21 | C24: 22 | D24: 383 | E24: 161001600 | F24: 57 | G24: 3247.54 | H24: 456.46 | I24: 0 | J24: 0 | K24: 0 | L24: 1 | M24: 45 | N24: 0 | O24: 0 | P24: 0 | S24: 0 | T24: 0 | U24: =T24*5% -> 0 | V24: =T24+U24 -> 0 | W24: BTPC | Y24: SUBMITTED ON 07.06.21
A25: 23 | B25: 06.06.21 | C25: 23 | D25: 384 | E25: 161001601 | F25: 56 | G25: 3176.54 | H25: 463.46 | I25: 0 | J25: 0 | K25: 0 | L25: 2 | M25: 5 | N25: 0 | O25: 0 | P25: 0 | S25: 0 | T25: 0 | U25: =T25*5% -> 0 | V25: =T25+U25 -> 0 | W25: PSPM
A26: 24 | B26: 07.06.21 | C26: 24 | D26: 385 | E26: 161001602 | F26: 58 | G26: 3319.42 | H26: 450.58 | I26: 0 | J26: 0 | K26: 0 | L26: 2 | M26: 30 | N26: 0 | O26: 0 | P26: 0 | S26: 0 | T26: 0 | U26: =T26*5% -> 0 | V26: =T26+U26 -> 0 | W26: BTPC
A27: 25 | B27: 07.06.21 | C27: 25 | D27: 386 | E27: 161001603 | F27: 58 | G27: 3228.03 | H27: 540.97 | I27: 0 | J27: 0 | K27: 0 | L27: 2 | M27: 0 | N27: 0 | O27: 0 | P27: 0 | S27: 0 | T27: 0 | U27: =T27*5% -> 0 | V27: =T27+U27 -> 0 | W27: PSPM
A28: 26 | B28: 07.06.21 | C28: 26 | D28: 387 | E28: 161001604 | F28: 59 | G28: 3278.94 | H28: 553.06 | I28: 0 | J28: 0 | K28: 0 | L28: 2 | M28: 5 | N28: 0 | O28: 0 | P28: 0 | S28: 0 | T28: 0 | U28: =T28*5% -> 0 | V28: =T28+U28 -> 0 | W28: PSPM
A29: 27 | B29: 07.06.21 | C29: 27 | D29: 388 | E29: 161001605 | F29: 58 | G29: 3314.12 | H29: 455.88 | I29: 0 | J29: 0 | K29: 0 | L29: 1 | M29: 55 | N29: 0 | O29: 0 | P29: 0 | S29: 0 | T29: 0 | U29: =T29*5% -> 0 | V29: =T29+U29 -> 0 | W29: BTPC
A30: 28 | B30: 07.06.21 | C30: 28 | D30: 389 | E30: 161001606 | F30: 58 | G30: 3393.43 | H30: 439.57 | I30: 0 | J30: 0 | K30: 0 | L30: 2 | M30: 5 | N30: 0 | O30: 0 | P30: 0 | S30: 0 | T30: 0 | U30: =T30*5% -> 0 | V30: =T30+U30 -> 0 | W30: BTPC
A31: 29 | B31: 07.06.21 | C31: 29 | D31: 390 | E31: 161001607 | F31: 59 | G31: 3376.73 | H31: 456.27 | I31: 0 | J31: 0 | K31: 0 | L31: 1 | M31: 55 | N31: 0 | O31: 0 | P31: 0 | S31: 0 | T31: 0 | U31: =T31*5% -> 0 | V31: =T31+U31 -> 0 | W31: PSPM
A32: 30 | B32: 08.06.21 | C32: 30 | D32: 391 | E32: 161001608 | F32: 56 | G32: 3225.28 | H32: 410.72 | I32: 0 | J32: 0 | K32: 0 | L32: 2 | M32: 10 | N32: 0 | O32: 0 | P32: 0 | S32: 0 | T32: 0 | U32: =T32*5% -> 0 | V32: =T32+U32 -> 0 | W32: BTPC
A33: 31 | B33: 08.06.21 | C33: 31 | D33: 393 | E33: 161001609 | F33: 56 | G33: 3109.04 | H33: 530.96 | I33: 0 | J33: 0 | K33: 0 | L33: 1 | M33: 50 | N33: 0 | O33: 0 | P33: 0 | S33: 0 | T33: 0 | U33: =T33*5% -> 0 | V33: =T33+U33 -> 0 | W33: PSPM
A34: 32 | B34: 08.06.21 | C34: 32 | D34: 392 | E34: 161001610 | F34: 56 | G34: 3227.14 | H34: 412.86 | I34: 0 | J34: 0 | K34: 0 | L34: 1 | M34: 50 | N34: 0 | O34: 0 | P34: 0 | S34: 0 | T34: 0 | U34: =T34*5% -> 0 | V34: =T34+U34 -> 0 | W34: BTPC
A35: 33 | B35: 08.06.21 | C35: 33 | D35: 395 | E35: 161001611 | F35: 58 | G35: 3322.53 | H35: 446.47 | I35: 0 | J35: 0 | K35: 0 | L35: 2 | M35: 30 | N35: 0 | O35: 0 | P35: 0 | S35: 0 | T35: 0 | U35: =T35*5% -> 0 | V35: =T35+U35 -> 0 | W35: PSPM
A36: 34 | B36: 08.06.21 | C36: 34 | D36: 394 | E36: 161001612 | F36: 59 | G36: 3392.51 | H36: 442.49 | I36: 0 | J36: 0 | K36: 0 | L36: 2 | M36: 0 | N36: 0 | O36: 0 | P36: 0 | S36: 0 | T36: 0 | U36: =T36*5% -> 0 | V36: =T36+U36 -> 0 | W36: BTPC
A37: 35 | B37: 08.06.21 | C37: 35 | D37: 396 | E37: 161001613 | F37: 56 | G37: 3263.34 | H37: 376.66 | I37: 0 | J37: 0 | K37: 0 | L37: 2 | M37: 5 | N37: 0 | O37: 0 | P37: 0 | S37: 0 | T37: 0 | U37: =T37*5% -> 0 | V37: =T37+U37 -> 0 | W37: BTPC
A38: 36 | B38: 09.06.21 | C38: 36 | D38: 397 | E38: 161001614 | F38: 57 | G38: 3374.53 | H38: 330.47 | I38: 0 | J38: 0 | K38: 0 | L38: 2 | M38: 35 | N38: 0 | O38: 0 | P38: 0 | S38: 0 | T38: 40000 | U38: =T38*5% -> 2000 | V38: =T38+U38 -> 42000 | W38: PSPM | X38: 01.06.21 TO 05.06.21
A39: 37 | B39: 09.06.21 | C39: 37 | D39: 398 | E39: 161001615 | F39: 58 | G39: 3427.55 | H39: 339.45 | I39: 0 | J39: 0 | K39: 0 | L39: 1 | M39: 55 | N39: 0 | O39: 0 | P39: 0 | S39: 0 | T39: 0 | U39: =T39*5% -> 0 | V39: =T39+U39 -> 0 | W39: PSPM
A40: 38 | B40: 09.06.21 | C40: 38 | D40: 399 | E40: 161001616 | F40: 59 | G40: 3463.15 | H40: 367.85 | I40: 0 | J40: 0 | K40: 0 | L40: 1 | M40: 30 | N40: 0 | O40: 0 | P40: 0 | S40: 0 | T40: 0 | U40: =T40*5% -> 0 | V40: =T40+U40 -> 0 | W40: PSPM
A41: 39 | B41: 10.06.21 | C41: 39 | D41: 400 | E41: 161001617 | F41: 56 | G41: 3264.44 | H41: 375.85 | I41: 0 | J41: 0 | K41: 0 | L41: 2 | M41: 0 | N41: 0 | O41: 0 | P41: 0 | S41: 0 | T41: 0 | U41: =T41*5% -> 0 | V41: =T41+U41 -> 0 | W41: PSPM
A42: 40 | B42: 10.06.21 | C42: 40 | D42: 401 | E42: 161001618 | F42: 56 | G42: 3250.85 | H42: 388.15 | I42: 0 | J42: 0 | K42: 0 | L42: 2 | M42: 10 | N42: 0 | O42: 0 | P42: 0 | S42: 0 | T42: 0 | U42: =T42*5% -> 0 | V42: =T42+U42 -> 0 | W42: PSPM
A43: 41 | B43: 10.06.21 | C43: 41 | D43: 402 | E43: 161001619 | F43: 57 | G43: 3307.93 | H43: 397.07 | I43: 0 | J43: 0 | K43: 0 | L43: 2 | M43: 0 | N43: 0 | O43: 0 | P43: 0 | S43: 0 | T43: 0 | U43: =T43*5% -> 0 | V43: =T43+U43 -> 0 | W43: PSPM
A44: 42 | B44: 10.06.21 | C44: 42 | D44: 403 | E44: 161001620 | F44: 56 | G44: 3237.14 | H44: 400.86 | I44: 0 | J44: 0 | K44: 0 | L44: 1 | M44: 55 | N44: 0 | O44: 0 | P44: 0 | S44: 0 | T44: 0 | U44: =T44*5% -> 0 | V44: =T44+U44 -> 0 | W44: PSPM
A45: 43 | B45: 11.06.21 | C45: 43 | D45: 404 | E45: 161001621 | F45: 58 | G45: 3285.43 | H45: 483.57 | I45: 0 | J45: 0 | K45: 0 | L45: 1 | M45: 55 | N45: 0 | O45: 0 | P45: 0 | S45: 0 | T45: 0 | U45: =T45*5% -> 0 | V45: =T45+U45 -> 0 | W45: PSPM
A46: 44 | B46: 11.06.21 | C46: 44 | D46: 405 | E46: 161001622 | F46: 58 | G46: 3312.15 | H46: 454.85 | I46: 0 | J46: 0 | K46: 0 | L46: 1 | M46: 55 | N46: 0 | O46: 0 | P46: 0 | S46: 0 | T46: 0 | U46: =T46*5% -> 0 | V46: =T46+U46 -> 0 | W46: PSPM
A47: 45 | B47: 11.06.21 | C47: 45 | D47: 406 | E47: 161001623 | F47: 58 | G47: 3312.95 | H47: 454.05 | I47: 0 | J47: 0 | K47: 0 | L47: 2 | M47: 25 | N47: 0 | O47: 0 | P47: 0 | S47: 0 | T47: 0 | U47: =T47*5% -> 0 | V47: =T47+U47 -> 0 | W47: PSPM
A48: 46 | B48: 11.06.21 | C48: 46 | D48: 407 | E48: 161001624 | F48: 59 | G48: 3409.27 | H48: 419.73 | I48: 0 | J48: 0 | K48: 0 | L48: 2 | M48: 0 | N48: 0 | O48: 0 | P48: 0 | S48: 0 | T48: 0 | U48: =T48*5% -> 0 | V48: =T48+U48 -> 0 | W48: PSPM
A49: 47 | B49: 11.06.21 | C49: 47 | D49: 408 | E49: 161001625 | F49: 56 | G49: 3288.14 | H49: 351.86 | I49: 0 | J49: 0 | K49: 0 | L49: 2 | M49: 5 | N49: 0 | O49: 0 | P49: 0 | S49: 0 | T49: 0 | U49: =T49*5% -> 0 | V49: =T49+U49 -> 0 | W49: PSPM
A50: 48 | B50: 12.06.21 | C50: 48 | D50: 409 | E50: 161001626 | F50: 55 | G50: 3122.25 | H50: 452.75 | I50: 0 | J50: 0 | K50: 0 | L50: 2 | M50: 0 | N50: 0 | O50: 0 | P50: 0 | S50: 0 | T50: 0 | U50: =T50*5% -> 0 | V50: =T50+U50 -> 0 | W50: PSPM
... A52: 50 | B52: 12.06.21 | C52: 50 | D52: 411 | E52: 161001628 | F52: 58 | G52: 3345.13 | H52: 423.87 | I52: 0 | J52: 0 | K52: 0 | L52: 1 | M52: 50 | N52: 0 | O52: 0 | P52: 0 | S52: 0 | T52: 0 | U52: =T52*5% -> 0 | V52: =T52+U52 -> 0 | W52: PSPM
A53: 51 | B53: 13.06.21 | C53: 51 | D53: 412 | E53: 161001629 | F53: 59 | G53: 3602.44 | H53: 229.65 | I53: 0.09 | J53: 0 | K53: 0 | L53: 1 | M53: 5 | N53: 0 | O53: 0 | P53: 0 | S53: 0 | T53: 40000 | U53: =T53*5% -> 2000 | V53: =T53+U53 -> 42000 | W53: PSPM | X53: 06.06.21 TO 10.06.21
A54: 52 | B54: 13.06.21 | C54: 52 | D54: 413 | E54: 161001630 | F54: 56 | G54: 3299.24 | H54: 340.76 | I54: 0 | J54: 0 | K54: 0 | L54: 1 | M54: 55 | N54: 0 | O54: 0 | P54: 0 | S54: 0 | T54: 0 | U54: =T54*5% -> 0 | V54: =T54+U54 -> 0 | W54: PSPM
A55: 53 | B55: 13.06.21 | C55: 53 | D55: 414 | E55: 161001631 | F55: 55 | G55: 3217.15 | H55: 363.83 | I55: 5.98 | J55: 2 | K55: 0 | L55: 2 | M55: 5 | N55: 0 | O55: 8250 | P55: 0 | S55: 0 | T55: 0 | U55: =O55*5% -> 412.5 | V55: =O55+U55 -> 8662.5 | W55: PSPM
A56: 54 | B56: 13.06.21 | C56: 54 | D56: 415 | E56: 161001632 | F56: 59 | G56: 3379.77 | H56: 449.23 | I56: 0 | J56: 0 | K56: 0 | L56: 1 | M56: 55 | N56: 0 | O56: 0 | P56: 0 | S56: 0 | T56: 0 | U56: =T56*5% -> 0 | V56: =T56+U56 -> 0 | W56: PSPM
A57: 55 | B57: 14.06.21 | C57: 55 | D57: 416 | E57: 161001633 | F57: 59 | G57: 3433.03 | H57: 399.97 | I57: 0 | J57: 0 | K57: 0 | L57: 2 | M57: 0 | N57: 0 | O57: 0 | P57: 0 | S57: 0 | T57: 0 | U57: =T57*5% -> 0 | V57: =T57+U57 -> 0 | W57: PSPM
A58: 56 | B58: 14.06.21 | C58: 56 | D58: 417 | E58: 161001634 | F58: 58 | G58: 3388.23 | H58: 380.77 | I58: 0 | J58: 0 | K58: 0 | L58: 2 | M58: 10 | N58: 0 | O58: 0 | P58: 0 | S58: 0 | T58: 0 | U58: =T58*5% -> 0 | V58: =T58+U58 -> 0 | W58: PSPM
A59: 57 | B59: 14.06.21 | C59: 57 | D59: 418 | E59: 161001635 | F59: 57 | G59: 3303.14 | H59: 400.86 | I59: 0 | J59: 0 | K59: 0 | L59: 2 | M59: 50 | N59: 0 | O59: 0 | P59: 0 | S59: 0 | T59: 0 | U59: =T59*5% -> 0 | V59: =T59+U59 -> 0 | W59: PSPM
A60: 58 | B60: 14.06.21 | C60: 58 | D60: 419 | E60: 161001636 | F60: 56 | G60: 3136.63 | H60: 508.36 | I60: 0 | J60: 0 | K60: 0 | L60: 2 | M60: 0 | N60: 0 | O60: 0 | P60: 0 | S60: 0 | T60: 0 | U60: =T60*5% -> 0 | V60: =T60+U60 -> 0 | W60: PSPM
A61: 59 | B61: 15.06.21 | C61: 59 | D61: 420 | E61: 161001637 | F61: 56 | G61: 3196.24 | H61: 443.76 | I61: 0 | J61: 0 | K61: 0 | L61: 2 | M61: 0 | N61: 0 | O61: 0 | P61: 0 | S61: 0 | T61: 0 | U61: =T61*5% -> 0 | V61: =T61+U61 -> 0 | W61: PSPM
A62: 60 | B62: 15.06.21 | C62: 60 | D62: 421 | E62: 161001638 | F62: 58 | G62: 3308.77 | H62: 456.23 | I62: 0 | J62: 0 | K62: 0 | L62: 1 | M62: 45 | N62: 0 | O62: 0 | P62: 0 | S62: 0 | T62: 0 | U62: =T62*5% -> 0 | V62: =T62+U62 -> 0 | W62: PSPM
A63: 61 | B63: 15.06.21 | C63: 61 | D63: 422 | E63: 161001639 | F63: 55 | G63: 3188.65 | H63: 386.35 | I63: 0 | J63: 0 | K63: 0 | L63: 1 | M63: 45 | N63: 0 | O63: 0 | P63: 0 | S63: 0 | T63: 0 | U63: =T63*5% -> 0 | V63: =T63+U63 -> 0 | W63: PSPM
A64: 62 | B64: 15.06.21 | C64: 62 | D64: 423 | E64: 161001640 | F64: 57 | G64: 3218.85 | H64: 484.15 | I64: 0 | J64: 0 | K64: 0 | L64: 1 | M64: 55 | N64: 0 | O64: 0 | P64: 0 | S64: 0 | T64: 0 | U64: =T64*5% -> 0 | V64: =T64+U64 -> 0 | W64: PSPM
A65: 63 | B65: 15.06.21 | C65: 63 | D65: 424 | E65: 161001641 | F65: 58 | G65: 3304.43 | H65: 464.57 | I65: 0 | J65: 0 | K65: 0 | L65: 1 | M65: 50 | N65: 0 | O65: 0 | P65: 0 | S65: 0 | T65: 0 | U65: =T65*5% -> 0 | V65: =T65+U65 -> 0 | W65: PSPM
A66: 64 | B66: 16.06.21 | C66: 64 | D66: 425 | E66: 161001642 | F66: 58 | G66: 3407.03 | H66: 361.97 | I66: 0 | J66: 0 | K66: 0 | L66: 1 | M66: 55 | N66: 0 | O66: 0 | P66: 0 | S66: 0 | T66: 0 | U66: =T66*5% -> 0 | V66: =T66+U66 -> 0 | W66: PSPM
A67: 65 | B67: 16.06.21 | C67: 65 | D67: 426 | E67: 161001643 | F67: 59 | G67: 3524.31 | H67: 310.69 | I67: 0 | J67: 0 | K67: 0 | L67: 1 | M67: 50 | N67: 0 | O67: 0 | P67: 0 | S67: 0 | T67: 0 | U67: =T67*5% -> 0 | V67: =T67+U67 -> 0 | W67: PSPM
... A74: 72 | B74: 18.06.21 | C74: 72 | D74: 433 | E74: 161001650 | F74: 58 | G74: 3379.02 | H74: 390.98 | I74: 0 | J74: 0 | K74: 0 | L74: 2 | M74: 0 | N74: 0 | O74: 0 | P74: 0 | S74: 0 | T74: 0 | U74: =T74*5% -> 0 | V74: =T74+U74 -> 0 | W74: PSPM
A75: 73 | B75: 18.06.21 | C75: 73 | D75: 434 | E75: 161001651 | F75: 57 | G75: 3359.48 | H75: 340.52 | I75: 0 | J75: 0 | K75: 0 | L75: 1 | M75: 50 | N75: 0 | O75: 0 | P75: 0 | S75: 0 | T75: 40000 | U75: =T75*5% -> 2000 | V75: =T75+U75 -> 42000 | W75: PSPM | X75: 11.06.21 TO 15.06.21
A76: 74 | B76: 18.06.21 | C76: 74 | D76: 435 | E76: 161001652 | F76: 59 | G76: 3436.71 | H76: 398.29 | I76: 0 | J76: 0 | K76: 0 | L76: 2 | M76: 10 | N76: 0 | O76: 0 | P76: 0 | S76: 0 | T76: 0 | U76: =T76*5% -> 0 | V76: =T76+U76 -> 0 | W76: BTPC
A77: 75 | B77: 18.06.21 | C77: 75 | D77: 436 | E77: 161001653 | F77: 56 | G77: 3235.56 | H77: 402.44 | I77: 0 | J77: 0 | K77: 0 | L77: 1 | M77: 50 | N77: 0 | O77: 0 | P77: 0 | S77: 0 | T77: 0 | U77: =T77*5% -> 0 | V77: =T77+U77 -> 0 | W77: PSPM
A78: 76 | B78: 19.06.21 | C78: 76 | D78: 437 | E78: 161001654 | F78: 58 | G78: 3380.93 | H78: 388.07 | I78: 0 | J78: 0 | K78: 0 | L78: 1 | M78: 55 | N78: 0 | O78: 0 | P78: 0 | S78: 0 | T78: 0 | U78: =T78*5% -> 0 | V78: =T78+U78 -> 0 | W78: PSPM
A79: 77 | B79: 19.06.21 | C79: 77 | D79: 438 | E79: 161001655 | F79: 57 | G79: 3356.33 | H79: 348.67 | I79: 0 | J79: 0 | K79: 0 | L79: 1 | M79: 45 | N79: 0 | O79: 0 | P79: 0 | S79: 0 | T79: 0 | U79: =T79*5% -> 0 | V79: =T79+U79 -> 0 | W79: PSPM
A80: 78 | B80: 19.06.21 | C80: 78 | D80: 439 | E80: 161001656 | F80: 57 | G80: 3292.04 | H80: 411.96 | I80: 0 | J80: 0 | K80: 0 | L80: 1 | M80: 45 | N80: 0 | O80: 0 | P80: 0 | S80: 0 | T80: 0 | U80: =T80*5% -> 0 | V80: =T80+U80 -> 0 | W80: BTPC
A81: 79 | B81: 19.06.21 | C81: 79 | D81: 440 | E81: 161001657 | F81: 57 | G81: 3315.95 | H81: 388.54 | I81: 1.49 | J81: 1 | K81: 0 | L81: 2 | M81: 10 | N81: 0 | O81: 8550 | P81: 0 | S81: 0 | T81: 0 | U81: =O81*5% -> 427.5 | V81: =O81+U81 -> 8977.5 | W81: PSPM
A82: 80 | B82: 20.06.21 | C82: 80 | D82: 441 | E82: 161001658 | F82: 58 | G82: 3172.45 | H82: 594.55 | I82: 0 | J82: 0 | K82: 0 | L82: 1 | M82: 50 | N82: 0 | O82: 0 | P82: 0 | S82: 0 | T82: 0 | U82: =T82*5% -> 0 | V82: =T82+U82 -> 0 | W82: PSPM
A83: 81 | B83: 20.06.21 | C83: 81 | D83: 442 | E83: 161001659 | F83: 54 | G83: 2964.06 | H83: 545.94 | I83: 0 | J83: 0 | K83: 0 | L83: 2 | M83: 0 | N83: 0 | O83: 0 | P83: 0 | S83: 0 | T83: 0 | U83: =T83*5% -> 0 | V83: =T83+U83 -> 0 | W83: BTPC
A84: 82 | B84: 20.06.21 | C84: 82 | D84: 443 | E84: 161001660 | F84: 57 | G84: 3201.03 | H84: 503.97 | I84: 0 | J84: 0 | K84: 0 | L84: 2 | M84: 10 | N84: 0 | O84: 0 | P84: 0 | S84: 0 | T84: 0 | U84: =T84*5% -> 0 | V84: =T84+U84 -> 0 | W84: PSPM | Y84: 22.06.21 SUBITTED TO SGTPP
A85: 83 | B85: 21.06.21 | C85: 83 | D85: 444 | E85: 161001661 | F85: 58 | G85: 3256.03 | H85: 512.97 | I85: 0 | J85: 0 | K85: 0 | L85: 2 | M85: 0 | N85: 0 | O85: 0 | P85: 0 | S85: 0 | T85: 0 | U85: =T85*5% -> 0 | V85: =T85+U85 -> 0 | W85: BTPC
A86: 84 | B86: 21.06.21 | C86: 84 | D86: 445 | E86: 141000080 | F86: 59 | G86: 3223.91 | H86: 611.09 | I86: 0 | J86: 0 | K86: 0 | L86: 1 | M86: 50 | N86: 0 | O86: 0 | P86: 0 | S86: 0 | T86: 0 | U86: =T86*5% -> 0 | V86: =T86+U86 -> 0 | W86: PSPM
A87: 85 | B87: 21.06.21 | C87: 85 | D87: 447 | E87: 161001662 | F87: 58 | G87: 3194.35 | H87: 572.65 | I87: 0 | J87: 0 | K87: 0 | L87: 1 | M87: 50 | N87: 0 | O87: 0 | P87: 0 | S87: 0 | T87: 0 | U87: =T87*5% -> 0 | V87: =T87+U87 -> 0 | W87: PSPM
A88: 86 | B88: 21.06.21 | C88: 86 | D88: 446 | E88: 161001663 | F88: 57 | G88: 3172.65 | H88: 530.35 | I88: 0 | J88: 0 | K88: 0 | L88: 1 | M88: 55 | N88: 0 | O88: 0 | P88: 0 | S88: 0 | T88: 0 | U88: =T88*5% -> 0 | V88: =T88+U88 -> 0 | W88: BTPC
A89: 87 | B89: 21.06.21 | C89: 87 | D89: 448 | E89: 161001664 | F89: 59 | G89: 3250.31 | H89: 584.69 | I89: 0 | J89: 0 | K89: 0 | L89: 2 | M89: 10 | N89: 0 | O89: 0 | P89: 0 | S89: 0 | T89: 0 | U89: =T89*5% -> 0 | V89: =T89+U89 -> 0 | W89: BTPC
A90: 88 | B90: 21.06.21 | C90: 88 | D90: 449 | E90: 161001665 | F90: 59 | G90: 3217.53 | H90: 615.47 | I90: 0 | J90: 0 | K90: 0 | L90: 2 | M90: 15 | N90: 0 | O90: 0 | P90: 0 | S90: 0 | T90: 0 | U90: =T90*5% -> 0 | V90: =T90+U90 -> 0 | W90: PSPM
A91: 89 | B91: 22.06.21 | C91: 89 | D91: 450 | E91: 161001666 | F91: 57 | G91: 3231.13 | H91: 473.87 | I91: 0 | J91: 0 | K91: 0 | L91: 1 | M91: 55 | N91: 0 | O91: 0 | P91: 0 | S91: 0 | T91: 0 | U91: =T91*5% -> 0 | V91: =T91+U91 -> 0 | W91: BTPC
A92: 90 | B92: 22.06.21 | C92: 90 | D92: 451 | E92: 161001667 | F92: 59 | G92: 3296.31 | H92: 538.69 | I92: 0 | J92: 0 | K92: 0 | L92: 1 | M92: 40 | N92: 0 | O92: 0 | P92: 0 | S92: 0 | T92: 0 | U92: =T92*5% -> 0 | V92: =T92+U92 -> 0 | W92: PSPM
A93: 91 | B93: 22.06.21 | C93: 91 | D93: 452 | E93: 161001668 | F93: 58 | G93: 3243.26 | H93: 522.74 | I93: 0 | J93: 0 | K93: 0 | L93: 1 | M93: 45 | N93: 0 | O93: 0 | P93: 0 | S93: 0 | T93: 0 | U93: =T93*5% -> 0 | V93: =T93+U93 -> 0 | W93: BTPC
